Workbook

Sheet BalansenWinstverlies - FY2018
A1: CodeAdministratie | B1: NaamAdministratie | C1: CodeDimensietype | D1: NaamDimensietype | E1: CodeRapportagestructuurgroep1 | F1: NaamRapportagestructuurgroep2 | G1: CodeRapportagestructuurgroep3 | H1: NaamRapportagestructuurgroep4 | I1: CodeRapportagestructuurgroep5 | J1: NaamRapportagestructuurgroep6 | K1: CodeGrootboekrekening | L1: NaamGrootboekrekening | M1: Saldo
A2: 041066359000 | B2: QSP ESS B.V. | C2: BAS | D2: Balans | E2: GLB15 | F2: Vastgoedbeleggingen | G2: SLB2510 | H2: Vastgoedbeleggingen | K2: 1600000 | L2: VG Vastgoedbeleggingen Verkrijgings- of vervaardigingsprijs | M2: 1.3492958e+08
A3: 041066359000 | B3: QSP ESS B.V. | C3: BAS | D3: Balans | E3: GLB15 | F3: Vastgoedbeleggingen | G3: SLB2510 | H3: Vastgoedbeleggingen | K3: 1600200 | L3: VG Vastgoedbeleggingen Cum afschrijvingen en waardeverm | M3: -8089661.7
A4: 041066359000 | B4: QSP ESS B.V. | C4: BAS | D4: Balans | E4: GLB15 | F4: Vastgoedbeleggingen | G4: SLB2510 | H4: Vastgoedbeleggingen | K4: 1610803 | L4: VG Comm VG in exploitatie Buitengebruikstellingen aanschaffingswaarde | M4: -2341968
A5: 041066359000 | B5: QSP ESS B.V. | C5: BAS | D5: Balans | E5: GLB20 | F5: Financiële vaste activa | G5: SLB2020 | H5: Overige deelneming | K5: 1710004 | L5: FVA Deelneming VvE portefeuille Vivare II | M5: -0.24
A6: 041066359000 | B6: QSP ESS B.V. | C6: BAS | D6: Balans | E6: GLB20 | F6: Financiële vaste activa | G6: SLB2100 | H6: Overige vorderingen | K6: 1790002 | L6: FVA Latente belastingvordering langlopend | M6: 2022416.4
A7: 041066359000 | B7: QSP ESS B.V. | C7: BAS | D7: Balans | E7: GLB40 | F7: Vorderingen | G7: SLB4010 | H7: Debiteuren | K7: 2000000 | L7: VOR Debiteuren | M7: 171593.69
A8: 041066359000 | B8: QSP ESS B.V. | C8: BAS | D8: Balans | E8: GLB40 | F8: Vorderingen | G8: SLB4010 | H8: Debiteuren | K8: 2000300 | L8: VOR Voorziening dubieuze debiteuren | M8: -14000
A9: 041066359000 | B9: QSP ESS B.V. | C9: BAS | D9: Balans | E9: GLB40 | F9: Vorderingen | G9: SLB4076 | H9: Rekening-courant aandeelhouder | K9: 2640000 | L9: RC Kortlopend DMRRP INV - I BV | M9: 110497
A10: 041066359000 | B10: QSP ESS B.V. | C10: BAS | D10: Balans | E10: GLB40 | F10: Vorderingen | G10: SLB4076 | H10: Rekening-courant aandeelhouder | K10: 2640001 | L10: RC Kortlopend QSPESS Limited | M10: 0
A11: 041066359000 | B11: QSP ESS B.V. | C11: BAS | D11: Balans | E11: GLB40 | F11: Vorderingen | G11: SLB4080 | H11: Overige vorderingen en overlopende activa | K11: 2040700 | L11: VOR Vooruitbetaalde servicekosten | M11: 0
A12: 041066359000 | B12: QSP ESS B.V. | C12: BAS | D12: Balans | E12: GLB40 | F12: Vorderingen | G12: SLB4080 | H12: Overige vorderingen en overlopende activa | K12: 2040900 | L12: VOR Vooruitbetaalde overige kosten | M12: 0
A13: 041066359000 | B13: QSP ESS B.V. | C13: BAS | D13: Balans | E13: GLB50 | F13: Liquide middelen | G13: SLB5020 | H13: Kruisposten | K13: 2300000 | L13: LM Kruisposten | M13: 0
... A33: 041066359000 | B33: QSP ESS B.V. | C33: BAS | D33: Balans | E33: GLB80 | F33: Kortlopende schulden | G33: SLB8025 | H33: Schulden aan lev en handelskred | K33: 2730001 | L33: KLS Crediteuren intercompany | M33: 0
A34: 041066359000 | B34: QSP ESS B.V. | C34: BAS | D34: Balans | E34: GLB80 | F34: Kortlopende schulden | G34: SLB8060 | H34: Belastingen en pensioen | I34: SLB80601 | J34: Omzetbelasting | K34: 2512100 | L34: BEL Afgedragen/ontvangen BTW | M34: -6845.46
A35: 041066359000 | B35: QSP ESS B.V. | C35: BAS | D35: Balans | E35: GLB80 | F35: Kortlopende schulden | G35: SLB8060 | H35: Belastingen en pensioen | I35: SLB80603 | J35: Vennootschapsbelasting | K35: 2530000 | L35: BEL Te betalen vennootschapsbelasting | M35: 536277
A36: 041066359000 | B36: QSP ESS B.V. | C36: BAS | D36: Balans | E36: GLB80 | F36: Kortlopende schulden | G36: SLB8060 | H36: Belastingen en pensioen | I36: SLB80606 | J36: Overige belastingen | K36: 2550000 | L36: BEL Te betalen overige belastingen | M36: 0
A37: 041066359000 | B37: QSP ESS B.V. | C37: BAS | D37: Balans | E37: GLB80 | F37: Kortlopende schulden | G37: SLB8065 | H37: Overige schulden | K37: 2740300 | L37: KLS Te betalen waarborgsommen kortlopend | M37: -666513.99
A38: 041066359000 | B38: QSP ESS B.V. | C38: BAS | D38: Balans | E38: GLB80 | F38: Kortlopende schulden | G38: SLB8065 | H38: Overige schulden | K38: 2740500 | L38: KLS Te betalen accountants- en administratiekosten | M38: -22500
A39: 041066359000 | B39: QSP ESS B.V. | C39: BAS | D39: Balans | E39: GLB80 | F39: Kortlopende schulden | G39: SLB8065 | H39: Overige schulden | K39: 2740600 | L39: KLS Te betalen rente | M39: 0
A40: 041066359000 | B40: QSP ESS B.V. | C40: BAS | D40: Balans | E40: GLB80 | F40: Kortlopende schulden | G40: SLB8065 | H40: Overige schulden | K40: 2741000 | L40: KLS Te betalen servicekosten | M40: -18117.02
A41: 041066359000 | B41: QSP ESS B.V. | C41: BAS | D41: Balans | E41: GLB80 | F41: Kortlopende schulden | G41: SLB8065 | H41: Overige schulden | K41: 2741001 | L41: KLS Te betalen exploitatiekosten | M41: 0
A42: 041066359000 | B42: QSP ESS B.V. | C42: BAS | D42: Balans | E42: GLB80 | F42: Kortlopende schulden | G42: SLB8065 | H42: Overige schulden | K42: 2741002 | L42: KLS Te betalen VVE | M42: 0
A43: 041066359000 | B43: QSP ESS B.V. | C43: BAS | D43: Balans | E43: GLB80 | F43: Kortlopende schulden | G43: SLB8065 | H43: Overige schulden | K43: 2741003 | L43: KLS Te betalen Wieglia | M43: 0
A44: 041066359000 | B44: QSP ESS B.V. | C44: BAS | D44: Balans | E44: GLB80 | F44: Kortlopende schulden | G44: SLB8065 | H44: Overige schulden | K44: 2741004 | L44: KLS Te betalen Hoen | M44: -40157.89
A45: 041066359000 | B45: QSP ESS B.V. | C45: BAS | D45: Balans | E45: GLB80 | F45: Kortlopende schulden | G45: SLB8065 | H45: Overige schulden | K45: 2741005 | L45: KLS Te betalen managementvergoedingen | M45: 0
A46: 041066359000 | B46: QSP ESS B.V. | C46: BAS | D46: Balans | E46: GLB80 | F46: Kortlopende schulden | G46: SLB8065 | H46: Overige schulden | K46: 2741200 | L46: KLS Te betalen overige kosten | M46: -5040
A47: 041066359000 | B47: QSP ESS B.V. | C47: BAS | D47: Balans | E47: GLB80 | F47: Kortlopende schulden | G47: SLB8065 | H47: Overige schulden | K47: 2741900 | L47: KLS Nog uit te zoeken posten MT940 | M47: 918.63
A48: 041066359000 | B48: QSP ESS B.V. | C48: BAS | D48: Balans | E48: GLB80 | F48: Kortlopende schulden | G48: SLB8065 | H48: Overige schulden | K48: 2742200 | L48: KLS Vooruitontvangen bedragen | M48: -146910.69
... A59: 041066359000 | B59: QSP ESS B.V. | C59: PNL | D59: Winst & verlies | E59: GLP20 | F59: Bedrijfslasten | G59: SLP2025 | H59: Overige personeelskosten | K59: 4051400 | L59: KN Diensten door derden | M59: 472384.16
A60: 041066359000 | B60: QSP ESS B.V. | C60: PNL | D60: Winst & verlies | E60: GLP20 | F60: Bedrijfslasten | G60: SLP2030 | H60: Afschrijvingen | I60: SLP20303 | J60: Afschrijvingen VG | K60: 4730000 | L60: AFKN Afschrijvingskosten Vastgoedbeleggingen | M60: 2698591.7
A61: 041066359000 | B61: QSP ESS B.V. | C61: PNL | D61: Winst & verlies | E61: GLP20 | F61: Bedrijfslasten | G61: SLP2030 | H61: Afschrijvingen | I61: SLP20303 | J61: Afschrijvingen VG | K61: 4730200 | L61: AFKN Boekresultaat Vastgoedbeleggingen | M61: -1219532
A62: 041066359000 | B62: QSP ESS B.V. | C62: PNL | D62: Winst & verlies | E62: GLP20 | F62: Bedrijfslasten | G62: SLP2040 | H62: Huisvestingskosten | K62: 4100400 | L62: KN Onderhoud gebouwen | M62: 1015338.5
A63: 041066359000 | B63: QSP ESS B.V. | C63: PNL | D63: Winst & verlies | E63: GLP20 | F63: Bedrijfslasten | G63: SLP2040 | H63: Huisvestingskosten | K63: 4100410 | L63: Verhuurdersheffing | M63: 568182
A64: 041066359000 | B64: QSP ESS B.V. | C64: PNL | D64: Winst & verlies | E64: GLP20 | F64: Bedrijfslasten | G64: SLP2040 | H64: Huisvestingskosten | K64: 4100900 | L64: KN Onroerende zaakbelasting | M64: 316136.1
A65: 041066359000 | B65: QSP ESS B.V. | C65: PNL | D65: Winst & verlies | E65: GLP20 | F65: Bedrijfslasten | G65: SLP2040 | H65: Huisvestingskosten | K65: 4101000 | L65: KN VvE-kosten | M65: 630780.63
A66: 041066359000 | B66: QSP ESS B.V. | C66: PNL | D66: Winst & verlies | E66: GLP20 | F66: Bedrijfslasten | G66: SLP2040 | H66: Huisvestingskosten | K66: 4101010 | L66: Gemeentelijke belastingen | M66: 1026.53
A67: 041066359000 | B67: QSP ESS B.V. | C67: PNL | D67: Winst & verlies | E67: GLP20 | F67: Bedrijfslasten | G67: SLP2040 | H67: Huisvestingskosten | K67: 4101020 | L67: Waterschapsbelasting | M67: 116470.82
A68: 041066359000 | B68: QSP ESS B.V. | C68: PNL | D68: Winst & verlies | E68: GLP20 | F68: Bedrijfslasten | G68: SLP2040 | H68: Huisvestingskosten | K68: 4101400 | L68: KN Kosten vereniging van eigenaren | M68: 0
A69: 041066359000 | B69: QSP ESS B.V. | C69: PNL | D69: Winst & verlies | E69: GLP20 | F69: Bedrijfslasten | G69: SLP2050 | H69: Verkoopkosten | K69: 4501300 | L69: KN Afboeking dubieuze debiteuren | M69: 1215.23
A70: 041066359000 | B70: QSP ESS B.V. | C70: PNL | D70: Winst & verlies | E70: GLP20 | F70: Bedrijfslasten | G70: SLP2060 | H70: Kantoorkosten | K70: 4300500 | L70: KN Incassokosten | M70: 45372.76
A71: 041066359000 | B71: QSP ESS B.V. | C71: PNL | D71: Winst & verlies | E71: GLP20 | F71: Bedrijfslasten | G71: SLP2065 | H71: Algemene kosten | K71: 4310400 | L71: KN Assurantiepremie algemeen | M71: 85028.99
A72: 041066359000 | B72: QSP ESS B.V. | C72: PNL | D72: Winst & verlies | E72: GLP20 | F72: Bedrijfslasten | G72: SLP2065 | H72: Algemene kosten | K72: 4310500 | L72: KN Managementvergoeding | M72: 16335
A73: 041066359000 | B73: QSP ESS B.V. | C73: PNL | D73: Winst & verlies | E73: GLP20 | F73: Bedrijfslasten | G73: SLP2065 | H73: Algemene kosten | K73: 4310600 | L73: KN Accountantskosten | M73: 122608.27
... A79: 041066359000 | B79: QSP ESS B.V. | C79: PNL | D79: Winst & verlies | E79: GLP20 | F79: Bedrijfslasten | G79: SLP2065 | H79: Algemene kosten | K79: 4319800 | L79: KN Overige algemene kosten | M79: -24.33
A80: 041066359000 | B80: QSP ESS B.V. | C80: PNL | D80: Winst & verlies | E80: GLP25 | F80: Financiële baten en lasten | G80: GLP30 | H80: Andere rentebaten/-lasten en soortgelijken opbrengsten/kosten | I80: SLP3025 | J80: Overige rentelasten | K80: 4623000 | L80: FINBL Rente ABN AMRO Bank NV leningen | M80: 832383.46
A81: 041066359000 | B81: QSP ESS B.V. | C81: PNL | D81: Winst & verlies | E81: GLP25 | F81: Financiële baten en lasten | G81: GLP30 | H81: Andere rentebaten/-lasten en soortgelijken opbrengsten/kosten | I81: SLP3025 | J81: Overige rentelasten | K81: 4623001 | L81: FINBL Rente ABN AMRO Bank NV Senior Facility Agreement | M81: 2477628.5
A82: 041066359000 | B82: QSP ESS B.V. | C82: PNL | D82: Winst & verlies | E82: GLP25 | F82: Financiële baten en lasten | G82: GLP30 | H82: Andere rentebaten/-lasten en soortgelijken opbrengsten/kosten | I82: SLP3025 | J82: Overige rentelasten | K82: 4628001 | L82: FINBL Rente LLS QSPESS Limited | M82: 872526.94
A83: 041066359000 | B83: QSP ESS B.V. | C83: PNL | D83: Winst & verlies | E83: GLP25 | F83: Financiële baten en lasten | G83: GLP30 | H83: Andere rentebaten/-lasten en soortgelijken opbrengsten/kosten | I83: SLP3025 | J83: Overige rentelasten | K83: 4630000 | L83: FINBL Rente belastingen | M83: 18603
A84: 041066359000 | B84: QSP ESS B.V. | C84: PNL | D84: Winst & verlies | E84: GLP25 | F84: Financiële baten en lasten | G84: GLP30 | H84: Andere rentebaten/-lasten en soortgelijken opbrengsten/kosten | I84: SLP3025 | J84: Overige rentelasten | K84: 4643000 | L84: FINBL Overige rentelasten | M84: 337456.51
A85: 041066359000 | B85: QSP ESS B.V. | C85: PNL | D85: Winst & verlies | E85: GLP55 | F85: Belastingen | G85: SLP5520 | H85: Mutatie belastinglatentie | K85: 9510000 | L85: VPB Mutatie belastinglatentie Mutatie actieve latentie | M85: -674648.44

Sheet Cijfers QSP - Q1 2019
C2: Beginbalans (01-04-2018) | E2: Balans per 30-06-2018 | H2: Balans per 30-09-2018 | K2: Balans per 31-12-2018 | P2: Balans per 31-03-2019
A3: Balans
A4: 1600000 | B4: VG Vastgoedbeleggingen Verkrijgings- of vervaardigingsprijs | C4: 1.3492958e+08 | E4: =C4 -> 1.3492958e+08 | H4: =E4 -> 1.3492958e+08 | K4: 1.3492958e+08 | P4: 134929585
A5: 1600200 | B5: VG Vastgoedbeleggingen Cum afschrijvingen en waardeverm | C5: -6065717.9 | E5: =C5-556672.89 -> -6622390.8 | H5: =E5-556672.89 -> -7179063.7 | K5: -8089661.7 | P5: -8764309.7
A6: 1610803 | B6: VG Comm VG in exploitatie Buitengebruikstellingen aanschaffingswaarde | K6: -2341968 | P6: -2967534
A7: Totaal Vastgoedbeleggingen | C7: =SUM(C4:C6) -> 1.2886387e+08 | E7: =SUM(E4:E6) -> 1.2830719e+08 | H7: =SUM(H4:H6) -> 1.2775052e+08 | K7: =SUM(K4:K6) -> 1.2449795e+08 | P7: =SUM(P4:P6) -> 1.2319774e+08
A9: 1790002 | B9: FVA Latente belastingvordering langlopend | C9: 1516430 | E9: =C9 -> 1516430 | H9: =E9+139168.22 -> 1655598.2 | K9: 2051910.2 | P9: 2220572.2
A10: Totaal Financiële vaste activa | C10: =SUM(C9) -> 1516430 | E10: =SUM(E9) -> 1516430 | H10: =SUM(H9) -> 1655598.2 | K10: =SUM(K9) -> 2051910.2 | P10: =SUM(P9) -> 2220572.2
A12: 2000000 | B12: VOR Debiteuren | C12: 101970.5 | E12: =C12+142289.81 -> 244260.31 | H12: =E12+271621.52 -> 515881.83 | K12: 171593.69 | P12: 329178.26
A13: 2000300 | B13: VOR Voorziening dubieuze debiteuren | C13: -14000 | E13: =C13 -> -14000 | H13: =E13 -> -14000 | K13: -14000 | P13: -14000
A14: Totaal Debiteuren | C14: =SUM(C12:C13) -> 87970.5 | E14: =SUM(E12:E13) -> 230260.31 | H14: =SUM(H12:H13) -> 501881.83 | K14: =SUM(K12:K13) -> 157593.69 | P14: =SUM(P12:P13) -> 315178.26
A16: 2040700 | B16: VOR Vooruitbetaalde servicekosten | C16: 29258.85 | E16: 0 | H16: 0 | K16: 0 | P16: 0
A17: 2040900 | B17: VOR Vooruitbetaalde overige kosten | C17: 51218.7 | E17: 0 | H17: 0 | K17: 0 | P17: 0
A18: Totaal Overige vorderingen en overlopende activa | C18: =SUM(C16:C17) -> 80477.55 | E18: =SUM(E16:E17) -> 0 | H18: =SUM(H16:H17) -> 0 | K18: =SUM(K16:K17) -> 0 | P18: =SUM(P16:P17) -> 0
A20: 2640000 | B20: RC Kortlopend DMRRP INV - I BV | C20: 510497 | E20: =C20-400000 -> 110497 | H20: =E20 -> 110497 | K20: 110497 | P20: 110497
A21: Totaal Rekening-courant aandeelhouder | C21: =C20 -> 510497 | E21: =E20 -> 110497 | H21: =H20 -> 110497 | K21: =K20 -> 110497 | P21: =P20 -> 110497
A23: 2300000 | B23: LM Kruisposten | C23: 0 | E23: 0 | H23: 0 | K23: 0 | P23: 671.55
A24: 2400200 | B24: LM ABN AMRO Bank Disposal NL58 ABNA 0818 9180 39 | C24: 0 | E24: 985.82 | H24: =E24+2403985.53 -> 2404971.3 | K24: 986584.53 | P24: 538961.82
A25: 2400201 | B25: LM ABN AMRO Bank Deposit NL57 ABNA 0541 6205 68 | C25: 17365.7 | E25: =C25+101804.22 -> 119169.92 | H25: =E25-101349.86 -> 17820.06 | K25: 9648.09 | P25: 1369615.4
A26: 2400202 | B26: LM ABN AMRO Bank General NL93 ABNA 0541 6132 27 | C26: 116513.7 | E26: =C26-9646.52 -> 106867.18 | H26: =E26-83687.36 -> 23179.82 | K26: 191789.66 | P26: 1034628.1
A27: 2400203 | B27: LM ABN AMRO Bank Maintres NL04 ABNA 0541 6188 06 | C27: 12.23 | E27: =C27+654441.82 -> 654454.05 | H27: =E27-219333.49 -> 435120.56 | K27: 491535.05 | P27: 601349.86
A28: 2400204 | B28: LM ABN AMRO Bank Rent NL46 ABNA 0541 6088 35 | C28: 290930.72 | E28: =C28-416085.32 -> -125154.6 | H28: =E28+374178.16 -> 249023.56 | K28: 415424.01 | P28: 499735.95
A29: 2400205 | B29: LM ABN AMRO Bank SR EXP NL88 ABNA 0541 6205 92 | C29: 10983.92 | E29: =C29+200327.39 -> 211311.31 | H29: =E29-61914.41 -> 149396.9 | K29: 275171.2 | P29: 58139.79
A30: Totaal Liquide middelen | C30: =SUM(C23:C29) -> 435806.27 | E30: =SUM(E23:E29) -> 967633.68 | H30: =SUM(H23:H29) -> 3279512.2 | K30: =SUM(K23:K29) -> 2370152.5 | P30: =SUM(P23:P29) -> 4103102.5
A32: 1000002 | B32: EV Normale aandelen Saldo | C32: -1 | E32: =C32 -> -1 | H32: =E32 -> -1 | K32: -1 | P32: -1
A33: 1100000 | B33: EV Agioreserve Agio aandelen | C33: -19431219 | E33: =C33 -> -19431219 | H33: =E33 -> -19431219 | K33: -19431219 | P33: -19431219
A34: 1160000 | B34: EV Overige reserve Reserve aandelen | C34: =9890198.2+417450.68 -> 10307649 | E34: =C34 -> 10307649 | H34: =E34 -> 10307649 | K34: 9890198.2 | P34: 16135048
A35: 1160100 | B35: EV Overige reserve Dividenduitkeringen aandelen | C35: 0 | E35: 7497104.1 | H35: 7497104.1 | K35: 7727104.1 | P35: 310000
A36: Totaal Eigen vermogen | C36: =SUM(C32:C35) -> -9123571.6 | E36: =SUM(E32:E35) -> -1626467.5 | H36: =SUM(H32:H35) -> -1626467.5 | K36: =SUM(K32:K35) -> -1813918.2 | P36: =SUM(P32:P35) -> -2986172.5
P37: 0
A38: 1930000 | B38: LLS Hoofdsom ABN AMRO Bank NV leningen | C38: -86326750 | E38: 0 | H38: 0 | K38: 0 | P38: -130000000
A39: 1930001 | B39: LLS Hoofdsom ABN AMRO Bank NV Senior Facility Agreement | C39: 0 | E39: -130000000 | H39: -130000000 | K39: -130000000 | P39: 0
A40: 1930100 | B40: LLS Cum aflossingen ABN AMRO Bank NV leningen | C40: 759062.18 | E40: 0 | H40: 0 | K40: 0 | P40: 5070232.5
A41: 1930101 | B41: LLS Cum aflossingen ABN AMRO Bank NV Senior Facility Agreement | C41: 0 | E41: 812500 | H41: =E41+812500 -> 1625000 | K41: 5070232.5 | P41: 0
A42: 1930201 | B42: LLS Kortlopend deel ABN AMRO Bank NV Senior Facility Agreement | C42: 0 | E42: =C42 -> 0 | H42: =E42 -> 0 | K42: -306833.59
P43: 0
A44: 1990001 | B44: LLS Hoofdsom QSPESS Limited | C44: -35257825 | E44: 0 | H44: 0 | K44: 0
A45: Totaal Langlopende schulden | C45: =SUM(C38:C44) -> -1.2082551e+08 | E45: =SUM(E38:E44) -> -129187500 | H45: =SUM(H38:H44) -> -128375000 | K45: =SUM(K38:K44) -> -1.252366e+08 | P45: =SUM(P38:P44) -> -1.2492977e+08
P46: -22162.98
A47: 2730000 | B47: KLS Crediteuren | C47: -143296.28 | E47: =C47+137851.28 -> -5445 | H47: =E47+5444.99 -> -0.01 | K47: -9075.01 | P47: 0
A48: 2730001 | B48: KLS Crediteuren intercompany | C48: 0 | E48: 5445 | H48: =E48-5445 -> 0 | K48: 0
A49: Totaal Crediteuren | C49: =SUM(C47:C48) -> -143296.28 | E49: =SUM(E47:E48) -> 0 | H49: =SUM(H47:H48) -> -0.01 | K49: =SUM(K47:K48) -> -9075.01 | P49: =SUM(P47:P48) -> 0
A51: 2511000 | B51: BEL BTW te vorderen hoog | C51: 0 | E51: =C51 -> 0 | H51: =E51 -> 0 | K51: 0 | P51: 4791.47
A52: 2512100 | B52: BEL Afgedragen/ontvangen BTW | C52: -4583 | E52: =C52-2003.99 -> -6586.99 | H52: =E52-248.2 -> -6835.19 | K52: -6845.46 | P52: -2695.96
A53: 2530000 | B53: BEL Te betalen vennootschapsbelasting | C53: -178576 | E53: =C53+396906 -> 218330 | H53: =E53+40582 -> 258912 | K53: 258912 | P53: 258912
A54: 2550000 | B54: BEL Te betalen overige belastingen | C54: 330803 | E54: =C54-330803 -> 0 | H54: 0 | K54: 0 | P54: 284637.87
A55: Totaal Belastingen | C55: =SUM(C51:C54) -> 147644 | E55: =SUM(E51:E54) -> 211743.01 | H55: =SUM(H51:H54) -> 252076.81 | K55: =SUM(K51:K54) -> 252066.54 | P55: =SUM(P51:P54) -> 545645.38
A57: 2740300 | B57: KLS Te betalen waarborgsommen kortlopend | C57: -615377.22 | E57: =C57-4490.01 -> -619867.23 | H57: =E57-14716.27 -> -634583.5 | K57: -666513.99 | P57: -678422.47
A58: 2740500 | B58: KLS Te betalen accountants- en administratiekosten | C58: -22500 | E58: =C58 -> -22500 | H58: =E58 -> -22500 | K58: -22500 | P58: -22500
A59: 2740600 | B59: KLS Te betalen rente | C59: -405058 | E59: =C59+405058 -> 0 | H59: =E59 -> 0 | K59: 0 | P59: -503883.39
A60: 2740700 | B60: KLS Te betalen verzekeringen | C60: 0 | E60: =C60 -> 0 | H60: =E60 -> 0 | K60: 0 | P60: 47711.56
A61: 2741000 | B61: KLS Te betalen servicekosten | C61: -93947.02 | E61: =C61+3500 -> -90447.02 | H61: =E61+63230 -> -27217.02 | K61: -18117.02 | P61: -9417.02
A62: 2741001 | B62: KLS Te betalen exploitatiekosten | C62: -238421.31 | E62: =C62+238421.31 -> 0 | H62: =E62 -> 0 | K62: 0 | P62: 0
A63: 2741002 | B63: KLS Te betalen VVE | C63: -4268.84 | E63: =C63+4268.84 -> 0 | H63: =E63 -> 0 | K63: 0 | P63: 0
A64: 2741003 | B64: KLS Te betalen Wieglia | C64: -10938.05 | E64: =C64+10938.05 -> 0 | H64: =E64 -> 0 | K64: 0 | P64: 0
A65: 2741004 | B65: KLS Te betalen Hoen | C65: -28081.34 | E65: =C65-11612.19 -> -39693.53 | H65: =E65-488.11 -> -40181.64 | K65: -40157.89 | P65: -80047.1
A66: 2741005 | B66: KLS Te betalen managementvergoedingen | C66: 0 | E66: =C66 -> 0 | H66: =E66 -> 0 | K66: 0 | P66: 0
A67: 2741200 | B67: KLS Te betalen overige kosten | C67: -5040 | E67: =C67 -> -5040 | H67: =E67 -> -5040 | K67: -5040 | P67: -5040
A68: 2741900 | B68: KLS Nog uit te zoeken posten MT940 | C68: 0 | E68: -5044.68 | H68: =E68+4404.2 -> -640.48 | K68: 918.63 | P68: -465.86
A69: 2742200 | B69: KLS Vooruitontvangen bedragen | C69: -126675.73 | E69: =C69+14685.03 -> -111990.7 | H69: =E69-5052.83 -> -117043.53 | K69: -146910.69 | P69: -120768.08
A70: 2749800 | B70: KLS Diverse overige schulden | C70: -3.66 | E70: =C70 -> -3.66 | H70: =E70 -> -3.66 | K70: -3.66 | P70: -3.66
A71: Totaal Overige schulden | C71: =SUM(C57:C70) -> -1550311.2 | E71: =SUM(E57:E70) -> -894586.82 | H71: =SUM(H57:H70) -> -847209.83 | K71: =SUM(K57:K70) -> -898324.62 | P71: =SUM(P57:P70) -> -1372836
A73: Winst- en verliesrekening (baten zijn positief, kosten negatief) | C73: Q1 - Actuals | E73: Q2 - Cumulatief | F73: Q2 - Actuals | H73: Q3 - Cumulatief | I73: Q3 - Actuals | K73: Q4 - Cumulatief | L73: Q4 - Actuals | M73: Check | P73: Q1 2019 - Actuals | R73: Q2-2018 tm Q1 2019
A74: 8000003 | B74: OPB Netto-omzet Theoretische huuropbrengsten | C74: =-(K74+-H74+-E74) -> -2686801.6 | E74: -5491757.3 | F74: =E74-C74 -> -2804955.7 | H74: -8311858.3 | I74: =H74-E74 -> -2820101.1 | K74: -11116814 | L74: =K74-H74 -> -2804955.7 | M74: =L74+I74+F74+C74 -> -11116814 | N74: =M74-K74 -> 0 | P74: -2797626.1 | R74: =P74+L74+I74+F74 -> -11227639
A75: 8000004 | B75: OPB Netto-omzet Leegstand huuropbrengsten | C75: =-(K75+-H75+-E75) -> 69696.13 | E75: 138590.8 | F75: =E75-C75 -> 68894.67 | H75: 238421.04 | I75: =H75-E75 -> 99830.24 | K75: 307315.71 | L75: =K75-H75 -> 68894.67 | M75: =L75+I75+F75+C75 -> 307315.71 | N75: =M75-K75 -> 0 | P75: 69244.36 | R75: =P75+L75+I75+F75 -> 306863.94
A76: Totaal Netto-omzet | C76: =-(K76+-H76+-E76) -> -2617105.4 | E76: -5353166.5 | F76: =E76-C76 -> -2736061 | H76: -8073437.3 | I76: =H76-E76 -> -2720270.8 | K76: -10809498 | L76: =K76-H76 -> -2736061 | M76: =L76+I76+F76+C76 -> -10809498 | N76: =M76-K76 -> 0 | P76: -2728381.7 | R76: =P76+L76+I76+F76 -> -10920775
C77: =-(K77+-H77+-E77) -> 0 | F77: =E77-C77 -> 0 | I77: =H77-E77 -> 0 | L77: =K77-H77 -> 0 | M77: =L77+I77+F77+C77 -> 0 | N77: =M77-K77 -> 0 | R77: =P77+L77+I77+F77 -> 0
A78: 8400600 | B78: OPB Overige bedrijfsopbrengsten Totale servicekosten | C78: =-(K78+-H78+-E78) -> -199833.59 | E78: -360058.39 | F78: =E78-C78 -> -160224.8 | H78: -521030.18 | I78: =H78-E78 -> -160971.79 | J78: =I78+L78 -> -321196.59 | K78: -681254.98 | L78: =K78-H78 -> -160224.8 | M78: =L78+I78+F78+C78 -> -681254.98 | N78: =M78-K78 -> 0 | P78: -174607.96 | R78: =P78+L78+I78+F78 -> -656029.35
A79: 8400700 | B79: OPB Overige bedrijfsopbrengsten Servicekosten leegstand | C79: =-(K79+-H79+-E79) -> -7260.69 | E79: 12394.03 | F79: =E79-C79 -> 19654.72 | H79: 54417.25 | I79: =H79-E79 -> 42023.22 | J79: =I79+L79 -> 61677.94 | K79: 74071.97 | L79: =K79-H79 -> 19654.72 | M79: =L79+I79+F79+C79 -> 74071.97 | N79: =M79-K79 -> 0 | P79: 10049.7 | R79: =P79+L79+I79+F79 -> 91382.36
A80: 8400800 | B80: OPB Overige bedrijfsopbrengsten Gerealiseerde servicekosten | C80: =-(K80+-H80+-E80) -> 135161.27 | E80: 284906.44 | F80: =E80-C80 -> 149745.17 | H80: 411383.19 | I80: =H80-E80 -> 126476.75 | J80: =I80+L80 -> 276221.92 | K80: 561128.36 | L80: =K80-H80 -> 149745.17 | M80: =L80+I80+F80+C80 -> 561128.36 | N80: =M80-K80 -> 0 | P80: 173160.71 | R80: =P80+L80+I80+F80 -> 599127.8
A81: Totaal Overige bedrijfsopbrengsten | C81: =-(K81+-H81+-E81) -> -71933.01 | E81: -62757.92 | F81: =E81-C81 -> 9175.09 | H81: -55229.74 | I81: =H81-E81 -> 7528.18 | J81: =I81+L81 -> 16703.27 | K81: -46054.65 | L81: =K81-H81 -> 9175.09 | M81: =L81+I81+F81+C81 -> -46054.65 | N81: =M81-K81 -> 0 | P81: 8602.45 | R81: =P81+L81+I81+F81 -> 34480.81
C82: =-(K82+-H82+-E82) -> 0 | F82: =E82-C82 -> 0 | I82: =H82-E82 -> 0 | L82: =K82-H82 -> 0 | M82: =L82+I82+F82+C82 -> 0 | N82: =M82-K82 -> 0 | R82: =P82+L82+I82+F82 -> 0
A83: 7000000 | B83: KP Inkoopwaarde omzet | C83: =-(K83+-H83+-E83) -> 0 | E83: 0 | F83: =E83-C83 -> 0 | H83: 0 | I83: =H83-E83 -> 0 | K83: 0 | L83: =K83-H83 -> 0 | M83: =L83+I83+F83+C83 -> 0 | N83: =M83-K83 -> 0 | P83: 0 | R83: =P83+L83+I83+F83 -> 0
A84: Totaal Inkoopwaarde omzet | C84: =-(K84+-H84+-E84) -> 0 | E84: 0 | F84: =E84-C84 -> 0 | H84: 0 | I84: =H84-E84 -> 0 | K84: 0 | L84: =K84-H84 -> 0 | M84: =L84+I84+F84+C84 -> 0 | N84: =M84-K84 -> 0 | P84: 0 | R84: =P84+L84+I84+F84 -> 0
C85: =-(K85+-H85+-E85) -> 0 | F85: =E85-C85 -> 0 | I85: =H85-E85 -> 0 | L85: =K85-H85 -> 0 | M85: =L85+I85+F85+C85 -> 0 | N85: =M85-K85 -> 0 | R85: =P85+L85+I85+F85 -> 0
A86: 4730000 | B86: AFKN Afschrijvingskosten Vastgoedbeleggingen | C86: =-(K86+-H86+-E86) -> 320722.78 | E86: 1231320.8 | F86: =E86-C86 -> 910598 | H86: 1787993.7 | I86: =H86-E86 -> 556672.89 | K86: 2698591.7 | L86: =K86-H86 -> 910598 | M86: =L86+I86+F86+C86 -> 2698591.7 | N86: =M86-K86 -> 0 | P86: 674648 | R86: =P86+L86+I86+F86 -> 3052516.9
A87: 4730200 | B87: AFKN Boekresultaat Vastgoedbeleggingen | C87: =-(K87+-H87+-E87) -> -1753968 | E87: -139500 | F87: =E87-C87 -> 1614468 | H87: -2834000 | I87: =H87-E87 -> -2694500 | K87: -1219532 | L87: =K87-H87 -> 1614468 | M87: =L87+I87+F87+C87 -> -1219532 | N87: =M87-K87 -> 0 | P87: -393684 | R87: =M87+P87 -> -1613216
A88: Totaal Afschrijvingen vastgoedbeleggingen | C88: =-(K88+-H88+-E88) -> -1433245.2 | E88: 1091820.8 | F88: =E88-C88 -> 2525066 | H88: -1046006.3 | I88: =H88-E88 -> -2137827.1 | K88: 1479059.7 | L88: =K88-H88 -> 2525066 | M88: =L88+I88+F88+C88 -> 1479059.7 | N88: =M88-K88 -> 0 | P88: 280964 | R88: =P88+L88+I88+F88 -> 3193268.9
C89: =-(K89+-H89+-E89) -> 0 | F89: =E89-C89 -> 0 | I89: =H89-E89 -> 0 | L89: =K89-H89 -> 0 | M89: =L89+I89+F89+C89 -> 0 | N89: =M89-K89 -> 0 | R89: =P89+L89+I89+F89 -> 0
A90: 4100400 | B90: KN Onderhoud gebouwen | C90: =-(K90+-H90+-E90) -> -12721.67 | E90: 375194.12 | F90: =E90-C90 -> 387915.79 | H90: 627422.75 | I90: =H90-E90 -> 252228.63 | K90: 1015338.5 | L90: =K90-H90 -> 387915.79 | M90: =L90+I90+F90+C90 -> 1015338.5 | N90: =M90-K90 -> 0 | P90: 292677.44 | R90: =P90+L90+I90+F90 -> 1320737.6
A91: 4100410 | B91: Verhuurdersheffing | C91: =-(K91+-H91+-E91) -> 0 | E91: 0 | F91: =E91-C91 -> 0 | H91: 568182 | I91: =H91-E91 -> 568182 | K91: 568182 | L91: =K91-H91 -> 0 | M91: =L91+I91+F91+C91 -> 568182 | N91: =M91-K91 -> 0 | P91: 0 | R91: =P91+L91+I91+F91 -> 568182
A92: 4100900 | B92: KN Onroerende zaakbelasting | C92: =-(K92+-H92+-E92) -> 317786.92 | E92: 318063.49 | F92: =E92-C92 -> 276.57 | H92: 315859.53 | I92: =H92-E92 -> -2203.96 | K92: 316136.1 | L92: =K92-H92 -> 276.57 | M92: =L92+I92+F92+C92 -> 316136.1 | N92: =M92-K92 -> 0 | P92: 98935.71 | R92: =P92+L92+I92+F92 -> 97284.89
A93: 4101000 | B93: KN VvE-kosten | C93: =-(K93+-H93+-E93) -> 210601.81 | E93: 327503.56 | F93: =E93-C93 -> 116901.75 | H93: 513878.88 | I93: =H93-E93 -> 186375.32 | K93: 630780.63 | L93: =K93-H93 -> 116901.75 | M93: =L93+I93+F93+C93 -> 630780.63 | N93: =M93-K93 -> 0 | P93: 132836.8 | R93: =P93+L93+I93+F93 -> 553015.62
A94: 4101010 | B94: Gemeentelijke belastingen | C94: =-(K94+-H94+-E94) -> 755.39 | E94: 890.96 | F94: =E94-C94 -> 135.57 | H94: 890.96 | I94: =H94-E94 -> 0 | K94: 1026.53 | L94: =K94-H94 -> 135.57 | M94: =L94+I94+F94+C94 -> 1026.53 | N94: =M94-K94 -> 0 | P94: 29292.78 | R94: =P94+L94+I94+F94 -> 29563.92
A95: 4101020 | B95: Waterschapsbelasting | C95: =-(K95+-H95+-E95) -> 91866.47 | E95: 93200.16 | F95: =E95-C95 -> 1333.69 | H95: 115137.13 | I95: =H95-E95 -> 21936.97 | K95: 116470.82 | L95: =K95-H95 -> 1333.69 | M95: =L95+I95+F95+C95 -> 116470.82 | N95: =M95-K95 -> 0 | P95: 3342.08 | R95: =P95+L95+I95+F95 -> 27946.43
A96: 4101300 | B96: KN Servicekosten leegstand | C96: =-(K96+-H96+-E96) -> 0 | E96: 0 | F96: =E96-C96 -> 0 | H96: 0 | I96: =H96-E96 -> 0 | K96: 0 | L96: =K96-H96 -> 0 | M96: =L96+I96+F96+C96 -> 0 | N96: =M96-K96 -> 0 | P96: -1.35 | R96: =P96+L96+I96+F96 -> -1.35
A97: 4051400 | B97: KN Diensten door derden | C97: =-(K97+-H97+-E97) -> 114268.16 | E97: 233501.76 | F97: =E97-C97 -> 119233.6 | H97: 353150.56 | I97: =H97-E97 -> 119648.8 | K97: 472384.16 | L97: =K97-H97 -> 119233.6 | M97: =L97+I97+F97+C97 -> 472384.16 | N97: =M97-K97 -> 0 | P97: 119182.54 | R97: =P97+L97+I97+F97 -> 477298.54
A98: Totaal Huisvestingskosten | C98: =-(K98+-H98+-E98) -> 722557.08 | E98: 1348354 | F98: =E98-C98 -> 625796.97 | H98: 2494521.8 | I98: =H98-E98 -> 1146167.8 | K98: 3120318.8 | L98: =K98-H98 -> 625796.97 | M98: =L98+I98+F98+C98 -> 3120318.8 | N98: =M98-K98 -> 0 | P98: 676266 | R98: =P98+L98+I98+F98 -> 3074027.7
C99: =-(K99+-H99+-E99) -> 0 | F99: =E99-C99 -> 0 | I99: =H99-E99 -> 0 | L99: =K99-H99 -> 0 | M99: =L99+I99+F99+C99 -> 0 | N99: =M99-K99 -> 0 | R99: =P99+L99+I99+F99 -> 0
A100: 4501300 | B100: KN Afboeking dubieuze debiteuren | C100: =-(K100+-H100+-E100) -> 554.3 | E100: 575.05 | F100: =E100-C100 -> 20.75 | H100: 1194.48 | I100: =H100-E100 -> 619.43 | K100: 1215.23 | L100: =K100-H100 -> 20.75 | M100: =L100+I100+F100+C100 -> 1215.23 | N100: =M100-K100 -> 0 | P100: 13168.22 | R100: =P100+L100+I100+F100 -> 13829.15
A101: Totaal Verkoopkosten | C101: =-(K101+-H101+-E101) -> 554.3 | E101: 575.05 | F101: =E101-C101 -> 20.75 | H101: 1194.48 | I101: =H101-E101 -> 619.43 | K101: 1215.23 | L101: =K101-H101 -> 20.75 | M101: =L101+I101+F101+C101 -> 1215.23 | N101: =M101-K101 -> 0 | P101: 13168.22 | R101: =P101+L101+I101+F101 -> 13829.15
C102: =-(K102+-H102+-E102) -> 0 | F102: =E102-C102 -> 0 | I102: =H102-E102 -> 0 | L102: =K102-H102 -> 0 | M102: =L102+I102+F102+C102 -> 0 | N102: =M102-K102 -> 0 | R102: =P102+L102+I102+F102 -> 0
A103: 4300500 | B103: KN Incassokosten | C103: =-(K103+-H103+-E103) -> 41376.69 | E103: 41479.54 | F103: =E103-C103 -> 102.85 | H103: 45269.91 | I103: =H103-E103 -> 3790.37 | K103: 45372.76 | L103: =K103-H103 -> 102.85 | M103: =L103+I103+F103+C103 -> 45372.76 | N103: =M103-K103 -> 0 | P103: 450 | R103: =P103+L103+I103+F103 -> 4446.07
A104: Totaal Kantoorkosten | C104: =-(K104+-H104+-E104) -> 41376.69 | E104: 41479.54 | F104: =E104-C104 -> 102.85 | H104: 45269.91 | I104: =H104-E104 -> 3790.37 | K104: 45372.76 | L104: =K104-H104 -> 102.85 | M104: =L104+I104+F104+C104 -> 45372.76 | N104: =M104-K104 -> 0 | P104: 450 | R104: =P104+L104+I104+F104 -> 4446.07
C105: =-(K105+-H105+-E105) -> 0 | F105: =E105-C105 -> 0 | I105: =H105-E105 -> 0 | L105: =K105-H105 -> 0 | M105: =L105+I105+F105+C105 -> 0 | N105: =M105-K105 -> 0 | R105: =P105+L105+I105+F105 -> 0
A106: 4310400 | B106: KN Assurantiepremie algemeen | C106: =-(K106+-H106+-E106) -> 57729.26 | E106: 70171.39 | F106: =E106-C106 -> 12442.13 | H106: 72586.86 | I106: =H106-E106 -> 2415.47 | K106: 85028.99 | L106: =K106-H106 -> 12442.13 | M106: =L106+I106+F106+C106 -> 85028.99 | N106: =M106-K106 -> 0 | P106: 17390.79 | R106: =P106+L106+I106+F106 -> 44690.52
A107: 4310500 | B107: KN Managementvergoeding | C107: =-(K107+-H107+-E107) -> 0 | E107: 5445 | F107: =E107-C107 -> 5445 | H107: 10890 | I107: =H107-E107 -> 5445 | K107: 16335 | L107: =K107-H107 -> 5445 | M107: =L107+I107+F107+C107 -> 16335 | N107: =M107-K107 -> 0 | P107: 4500 | R107: =P107+L107+I107+F107 -> 20835
A108: 4310600 | B108: KN Accountantskosten | C108: =-(K108+-H108+-E108) -> 47553.61 | E108: 66268.05 | F108: =E108-C108 -> 18714.44 | H108: 103893.83 | I108: =H108-E108 -> 37625.78 | K108: 122608.27 | L108: =K108-H108 -> 18714.44 | M108: =L108+I108+F108+C108 -> 122608.27 | N108: =M108-K108 -> 0 | P108: 7500 | R108: =P108+L108+I108+F108 -> 82554.66
A109: 4310700 | B109: KN Administratiekosten | C109: =-(K109+-H109+-E109) -> 0 | E109: 1210 | F109: =E109-C109 -> 1210 | H109: 2420 | I109: =H109-E109 -> 1210 | K109: 3630 | L109: =K109-H109 -> 1210 | M109: =L109+I109+F109+C109 -> 3630 | N109: =M109-K109 -> 0 | P109: 1210 | R109: =P109+L109+I109+F109 -> 4840
A110: 4310800 | B110: KN Makelaarskosten | C110: =-(K110+-H110+-E110) -> -27336.77 | E110: 29277.71 | F110: =E110-C110 -> 56614.48 | H110: 100812.93 | I110: =H110-E110 -> 71535.22 | K110: 157427.41 | L110: =K110-H110 -> 56614.48 | M110: =L110+I110+F110+C110 -> 157427.41 | N110: =M110-K110 -> 0 | P110: 68270.43 | R110: =P110+L110+I110+F110 -> 253034.61
...

Sheet BDO - Q2 2019
C1: Mutaties Q1 2019 | D1: Mutaties Q2 2019 | E1: Saldi per 30-06-2019
A3: Balans | C3: 0 | D3: 0
A4: 1600000 | B4: VG Vastgoedbeleggingen Verkrijgings- of vervaardigingsprijs | C4: -662362 | D4: -650161 | E4: 132164783
A5: 1600200 | B5: VG Vastgoedbeleggingen Cum afschrijvingen en waardeverm | C5: -651550 | D5: -1011554 | E5: -10634612 | G5: =E5+E6+E83 -> -7636718
A6: 1610803 | B6: VG Comm VG in exploitatie Buitengebruikstellingen aanschaffingswaarde | C6: 41286 | D6: 71536 | E6: 233092
A7: Totaal Vastgoedbeleggingen | C7: =SUM(C3:C6) -> -1272626 | D7: =SUM(D3:D6) -> -1590179 | E7: 121763263
A9: 1710004 | B9: FVA Deelneming VvE Portefeuille Vivare II
A10: 1790002 | B10: FVA Latente belastingvordering langlopend | C10: 168662 | D10: 142232 | E10: 2706901
A11: Totaal Financiële vaste activa | D11: =SUM(D9:D10) -> 142232 | E11: 2706901
A13: 2000000 | B13: VOR Debiteuren | C13: 157585 | D13: 66045 | E13: 342834
A14: 2000300 | B14: VOR Voorziening dubieuze debiteuren | C14: 0 | D14: 0 | E14: -64501
A15: Totaal Debiteuren | C15: =SUM(C13:C14) -> 157585 | D15: =SUM(D13:D14) -> 66045 | E15: 278333
A17: 2040700 | B17: VOR Vooruitbetaalde servicekosten | C17: 0 | D17: 0 | E17: 15594
A18: 2040900 | B18: VOR Vooruitbetaalde overige kosten | C18: 0 | D18: 0 | E18: 737
A19: Totaal overige vorderingen | C19: =SUM(C17:C18) -> 0 | D19: =SUM(D17:D18) -> 0 | E19: 16331
A21: 2640000 | B21: RC Kortlopend DMRRP INV - I BV | C21: 0 | D21: 0 | E21: 110497
A22: Totaal Rekening-courant aandeelhouder | C22: =SUM(C21) -> 0 | D22: =SUM(D21) -> 0 | E22: 110497
A24: 2300000 | B24: LM Kruisposten | C24: 672 | D24: -672 | E24: 0
A25: 2400200 | B25: LM ABN AMRO Bank Disposal NL58 ABNA 0818 9180 39 | C25: -447623 | D25: -458920 | E25: 80042
A26: 2400201 | B26: LM ABN AMRO Bank Deposit NL57 ABNA 0541 6205 68 | C26: 1359967 | D26: -1368856 | E26: 759
A27: 2400202 | B27: LM ABN AMRO Bank General NL93 ABNA 0541 6132 27 | C27: 842838 | D27: -1028597 | E27: 6031
A28: 2400203 | B28: LM ABN AMRO Bank Maintres NL04 ABNA 0541 6188 06 | C28: 109815 | D28: 44887 | E28: 646236
A29: 2400204 | B29: LM ABN AMRO Bank Rent NL46 ABNA 0541 6088 35 | C29: 84312 | D29: 528567 | E29: 1028303
A30: 2400205 | B30: LM ABN AMRO Bank SR EXP NL88 ABNA 0541 6205 92 | C30: -217031 | D30: 58399 | E30: 116539
A31: Totaal Liquide middelen | C31: =SUM(C25:C30) -> 1732278 | D31: =SUM(D25:D30) -> -2224520 | E31: 1877910
A33: 1000002 | B33: EV Normale aandelen Saldo | C33: 0 | D33: 0 | E33: -1
A34: 1100000 | B34: EV Agioreserve Agio aandelen | C34: 0 | D34: 0 | E34: -19431219
A35: 1160000 | B35: EV Overige reserve Reserve aandelen | C35: 0 | D35: 0 | E35: 11244686
A36: 1160100 | B36: EV Overige reserve Dividenduitkeringen aandelen | C36: 310000 | D36: 225000 | E36: 8262104
A37: Totaal Eigen vermogen | C37: =SUM(C33:C36) -> 310000 | D37: =SUM(D33:D36) -> 225000 | E37: 75570
A39: 1930001 | B39: LLS Hoofdsom ABN AMRO Bank NV Senior Facility Agreement | C39: 0 | D39: 0 | E39: -130000000
A40: 1930101 | B40: LLS Cum aflossingen ABN AMRO Bank NV Senior Facility Agreement | C40: 0 | D40: 4692972 | E40: 9763205
A41: 1930201 | B41: LLS Kortlopend deel ABN AMRO Bank NV Senior Facility Agreement | C41: 306834 | D41: 0 | E41: 0
A42: Totaal Langlopende schulden | C42: =SUM(C39:C41) -> 306834 | D42: =SUM(D39:D41) -> 4692972 | E42: -120236795
A44: 2730000 | B44: KLS Crediteuren | C44: -18824 | D44: 27899 | E44: -167794
A45: 2730001 | B45: KLS Crediteuren intercompany | C45: 0 | D45: 0 | E45: 0
A46: Totaal Crediteuren | C46: =SUM(C44:C45) -> -18824 | D46: =SUM(D44:D45) -> 27899 | E46: -167794
A48: 2511000 | B48: BEL BTW te vorderen hoog | D48: 0 | E48: 0
A49: 2512100 | B49: BEL Afgedragen/ontvangen BTW | C49: 4150 | D49: 9 | E49: -3707
A50: 2530000 | B50: BEL Te betalen vennootschapsbelasting | C50: 0 | D50: -197342 | E50: -528792
A51: 2550000 | B51: BEL Te betalen overige belastingen | C51: 285682 | D51: -94879 | E51: 189758
A52: Totaal Belastingen | C52: =SUM(C48:C51) -> 289832 | D52: =SUM(D48:D51) -> -292212 | E52: -342741
A54: 2740300 | B54: KLS Te betalen waarborgsommen kortlopend | C54: -11908 | D54: -13448 | E54: -691871
A55: 2740500 | B55: KLS Te betalen accountants- en administratiekosten | C55: 0 | D55: 0 | E55: -22500
A56: 2740600 | B56: KLS Te betalen rente | C56: -503883 | D56: 503883 | E56: 0
A57: 2740700 | B57: KLS Te betalen verzekeringen | C57: 47712 | D57: -15904 | E57: 31808
A58: 2741000 | B58: KLS Te betalen servicekosten | C58: 8700 | D58: -8500 | E58: 0
A59: 2741001 | B59: KLS Te betalen exploitatiekosten | C59: 36832 | D59: 0 | E59: 0
A60: 2741002 | B60: KLS Te betalen VVE | C60: 675 | D60: 0 | E60: 0
A61: 2741003 | B61: KLS Te betalen Wieglia | C61: 0 | D61: 0 | E61: 0
A62: 2741004 | B62: KLS Te betalen Hoen | C62: -39889 | D62: 487 | E62: -79560
A63: 2741005 | B63: KLS Te betalen managementvergoedingen | C63: 0 | D63: 0 | E63: 0
A64: 2741200 | B64: KLS Te betalen overige kosten | C64: 13168 | D64: 0 | E64: 0
A65: 2741900 | B65: KLS Nog uit te zoeken posten MT940 | C65: -1384 | D65: 1385 | E65: 0
... A67: 2749800 | B67: KLS Diverse overige schulden | C67: 0 | D67: 0 | E67: 0
A68: Totaal Overige schulden | C68: =SUM(C54:C67) -> -423834 | D68: =SUM(D54:D67) -> 473113 | E68: -871541
A70: Winst- en verliesrekening (baten zijn positief, kosten negatief)
A71: 8000003 | B71: OPB Netto-omzet Theoretische huuropbrengsten | C71: -2797626 | D71: -2785968 | E71: -11207630
A72: 8000004 | B72: OPB Netto-omzet Leegstand huuropbrengsten | C72: 69244 | D72: 52029 | E72: 289999
A73: Totaal Netto-omzet | C73: =SUM(C71:C72) -> -2728382 | D73: =SUM(D71:D72) -> -2733939 | E73: -10917631
A75: 8400600 | B75: OPB Overige bedrijfsopbrengsten Totale servicekosten | C75: -174608 | D75: -175044 | E75: -670849
A76: 8400700 | B76: OPB Overige bedrijfsopbrengsten Servicekosten leegstand | C76: 10050 | D76: 8634 | E76: 80362
A77: 8400800 | B77: OPB Overige bedrijfsopbrengsten Gerealiseerde servicekosten | C77: 173161 | D77: 178493 | E77: 692047
A78: Totaal Overige bedrijfsopbrengsten | C78: =SUM(C75:C77) -> 8603 | D78: =SUM(D75:D77) -> 12083 | E78: 101560
A80: 4051400 | B80: Diensten door derden | C80: 119183 | D80: 118277 | E80: 476341
A81: Totaal overige personeelskosten | C81: =SUM(C80) -> 119183 | D81: =SUM(D80) -> 118277 | E81: 476341
A83: 4730000 | B83: AFKN Afschrijvingskosten Vastgoedbeleggingen | C83: 662362 | D83: 650161 | E83: 2764802
A84: 4730200 | B84: AFKN Boekresultaat Vastgoedbeleggingen | C84: -408986 | D84: -899982 | E84: -2592121
A85: Totaal Afschrijvingen vastgoedbeleggingen | C85: =SUM(C83:C84) -> 253376 | D85: =SUM(D83:D84) -> -249821 | E85: 172681
A87: 4100400 | B87: KN Onderhoud gebouwen | C87: 258876 | D87: 364950 | E87: 1378679
A88: 4100410 | B88: Verhuurdersheffing | C88: 0 | D88: 671 | E88: 568853
A89: 4100900 | B89: KN Onroerende zaakbelasting | C89: 97891 | D89: 82857 | E89: 179948
A90: 4101000 | B90: KN VvE-kosten | C90: 131618 | D90: 169899 | E90: 577286
A91: 4101010 | B91: Gemeentelijke belastingen | C91: 29293 | D91: 41233 | E91: 70662
A92: 4101020 | B92: Waterschapsbelasting | C92: 3342 | D92: 48209 | E92: 75164
A93: 4101300 | B93: KN Servicekosten leegstand | C93: -676 | D93: 41592 | E93: 42212
A94: 4109800 | B94: KN Overige huisvestingskosten | C94: 0 | D94: 39569 | E94: 39569
A95: Totaal Huisvestingskosten | C95: =SUM(C87:C94) -> 520344 | D95: =SUM(D87:D94) -> 788980 | E95: 2932373
A97: 4501200 | B97: KN Mutatie voorziening dubieuze debiteuren | C97: 0 | D97: 0 | E97: 50501
A98: 4501300 | B98: KN Afboeking dubieuze debiteuren | C98: 0 | D98: -800 | E98: 59258
A99: Totaal Verkoopkosten | C99: =SUM(C97:C98) -> 0 | D99: =SUM(D97:D98) -> -800 | E99: 109759 | G99: =E94+E101+E110+E112+E113+E104 -> 114029 | H99: =E99+G99 -> 223788
A101: 4300500 | B101: KN Incassokosten | C101: 837 | D101: 0 | E101: 4933
A102: Totaal Kantoorkosten | C102: =SUM(C101) -> 837 | D102: =SUM(D101) -> 0 | E102: 4933
A104: 4310000 | B104: KN Abonnementen en contributies | C104: 0 | D104: 4385 | E104: 4385
A105: 4310400 | B105: KN Assurantiepremie algemeen | C105: 18526 | D105: 28966 | E105: 63531
A106: 4310500 | B106: KN Managementvergoeding | C106: 5445 | D106: 5445 | E106: 21780
A107: 4310600 | B107: KN Accountantskosten | C107: 14811 | D107: 20153 | E107: 91304
A108: 4310700 | B108: KN Administratiekosten | C108: 1384 | D108: 1210 | E108: 4840
A109: 4310800 | B109: KN Makelaarskosten | C109: 66316 | D109: 85400 | E109: 302643
A110: 4311000 | B110: KN Juridische kosten | C110: 23912 | D110: 7816 | E110: 60648
A111: 4311800 | B111: KN Advieskosten | C111: 0 | D111: 0 | E111: 5445
A112: 4311900 | B112: KN Bankkosten | C112: 1306 | D112: 1261 | E112: 5291
A113: 4319800 | B113: KN Overige algemene kosten | C113: 2680 | D113: 561 | E113: -797
A114: Totaal Algemene kosten | C114: =SUM(C104:C113) -> 134380 | D114: =SUM(D104:D113) -> 155197 | E114: 559070
A116: 4623000 | B116: FINBL Rente ABN AMRO Bank NV Leningen | C116: 0 | D116: 0 | E116: 0
A117: 4623001 | B117: FINBL Rente ABN AMRO Bank NV Senior Facility Agreement | C117: 503883 | D117: 513800 | E117: 2102146
A118: 4628001 | B118: FINBL Rente LLS QSPESS Limited | C118: 0 | D118: 0 | E118: 0
A119: 4630000 | B119: FINBL Rente belastingen | C119: 0 | D119: 0 | E119: 0
A120: 4643000 | B120: FINBL Overige rentelasten | C120: 105863 | D120: 108774 | E120: 439304
A121: Totaal Financiële baten en lasten | C121: =SUM(C116:C120) -> 609746 | D121: =SUM(D116:D120) -> 622574 | E121: 2541450
...

Sheet BDO - Q3 2019
C1: Eindbalans 30-09-2018 | D1: Mutaties periode Q4 2018 | E1: Mutaties Q1 t/m Q3 2019 | F1: Saldi per 30-09-2019 | H1: Mutaties Q3 2019
A3: Balans
A4: 1600200 | B4: VG Vastgoedbeleggingen Verkrijgings- of vervaardigingsprijs | C4: 134929585 | D4: -2259117 | E4: 0 | F4: =SUM(C4:E4) -> 132670468 | H4: 0
A5: 1600200 | B5: VG Vastgoedbeleggingen Cum afschrijvingen en waardeverm | C5: =-7179064 -> -7179064 | D5: -895606 | E5: -1966185 | F5: =SUM(C5:E5) -> -10040855 | H5: -653662
A6: 1610803 | B6: VG Comm VG in exploitatie Buitengebruikstellingen aanschaffingswaarde | E6: -2215390 | F6: =SUM(C6:E6) -> -2215390 | H6: -462286
A7: 1611003 | B7: VG Comm VG in exploitatie Buitengebruikstellingen cum. afschr. en waardeverm. | C7: 83981 | D7: 36289 | E7: 146755 | F7: =SUM(C7:E7) -> 267025 | H7: 33933
A8: Totaal Vastgoedbeleggingen | C8: =SUM(C4:C7) -> 127834502 | D8: =SUM(D4:D7) -> -3118434 | E8: =SUM(E4:E7) -> -4034820 | F8: =SUM(C8:E8) -> 120681248 | H8: =SUM(H4:H7) -> -1082015
A10: 1790002 | B10: FVA Latente belastingvordering langlopend | C10: 1655598 | D10: 740409 | E10: 464688 | F10: =SUM(C10:E10) -> 2860695 | H10: 153794
A11: Totaal Financiële vaste activa | C11: =SUM(C10) -> 1655598 | D11: =SUM(D10) -> 740409 | E11: =SUM(E10) -> 464688 | F11: =SUM(C11:E11) -> 2860695 | H11: =SUM(H10) -> 153794
A13: 2000000 | B13: VOR Debiteuren | C13: =515882-177000-115000 -> 223882 | D13: =-396678+177000+115000 -> -104678 | E13: 130719 | F13: =SUM(C13:E13) -> 249923 | H13: -93669
A14: 2000300 | B14: VOR Voorziening dubieuze debiteuren | C14: -14000 | D14: -50501 | F14: =SUM(C14:E14) -> -64501 | H14: 0
A15: Totaal Debiteuren | C15: =SUM(C13:C14) -> 209882 | D15: =SUM(D13:D14) -> -155179 | E15: =SUM(E13:E14) -> 130719 | F15: =SUM(C15:E15) -> 185422 | H15: =SUM(H13:H14) -> -93669
A17: 2640000 | B17: RC Kortlopend DMRRP INV - I BV | C17: 110497 | D17: 0 | E17: 0 | F17: =SUM(C17:E17) -> 110497 | H17: 0
A18: Totaal Rekening-courant aandeelhouder | C18: =SUM(C17) -> 110497 | D18: =SUM(D17) -> 0 | E18: =SUM(E17) -> 0 | F18: =SUM(C18:E18) -> 110497 | H18: =SUM(H17) -> 0
A20: 2040700 | B20: VOR Vooruitbetaalde servicekosten | C20: 0 | D20: 15594 | E20: 0 | F20: =SUM(C20:E20) -> 15594 | H20: 0
A21: 2040900 | B21: VOR Vooruitbetaalde overige kosten | C21: 0 | D21: 737 | E21: 0 | F21: =SUM(C21:E21) -> 737 | H21: 0
A22: Totaal overige vorderingen | C22: =SUM(C20:C21) -> 0 | D22: =SUM(D20:D21) -> 16331 | E22: =SUM(E20:E21) -> 0 | F22: =SUM(C22:E22) -> 16331 | H22: =SUM(H20:H21) -> 0
A24: 2300000 | B24: LM Kruisposten | C24: 0 | D24: 0 | E24: 3338 | F24: =SUM(C24:E24) -> 3338 | H24: 3338
A25: 2400200 | B25: LM ABN AMRO Bank Disposal NL58 ABNA 0818 9180 39 | C25: 2404971 | D25: -1418387 | E25: -256886 | F25: =SUM(C25:E25) -> 729698 | H25: 649658
A26: 2400201 | B26: LM ABN AMRO Bank Deposit NL57 ABNA 0541 6205 68 | C26: 17820 | D26: -8172 | E26: 3265 | F26: =SUM(C26:E26) -> 12913 | H26: 12154
A27: 2400202 | B27: LM ABN AMRO Bank General NL93 ABNA 0541 6132 27 | C27: 23180 | D27: 168612 | E27: 599999 | F27: =SUM(C27:E27) -> 791791 | H27: 785758
A28: 2400203 | B28: LM ABN AMRO Bank Maintres NL04 ABNA 0541 6188 06 | C28: 435121 | D28: 56414 | E28: 91777 | F28: =SUM(C28:E28) -> 583312 | H28: -62925
A29: 2400204 | B29: LM ABN AMRO Bank Rent NL46 ABNA 0541 6088 35 | C29: 249024 | D29: 166400 | E29: 247984 | F29: =SUM(C29:E29) -> 663408 | H29: -364896
A30: 2400205 | B30: LM ABN AMRO Bank SR EXP NL88 ABNA 0541 6205 92 | C30: 149397 | D30: 125774 | E30: -274333 | F30: =SUM(C30:E30) -> 838 | H30: -115700
A31: Totaal Liquide middelen | C31: =SUM(C24:C30) -> 3279513 | D31: =SUM(D24:D30) -> -909359 | E31: =SUM(E24:E30) -> 415144 | F31: =SUM(C31:E31) -> 2785298 | H31: =SUM(H24:H30) -> 907387
A33: 1000002 | B33: EV Normale aandelen Saldo | C33: -1 | D33: 0 | E33: 0 | F33: =SUM(C33:E33) -> -1 | H33: 0
A34: 1100000 | B34: EV Agioreserve Agio aandelen | C34: -19431219 | D34: 0 | E34: 0 | F34: =SUM(C34:E34) -> -19431219 | H34: 0
A35: 1160000 | B35: EV Overige reserve Reserve aandelen | C35: =9890198-1711717+1831580 -> 10010061 | E35: 0 | F35: =SUM(C35:E35) -> 10010061 | H35: 0
A36: 1160100 | B36: EV Overige reserve Dividenduitkeringen aandelen | C36: 7497104 | D36: =230000 -> 230000 | E36: 820500 | F36: =SUM(C36:E36) -> 8547604 | H36: 285500
A37: Totaal Eigen vermogen | C37: =SUM(C33:C36) -> -1924055 | D37: =SUM(D33:D36) -> 230000 | E37: =SUM(E33:E36) -> 820500 | F37: =SUM(C37:E37) -> -873555 | H37: =SUM(H33:H36) -> 285500
A39: 1930001 | B39: LLS Hoofdsom ABN AMRO Bank NV Senior Facility Agreement | C39: =-130000000 -> -130000000 | D39: 0 | E39: 0 | F39: =SUM(C39:E39) -> -130000000 | H39: 0
A40: 1930101 | B40: LLS Cum aflossingen ABN AMRO Bank NV Senior Facility Agreement | C40: 1625000 | D40: 3445233 | E40: 5294156 | F40: =SUM(C40:E40) -> 10364389 | H40: 601184
A41: 1930201 | B41: LLS Kortlopend deel ABN AMRO Bank NV Senior Facility Agreement | C41: 0 | D41: -306834 | E41: 306834 | F41: =SUM(C41:E41) -> 0 | H41: 0
A42: Totaal Langlopende schulden | C42: =SUM(C39:C41) -> -128375000 | D42: =SUM(D39:D41) -> 3138399 | E42: =SUM(E39:E41) -> 5600990 | F42: =SUM(C42:E42) -> -119635611 | H42: =SUM(H39:H41) -> 601184
A44: 2730000 | B44: KLS Crediteuren | C44: 0 | D44: -176869 | E44: 3388 | F44: =SUM(C44:E44) -> -173481 | H44: 28193
A45: 2730001 | B45: KLS Crediteuren intercompany | C45: 0 | D45: 0 | E45: 0 | F45: =SUM(C45:E45) -> 0 | H45: 0
A46: Totaal Crediteuren | C46: =SUM(C44:C45) -> 0 | D46: =SUM(D44:D45) -> -176869 | E46: =SUM(E44:E45) -> 3388 | F46: =SUM(C46:E46) -> -173481 | H46: =SUM(H44:H45) -> 28193
A48: 2512100 | B48: BEL Afgedragen/ontvangen BTW | C48: -6835 | D48: -1031 | E48: 4140 | F48: =SUM(C48:E48) -> -3726 | H48: -19
A49: 2530000 | B49: BEL Te betalen vennootschapsbelasting | C49: -331450 | D49: 165522 | E49: -272134 | F49: =SUM(C49:E49) -> -438062 | H49: -74792
A50: 2550000 | B50: BEL Te betalen overige belastingen | C50: 0 | D50: -1045 | E50: 95924 | F50: =SUM(C50:E50) -> 94879 | H50: -94878
A51: Totaal Belastingen | C51: =SUM(C48:C50) -> -338285 | D51: =SUM(D48:D50) -> 163446 | E51: =SUM(E48:E50) -> -172070 | F51: =SUM(C51:E51) -> -346909 | H51: =SUM(H48:H50) -> -169689
A53: 2740300 | B53: KLS Te betalen waarborgsommen kortlopend | C53: -634584 | D53: -31930 | E53: -33963 | F53: =SUM(C53:E53) -> -700477 | H53: -8607
A54: 2740500 | B54: KLS Te betalen accountants- en administratiekosten | C54: -22500 | D54: 0 | E54: 0 | F54: =SUM(C54:E54) -> -22500 | H54: 0
A55: 2740600 | B55: KLS Te betalen rente | C55: 0 | D55: 0 | E55: 0 | F55: =SUM(C55:E55) -> 0 | H55: 0
A56: 2740700 | B56: KLS Te betalen verzekeringen | C56: 0 | D56: 0 | E56: 15904 | F56: =SUM(C56:E56) -> 15904 | H56: -15903
A57: 2741000 | B57: KLS Te betalen servicekosten | C57: -9100 | D57: 8900 | E57: 200 | F57: =SUM(C57:E57) -> 0 | H57: 0
A58: 2741001 | B58: KLS Te betalen exploitatiekosten | C58: 0 | D58: -36832 | E58: 36832 | F58: =SUM(C58:E58) -> 0 | H58: 0
A59: 2741002 | B59: KLS Te betalen VVE | C59: 0 | D59: -675 | E59: 675 | F59: =SUM(C59:E59) -> 0 | H59: 0
A60: 2741004 | B60: KLS Te betalen Hoen | C60: -40182 | D60: 24 | E60: -723 | F60: =SUM(C60:E60) -> -40881 | H60: 38680
A61: 2741005 | B61: KLS Te betalen managementvergoedingen | C61: 0 | D61: 0 | E61: 0 | F61: =SUM(C61:E61) -> 0 | H61: 0
A62: 2741200 | B62: KLS Te betalen overige kosten | C62: -5040 | D62: -8128 | E62: 33168 | F62: =SUM(C62:E62) -> 20000 | H62: 20000
A63: 2741900 | B63: KLS Nog uit te zoeken posten MT940 | C63: -640 | D63: 640 | E63: 0 | F63: =SUM(C63:E63) -> 0 | H63: 0
A64: 2742200 | B64: KLS Vooruitontvangen bedragen | C64: -117044 | D64: -23728 | E64: 10923 | F64: =SUM(C64:E64) -> -129849 | H64: =-20427-5 -> -20432
A65: Totaal Overige schulden | C65: =SUM(C53:C64) -> -829090 | D65: =SUM(D53:D64) -> -91729 | E65: =SUM(E53:E64) -> 63016 | F65: =SUM(C65:E65) -> -857803 | H65: =SUM(H53:H64) -> 13738
F67: =F65+F51+F46+F42+F37+F31+F22+F18+F15+F11+F8 -> 4752132
A68: Winst- en verliesrekening (baten zijn positief, kosten negatief)
A69: 8000003 | B69: OPB Netto-omzet Theoretische huuropbrengsten | D69: -2803935 | E69: -8448106 | F69: =SUM(C69:E69) -> -11252041 | H69: -2864512 | I69: =H69*4 -> -11458048 | J69: =I69/1000000 -> -11.458048
A70: 8000004 | B70: OPB Netto-omzet Leegstand huuropbrengsten | D70: 68895 | E70: 188144 | F70: =SUM(C70:E70) -> 257039 | H70: 66870
A71: Totaal Netto-omzet | D71: =SUM(D69:D70) -> -2735040 | E71: =SUM(E69:E70) -> -8259962 | F71: =SUM(C71:E71) -> -10995002 | H71: =SUM(H69:H70) -> -2797642 | I71: =H71/H69 -> 0.97665571 | J71: =1-I71 -> 0.02334429
A73: 8400600 | B73: OPB Overige bedrijfsopbrengsten Totale servicekosten | D73: -160225 | E73: -523067 | F73: =SUM(C73:E73) -> -683292 | H73: -173416
A74: 8400700 | B74: OPB Overige bedrijfsopbrengsten Servicekosten leegstand | D74: 19655 | E74: 27042 | F74: =SUM(C74:E74) -> 46697 | H74: 8357
A75: 8400800 | B75: OPB Overige bedrijfsopbrengsten Gerealiseerde servicekosten | D75: 213916 | E75: 514502 | F75: =SUM(C75:E75) -> 728418 | H75: 162849
A76: Totaal Overige bedrijfsopbrengsten | D76: =SUM(D73:D75) -> 73346 | E76: =SUM(E73:E75) -> 18477 | F76: =SUM(C76:E76) -> 91823 | H76: =SUM(H73:H75) -> -2210
A78: 4051400 | B78: KN Diensten door derden | D78: 119234 | E78: 359128 | F78: =SUM(C78:E78) -> 478362 | H78: 121669
A79: Totaal overige personeelskosten | D79: =SUM(D78) -> 119234 | E79: =SUM(E78) -> 359128 | F79: =SUM(C79:E79) -> 478362 | H79: =SUM(H78) -> 121669
A81: 4730000 | B81: AFKN Afschrijvingskosten Vastgoedbeleggingen | D81: 895606 | E81: 1966185 | F81: =SUM(C81:E81) -> 2861791 | H81: 653662
A82: 4730200 | B82: AFKN Boekresultaat Vastgoedbeleggingen | D82: -420234 | E82: -1794615 | F82: =SUM(D82:E82) -> -2214849 | H82: -485647
A83: Totaal Afschrijvingen vastgoedbeleggingen | D83: =SUM(D81:D82) -> 475372 | E83: =SUM(E81:E82) -> 171570 | F83: =SUM(C83:E83) -> 646942 | H83: =SUM(H81:H82) -> 168015
A85: 4100400 | B85: KN Onderhoud gebouwen | D85: 502624 | E85: 1097034 | F85: =SUM(C85:E85) -> 1599658 | H85: 473207
A86: 4100410 | B86: Verhuurdersheffing | D86: 0 | E86: 526887 | F86: =SUM(C86:E86) -> 526887 | H86: 526216
A87: 4100900 | B87: KN Onroerende zaakbelasting | D87: 1403 | E87: 246042 | F87: =SUM(C87:E87) -> 247445 | H87: 65301
A88: 4101000 | B88: KN VvE-kosten | D88: 89393 | E88: 444694 | F88: =SUM(C88:E88) -> 534087 | H88: 143177
A89: 4101010 | B89: Gemeentelijke belastingen | D89: 136 | E89: 99818 | F89: =SUM(C89:E89) -> 99954 | H89: 29292
A90: 4101020 | B90: Waterschapsbelasting | D90: 1676 | E90: 69748 | F90: =SUM(C90:E90) -> 71424 | H90: 18196
A91: 4101300 | B91: KN Servicekosten leegstand | D91: 1296 | E91: 51189 | F91: =SUM(C91:E91) -> 52485 | H91: 10273
A92: 4109800 | B92: KN Overige huisvestingskosten | D92: 0 | E92: 39569 | F92: =SUM(C92:E92) -> 39569 | H92: 0
A93: Totaal Huisvestingskosten | D93: =SUM(D85:D92) -> 596528 | E93: =SUM(E85:E92) -> 2574981 | F93: =SUM(C93:E93) -> 3171509 | H93: =SUM(H85:H92) -> 1265662
A95: 4500400 | B95: KN Representatiekosten | D95: 0 | E95: 4200 | F95: =SUM(C95:E95) -> 4200 | H95: 4200
A96: 4501200 | B96: KN Mutatie voorziening dubieuze debiteuren | D96: 50501 | E96: 0 | F96: =SUM(C96:E96) -> 50501 | H96: 0
A97: 4501300 | B97: KN Afboeking dubieuze debiteuren | D97: 59438 | E97: 1481 | F97: =SUM(C97:E97) -> 60919 | H97: 2282
A98: Totaal Verkoopkosten | D98: =SUM(D95:D97) -> 109939 | E98: =SUM(E95:E97) -> 5681 | F98: =SUM(C98:E98) -> 115620 | H98: =SUM(H95:H97) -> 6482
A100: 4300500 | B100: KN Incassokosten | D100: 306 | E100: 837 | F100: =SUM(C100:E100) -> 1143 | H100: 0
A101: Totaal Kantoorkosten | D101: =SUM(D100) -> 306 | E101: =SUM(E100) -> 837 | F101: =SUM(C101:E101) -> 1143 | H101: =SUM(H100) -> 0
A103: 4310000 | B103: KN Abonnementen en contributies | D103: 0 | E103: 4385 | F103: =SUM(C103:E103) -> 4385 | H103: 0
A104: 4310400 | B104: KN Assurantiepremie algemeen | D104: 13624 | E104: 75564 | F104: =SUM(C104:E104) -> 89188 | H104: 28072
A105: 4310500 | B105: KN Managementvergoeding | D105: 5445 | E105: 16335 | F105: =SUM(C105:E105) -> 21780 | H105: 5445
A106: 4310600 | B106: KN Accountantskosten | D106: 18714 | E106: 85771 | F106: =SUM(C106:E106) -> 104485 | H106: 16927
A107: 4310700 | B107: KN Administratiekosten | D107: 1036 | E107: 2594 | F107: =SUM(C107:E107) -> 3630
A108: 4310800 | B108: KN Makelaarskosten | D108: 79392 | E108: 190795 | F108: =SUM(C108:E108) -> 270187 | H108: 39079
A109: 4311000 | B109: KN Juridische kosten | D109: 25355 | E109: 67982 | F109: =SUM(C109:E109) -> 93337 | H109: 37004
A110: 4311800 | B110: KN Advieskosten | D110: 5445 | E110: 0 | F110: =SUM(C110:E110) -> 5445
A111: 4311900 | B111: KN Bankkosten | D111: 1336 | E111: 3959 | F111: =SUM(C111:E111) -> 5295 | H111: 1391
A112: 4312600 | B112: KN Agent Fee facility | D112: 0 | E112: 20000 | F112: =SUM(C112:E112) -> 20000 | H112: 20000
A113: 4319800 | B113: KN Overige algemene kosten | D113: -4121 | E113: 4450 | F113: =SUM(C113:E113) -> 329 | H113: 1210
A114: Totaal Algemene kosten | D114: =SUM(D103:D113) -> 146226 | E114: =SUM(E103:E113) -> 471835 | F114: =SUM(C114:E114) -> 618061 | H114: =SUM(H103:H113)+2 -> 149130
A116: 4623000 | B116: FINBL Rente ABN AMRO Bank NV leningen | E116: 0 | F116: =SUM(C116:E116) -> 0 | H116: 0
A117: 4623001 | B117: FINBL Rente ABN AMRO Bank NV Senior Facility Agreement | D117: 545642 | E117: 1504309 | F117: =SUM(C117:E117) -> 2049951 | H117: 486625
A118: 4628001 | B118: FINBL Rente LLS QSPESS Limited | D118: 0 | E118: 0 | F118: =SUM(C118:E118) -> 0 | H118: 0
A119: 4630000 | B119: FINBL Rente belastingen | D119: 0 | E119: 0 | F119: =SUM(C119:E119) -> 0 | H119: 0
A120: 4643000 | B120: FINBL Overige rentelasten | D120: 113801 | E120: 326277 | F120: =SUM(C120:E120) -> 440078 | H120: 111640
...

Sheet BDO Q4 2019
C1: Eindbalans 31-12-2018 | D1: Mutaties periode Q1 2019 | E1: Mutaties Q2 2019 | F1: Mutaties Q3 2019 | G1: Mutaties Q4 2019 | H1: Saldi per 31-12-2019
A3: Balans
A4: 1600200 | B4: VG Vastgoedbeleggingen Verkrijgings- of vervaardigingsprijs | C4: =134929585-2259117 -> 132670468 | F4: 0 | H4: =SUM(C4:G4) -> 132670468
A5: 1600200 | B5: VG Vastgoedbeleggingen Cum afschrijvingen en waardeverm | C5: =-8074670+120270 -> -7954400 | D5: -662362 | E5: -650161 | F5: -653662 | G5: -656408 | H5: =SUM(C5:G5) -> -10576993
A6: 1610803 | B6: VG Comm VG in exploitatie Buitengebruikstellingen aanschaffingswaarde | D6: -651550 | E6: -1101554 | F6: -462286 | G6: -1443087 | H6: =SUM(C6:G6) -> -3658477
A7: 1611003 | B7: VG Comm VG in exploitatie Buitengebruikstellingen cum. afschr. en waardeverm. | D7: 41286 | E7: 71536 | F7: 33933 | G7: 116170 | H7: =SUM(C7:G7) -> 262925
A8: Totaal Vastgoedbeleggingen
A10: 1790002 | B10: FVA Latente belastingvordering langlopend | C10: 2396007 | D10: 168662 | E10: 142232 | F10: 153794 | G10: 129418 | H10: =SUM(C10:G10) -> 2990113
A11: Totaal Financiële vaste activa
A13: 2000000 | B13: VOR Debiteuren | C13: 119205 | D13: 158343 | E13: 66045 | F13: -93669 | G13: -177050 | H13: =SUM(C13:G13) -> 72874
A14: 2000300 | B14: VOR Voorziening dubieuze debiteuren | C14: -64501 | D14: 0 | E14: 0 | F14: 0 | G14: 0 | H14: =SUM(C14:G14) -> -64501
A15: Totaal Debiteuren
A17: 2640000 | B17: RC Kortlopend DMRRP INV - I BV | C17: 110497 | D17: 0 | E17: 0 | F17: 0 | G17: 0 | H17: =SUM(C17:G17) -> 110497
A18: Totaal Rekening-courant aandeelhouder
A20: 2040200 | B20: VOR Te vorderen waarborgsommen kortlopen | C20: 0 | D20: 0 | E20: 0 | F20: 0 | G20: 5000 | H20: =SUM(C20:G20) -> 5000
A21: 2040700 | B21: VOR Vooruitbetaalde servicekosten | C21: 15594 | D21: 0 | E21: 0 | F21: 0 | G21: -15581 | H21: =SUM(C21:G21) -> 13
A22: 2040900 | B22: VOR Vooruitbetaalde overige kosten | C22: 737 | D22: 0 | E22: 0 | F22: 0 | G22: 0 | H22: =SUM(C22:G22) -> 737
A23: Totaal overige vorderingen
A25: 2300000 | B25: LM Kruisposten | C25: 0 | D25: 672 | E25: -672 | F25: 3338 | G25: 547 | H25: =SUM(C25:G25) -> 3885
A26: 2400200 | B26: LM ABN AMRO Bank Disposal NL58 ABNA 0818 9180 39 | C26: 986584 | D26: -447623 | E26: -458920 | F26: 649658 | G26: 1729271 | H26: =SUM(C26:G26)-2 -> 2458968
A27: 2400201 | B27: LM ABN AMRO Bank Deposit NL57 ABNA 0541 6205 68 | C27: 9648 | D27: 1359967 | E27: -1368856 | F27: 12154 | G27: 74896 | H27: =SUM(C27:G27) -> 87809
A28: 2400202 | B28: LM ABN AMRO Bank General NL93 ABNA 0541 6132 27 | C28: 191790 | D28: 842838 | E28: -1028597 | F28: 785758 | G28: -19584 | H28: =SUM(C28:G28)+2 -> 772207
A29: 2400203 | B29: LM ABN AMRO Bank Maintres NL04 ABNA 0541 6188 06 | C29: 491534 | D29: 109815 | E29: 44887 | F29: -62925 | G29: 66151 | H29: =SUM(C29:G29) -> 649462
A30: 2400204 | B30: LM ABN AMRO Bank Rent NL46 ABNA 0541 6088 35 | C30: 415425 | D30: 84312 | E30: 528567 | F30: -364896 | G30: 1098220 | H30: =SUM(C30:G30) -> 1761628
A31: 2400205 | B31: LM ABN AMRO Bank SR EXP NL88 ABNA 0541 6205 92 | C31: 275171 | D31: -217031 | E31: 58399 | F31: -115700 | G31: 194761 | H31: =SUM(C31:G31) -> 195600
A32: Totaal Liquide middelen
A34: 1000002 | B34: EV Normale aandelen Saldo | C34: -1 | D34: 0 | E34: 0 | F34: 0 | G34: 0 | H34: =SUM(C34:G34) -> -1
A35: 1100000 | B35: EV Agioreserve Agio aandelen | C35: -19431219 | D35: 0 | E35: 0 | F35: 0 | G35: 0 | H35: =SUM(C35:G35) -> -19431219
A36: 1160000 | B36: EV Overige reserve Reserve aandelen | C36: =9890198-1340715+7727104 -> 16276587 | D36: 0 | E36: 0 | F36: 0 | G36: 0 | H36: =SUM(C36:G36) -> 16276587
A37: 1160100 | B37: EV Overige reserve Dividenduitkeringen aandelen | C37: 0 | D37: 310000 | E37: 225000 | F37: 285500 | G37: 235000 | H37: =SUM(C37:G37) -> 1055500
A38: Totaal Eigen vermogen
H39: =SUM(C39:G39) -> 0
A40: 1930001 | B40: LLS Hoofdsom ABN AMRO Bank NV Senior Facility Agreement | C40: -130000000 | D40: 0 | E40: 0 | F40: 0 | G40: 0 | H40: =SUM(C40:G40) -> -130000000
A41: 1930101 | B41: LLS Cum aflossingen ABN AMRO Bank NV Senior Facility Agreement | C41: 5070233 | D41: 0 | E41: 4692972 | F41: 601184 | G41: 601184 | H41: =SUM(C41:G41) -> 10965573
A42: 1930201 | B42: LLS Kortlopend deel ABN AMRO Bank NV Senior Facility Agreement | C42: -306834 | D42: 306834 | E42: 0 | F42: 0 | G42: 0 | H42: =SUM(C42:G42) -> 0
A43: Totaal Langlopende schulden
A45: 2730000 | B45: KLS Crediteuren | C45: -176869 | D45: -18824 | E45: -5981 | F45: 28193 | G45: -55987 | H45: =SUM(C45:G45) -> -229468
A46: 2730001 | B46: KLS Crediteuren intercompany | C46: 0 | D46: 0 | E46: 0 | F46: 0 | G46: 0 | H46: =SUM(C46:G46) -> 0
A47: Totaal Crediteuren
H48: =SUM(C48:G48) -> 0
A49: 2512100 | B49: BEL Afgedragen/ontvangen BTW | C49: -7866 | D49: 4150 | E49: 9 | F49: -19 | G49: -205 | H49: =SUM(C49:G49) -> -3931
A50: 2530000 | B50: BEL Te betalen vennootschapsbelasting | C50: -165928 | D50: 0 | E50: -197342 | F50: -74792 | G50: 94944 | H50: =SUM(C50:G50) -> -343118
A51: 2550000 | B51: BEL Te betalen overige belastingen | C51: -1045 | D51: 285682 | E51: -94879 | F51: -94878 | G51: -94879 | H51: =SUM(C51:G51) -> 1
A52: Totaal Belastingen
A54: 2740300 | B54: KLS Te betalen waarborgsommen kortlopend | C54: -666515 | D54: -11908 | E54: -13448 | F54: -8607 | G54: =-10298+1 -> -10297 | H54: =SUM(C54:G54) -> -710775
A55: 2740500 | B55: KLS Te betalen accountants- en administratiekosten | C55: -22500 | D55: 0 | E55: 0 | F55: 0 | G55: 0 | H55: =SUM(C55:G55) -> -22500
A56: 2740600 | B56: KLS Te betalen rente | C56: 0 | D56: -503883 | E56: 503883 | F56: 0 | G56: 0 | H56: =SUM(C56:G56) -> 0
A57: 2740700 | B57: KLS Te betalen verzekeringen | C57: 0 | D57: 47712 | E57: -15904 | F57: -15903 | G57: -15904 | H57: =SUM(C57:G57) -> 1
A58: 2741000 | B58: KLS Te betalen servicekosten | C58: -200 | D58: 8700 | E58: -8500 | F58: 0 | G58: 36335 | H58: =SUM(C58:G58) -> 36335
A59: 2741001 | B59: KLS Te betalen exploitatiekosten | C59: -36832 | D59: 36832 | E59: 0 | F59: 0 | G59: 0 | H59: =SUM(C59:G59) -> 0
A60: 2741002 | B60: KLS Te betalen VVE | C60: -675 | D60: 675 | E60: 0 | F60: 0 | G60: 0 | H60: =SUM(C60:G60) -> 0
A61: 2741004 | B61: KLS Te betalen Hoen | C61: -40157 | D61: -39889 | E61: 487 | F61: 38680 | G61: 61 | H61: =SUM(C61:G61) -> -40818
A62: 2741005 | B62: KLS Te betalen managementvergoedingen | C62: 0 | D62: 0 | E62: 0 | F62: 0 | G62: 0 | H62: =SUM(C62:G62) -> 0
A63: 2741200 | B63: KLS Te betalen overige kosten | C63: -13168 | D63: 13168 | E63: 0 | F63: 20000 | G63: -1083 | H63: =SUM(C63:G63) -> 18917
A64: 2741900 | B64: KLS Nog uit te zoeken posten MT940 | C64: 1 | D64: =-1384-4 -> -1388 | E64: =1385+1 -> 1386 | F64: 0 | G64: 558 | H64: =SUM(C64:G64) -> 557
A65: 2742200 | B65: KLS Vooruitontvangen bedragen | C65: -140771 | D65: 26143 | E65: 5210 | F65: =-20427-5 -> -20432 | G65: -17605 | H65: =SUM(C65:G65) -> -147455
A66: Totaal Overige schulden
A69: Winst- en verliesrekening (baten zijn positief, kosten negatief)
A70: 8000003 | B70: OPB Netto-omzet Theoretische huuropbrengsten | D70: -2797626 | E70: -2785968 | F70: -2864512 | G70: -2858133 | H70: =SUM(C70:G70) -> -11306239
A71: 8000004 | B71: OPB Netto-omzet Leegstand huuropbrengsten | D71: 69244 | E71: 52029 | F71: 66870 | G71: 63771 | H71: =SUM(C71:G71) -> 251914
A72: Totaal Netto-omzet | D72: =SUM(D70:D71) -> -2728382 | E72: =SUM(E70:E71) -> -2733939 | F72: =SUM(F70:F71) -> -2797642 | G72: =SUM(G70:G71) -> -2794362 | H72: =SUM(C72:G72) -> -11054325
H73: =SUM(C73:G73) -> 0
A74: 8400600 | B74: OPB Overige bedrijfsopbrengsten Totale servicekosten | D74: -174608 | E74: -175044 | F74: -173416 | G74: -173087 | H74: =SUM(C74:G74) -> -696155
A75: 8400700 | B75: OPB Overige bedrijfsopbrengsten Servicekosten leegstand | D75: 10050 | E75: 8634 | F75: 8357 | G75: 29132 | H75: =SUM(C75:G75) -> 56173
A76: 8400800 | B76: OPB Overige bedrijfsopbrengsten Gerealiseerde servicekosten | D76: 173161 | E76: 178493 | F76: 162849 | G76: 74503 | H76: =SUM(C76:G76) -> 589006
A77: Totaal Overige bedrijfsopbrengsten | D77: =SUM(D74:D76) -> 8603 | E77: =SUM(E74:E76) -> 12083 | F77: =SUM(F74:F76) -> -2210 | G77: =SUM(G74:G76) -> -69452 | H77: =SUM(C77:G77) -> -50976
H78: =SUM(C78:G78) -> 0
A79: 4051400 | B79: KN Diensten door derden | D79: 119183 | E79: 118277 | F79: 121669 | G79: 121336 | H79: =SUM(C79:G79) -> 480465
A80: Totaal overige personeelskosten | D80: =SUM(D79) -> 119183 | E80: =SUM(E79) -> 118277 | F80: =SUM(F79) -> 121669 | G80: =SUM(G79) -> 121336 | H80: =SUM(C80:G80) -> 480465
H81: =SUM(C81:G81) -> 0
A82: 4730000 | B82: AFKN Afschrijvingskosten Vastgoedbeleggingen | D82: 662362 | E82: 650161 | F82: 653662 | G82: 656408 | H82: =SUM(C82:G82) -> 2622593
A83: 4730200 | B83: AFKN Boekresultaat Vastgoedbeleggingen | D83: -408986 | E83: -899982 | F83: -485647 | G83: -1058583 | H83: =SUM(C83:G83) -> -2853198
A84: Totaal Afschrijvingen vastgoedbeleggingen | D84: =SUM(D82:D83) -> 253376 | E84: =SUM(E82:E83) -> -249821 | F84: =SUM(F82:F83) -> 168015 | G84: =SUM(G82:G83) -> -402175 | H84: =SUM(C84:G84) -> -230605
H85: =SUM(C85:G85) -> 0
A86: 4100400 | B86: KN Onderhoud gebouwen | D86: 258876 | E86: 364950 | F86: 473207 | G86: 578341 | H86: =SUM(C86:G86) -> 1675374
A87: 4100410 | B87: Verhuurdersheffing | E87: 671 | F87: 526216 | H87: =SUM(C87:G87) -> 526887
A88: 4100900 | B88: KN Onroerende zaakbelasting | D88: 97883 | E88: 82857 | F88: 65301 | G88: 65007 | H88: =SUM(C88:G88) -> 311048
A89: 4101000 | B89: KN VvE-kosten | D89: 131618 | E89: 169899 | F89: 143177 | G89: 9198 | H89: =SUM(C89:G89) -> 453892
A90: 4101010 | B90: Gemeentelijke belastingen | D90: 29293 | E90: 41233 | F90: 29292 | G90: 29293 | H90: =SUM(C90:G90) -> 129111
A91: 4101020 | B91: Waterschapsbelasting | D91: 3342 | E91: 48209 | F91: 18196 | G91: 1662 | H91: =SUM(C91:G91) -> 71409
A92: 4101300 | B92: KN Servicekosten leegstand | D92: -676 | E92: 41592 | F92: 10273 | G92: -675 | H92: =SUM(C92:G92) -> 50514
A93: 4109800 | B93: KN Overige huisvestingskosten | E93: 39569 | F93: 0 | G93: 2153 | H93: =SUM(C93:G93) -> 41722
A94: Totaal Huisvestingskosten | D94: =SUM(D86:D93) -> 520336 | E94: =SUM(E86:E93) -> 788980 | F94: =SUM(F86:F93) -> 1265662 | G94: =SUM(G86:G93) -> 684979 | H94: =SUM(C94:G94) -> 3259957
H95: =SUM(C95:G95) -> 0
A96: 4500400 | B96: KN Representatiekosten | F96: 4200 | G96: 0 | H96: =SUM(C96:G96) -> 4200
A97: 4501200 | B97: KN Mutatie voorziening dubieuze debiteuren | F97: 0 | G97: 0 | H97: =SUM(C97:G97) -> 0
A98: 4501300 | B98: KN Afboeking dubieuze debiteuren | D98: 0 | E98: -800 | F98: 2282 | G98: 28608 | H98: =SUM(C98:G98) -> 30090
A99: Totaal Verkoopkosten | D99: =SUM(D96:D98) -> 0 | E99: =SUM(E96:E98) -> -800 | F99: =SUM(F96:F98) -> 6482 | G99: =SUM(G96:G98) -> 28608 | H99: =SUM(C99:G99) -> 34290
H100: =SUM(C100:G100) -> 0
A101: 4300500 | B101: KN Incassokosten | D101: 837 | E101: 0 | F101: 0 | G101: 0 | H101: =SUM(C101:G101) -> 837
A102: Totaal Kantoorkosten | D102: =SUM(D101) -> 837 | E102: 0 | F102: =SUM(F101) -> 0 | G102: -590 | H102: =SUM(C102:G102) -> 247
H103: =SUM(C103:G103) -> 0
A104: 4310000 | B104: KN Abonnementen en contributies | D104: 0 | E104: 4385 | F104: 0 | G104: 0 | H104: =SUM(C104:G104) -> 4385
A105: 4310400 | B105: KN Assurantiepremie algemeen | D105: 18526 | E105: 28966 | F105: 28072 | G105: 13908 | H105: =SUM(C105:G105) -> 89472
A106: 4310500 | B106: KN Managementvergoeding | D106: 5445 | E106: 5445 | F106: 5445 | G106: 5445 | H106: =SUM(C106:G106) -> 21780
A107: 4310600 | B107: KN Accountantskosten | D107: 14811 | E107: 54033 | F107: 16927 | G107: 21556 | H107: =SUM(C107:G107) -> 107327
A108: 4310700 | B108: KN Administratiekosten | D108: 1384 | E108: 1210 | F108: 0 | G108: 1210 | H108: =SUM(C108:G108) -> 3804
A109: 4310800 | B109: KN Makelaarskosten | D109: 66316 | E109: 85400 | F109: 39079 | G109: 53976 | H109: =SUM(C109:G109) -> 244771
A110: 4311000 | B110: KN Juridische kosten | D110: 23162 | E110: 7816 | F110: 37004 | G110: 6268 | H110: =SUM(C110:G110) -> 74250
A111: 4311800 | B111: KN Advieskosten | D111: 0 | E111: 0 | F111: 0 | G111: 0 | H111: =SUM(C111:G111) -> 0
...

Sheet BDO - Q1 2020
C1: Eindbalans 31-03-2019 | D1: Mutaties Q2 2019 | E1: Mutaties Q3 2019 | F1: Mutaties Q4 2019 | G1: Mutaties Q1 2020 | H1: Saldi per 31-03-2020
A3: Balans
A4: 1600200 | B4: VG Vastgoedbeleggingen Verkrijgings- of vervaardigingsprijs | C4: 132670468 | E4: 0 | G4: -3658477 | H4: =SUM(C4:G4) -> 129011991
A5: 1600200 | B5: VG Vastgoedbeleggingen Cum afschrijvingen en waardeverm | C5: -8616762 | D5: -650161 | E5: -653662 | F5: -656408 | G5: -380013 | H5: =SUM(C5:G5) -> -10957006
A6: 1610803 | B6: VG Comm VG in exploitatie Buitengebruikstellingen aanschaffingswaarde | C6: -651550 | D6: -1101554 | E6: -462286 | F6: -1443087 | G6: 2472387 | H6: =SUM(C6:G6) -> -1186090
A7: 1611003 | B7: VG Comm VG in exploitatie Buitengebruikstellingen cum. afschr. en waardeverm. | C7: 41286 | D7: 71536 | E7: 33933 | F7: 116170 | G7: -162402 | H7: =SUM(C7:G7) -> 100523
A8: Totaal Vastgoedbeleggingen
A10: 1790002 | B10: FVA Latente belastingvordering langlopend | C10: 2564669 | D10: 142232 | E10: 153794 | F10: 129418 | G10: -293081 | H10: =SUM(C10:G10) -> 2697032
A11: Totaal Financiële vaste activa
A13: 2000000 | B13: VOR Debiteuren | C13: 277548 | D13: 66045 | E13: -93669 | F13: -177050 | G13: 5313 | H13: =SUM(C13:G13) -> 78187
A14: 2000300 | B14: VOR Voorziening dubieuze debiteuren | C14: -64501 | D14: 0 | E14: 0 | F14: 0 | G14: 0 | H14: =SUM(C14:G14) -> -64501
A15: Totaal Debiteuren
A17: 2640000 | B17: RC Kortlopend DMRRP INV - I BV | C17: 110497 | D17: 0 | E17: 0 | F17: 0 | G17: 100000 | H17: =SUM(C17:G17) -> 210497
A18: Totaal Rekening-courant aandeelhouder
A20: 2040200 | B20: VOR Te vorderen waarborgsommen kortlopen | C20: 0 | D20: 0 | E20: 0 | F20: 5000 | G20: 0 | H20: =SUM(C20:G20) -> 5000
A21: 2040700 | B21: VOR Vooruitbetaalde servicekosten | C21: 15594 | D21: 0 | E21: 0 | F21: -10713 | G21: 0 | H21: =SUM(C21:G21) -> 4881
A22: 2040900 | B22: VOR Vooruitbetaalde overige kosten | D22: 0 | E22: 0 | F22: 425 | G22: 0 | H22: =SUM(C22:G22) -> 425
A23: Totaal overige vorderingen
A25: 2300000 | B25: LM Kruisposten | C25: 672 | D25: -4010 | E25: 3338 | F25: 0 | H25: =SUM(C25:G25) -> 0
A26: 2400200 | B26: LM ABN AMRO Bank Disposal NL58 ABNA 0818 9180 39 | C26: 538961 | D26: -458920 | E26: 649658 | F26: 1729271 | G26: -1031638 | H26: =SUM(C26:G26) -> 1427332
A27: 2400201 | B27: LM ABN AMRO Bank Deposit NL57 ABNA 0541 6205 68 | C27: 1369615 | D27: -1368856 | E27: 12154 | F27: 74896 | G27: 1058693 | H27: =SUM(C27:G27) -> 1146502
A28: 2400202 | B28: LM ABN AMRO Bank General NL93 ABNA 0541 6132 27 | C28: 1034628 | D28: -1028597 | E28: 785758 | F28: -19584 | G28: -29065 | H28: =SUM(C28:G28) -> 743140
A29: 2400203 | B29: LM ABN AMRO Bank Maintres NL04 ABNA 0541 6188 06 | C29: 601349 | D29: 44887 | E29: -62925 | F29: 66151 | G29: -46640 | H29: =SUM(C29:G29) -> 602822
A30: 2400204 | B30: LM ABN AMRO Bank Rent NL46 ABNA 0541 6088 35 | C30: 499737 | D30: 528567 | E30: -364896 | F30: 1098220 | G30: -73423 | H30: =SUM(C30:G30) -> 1688205
A31: 2400205 | B31: LM ABN AMRO Bank SR EXP NL88 ABNA 0541 6205 92 | C31: 58140 | D31: 58399 | E31: -115700 | F31: 194761 | G31: 114437 | H31: =SUM(C31:G31) -> 310037
A32: Totaal Liquide middelen
A34: 1000002 | B34: EV Normale aandelen Saldo | C34: -1 | D34: 0 | E34: 0 | F34: 0 | G34: 0 | H34: =SUM(C34:G34) -> -1
A35: 1100000 | B35: EV Agioreserve Agio aandelen | C35: -19431219 | D35: 0 | E35: 0 | F35: 0 | G35: 0 | H35: =SUM(C35:G35) -> -19431219
A36: 1160000 | B36: EV Overige reserve Reserve aandelen | C36: =16276587-1251333-650 -> 15024604 | D36: 0 | E36: 0 | F36: 0 | G36: 0 | H36: =SUM(C36:G36) -> 15024604
A37: 1160100 | B37: EV Overige reserve Dividenduitkeringen aandelen | C37: 310000 | D37: 225000 | E37: 285500 | F37: 235000 | G37: 1510938 | H37: =SUM(C37:G37) -> 2566438
A38: Totaal Eigen vermogen
A40: 1930001 | B40: LLS Hoofdsom ABN AMRO Bank NV Senior Facility Agreement | C40: -130000000 | D40: 0 | E40: 0 | F40: 0 | G40: 0 | H40: =SUM(C40:G40) -> -130000000
A41: 1930101 | B41: LLS Cum aflossingen ABN AMRO Bank NV Senior Facility Agreement | C41: 5070233 | D41: 4692972 | E41: 601184 | F41: 601184 | G41: 2258971 | H41: =SUM(C41:G41) -> 13224544
A42: 1930201 | B42: LLS Kortlopend deel ABN AMRO Bank NV Senior Facility Agreement | C42: 0 | D42: 0 | E42: 0 | F42: 0 | G42: 0 | H42: =SUM(C42:G42) -> 0
A43: Totaal Langlopende schulden
A45: 2730000 | B45: KLS Crediteuren | C45: -195693 | D45: -5981 | E45: 28193 | F45: -67126 | G45: 17250 | H45: =SUM(C45:G45) -> -223357
A46: 2730001 | B46: KLS Crediteuren intercompany | C46: 0 | D46: 0 | E46: 0 | F46: 0 | G46: 0 | H46: =SUM(C46:G46) -> 0
A47: Totaal Crediteuren
H48: =SUM(C48:F48) -> 0
A49: 2512100 | B49: BEL Afgedragen/ontvangen BTW | C49: -3716 | D49: 9 | E49: -19 | F49: -204 | G49: 17 | H49: =SUM(C49:G49) -> -3913
A50: 2530000 | B50: BEL Te betalen vennootschapsbelasting | C50: -165928 | D50: -197342 | E50: -74792 | F50: 94944 | G50: 0 | H50: =SUM(C50:G50) -> -343118
A51: 2550000 | B51: BEL Te betalen overige belastingen | C51: 284637 | D51: -94879 | E51: -94878 | F51: -94878 | G51: 0 | H51: =SUM(C51:G51) -> 2
A52: Totaal Belastingen
A54: 2740300 | B54: KLS Te betalen waarborgsommen kortlopend | C54: -678423 | D54: -13448 | E54: -8607 | F54: -10299 | G54: 10687 | H54: =SUM(C54:G54) -> -700090
A55: 2740500 | B55: KLS Te betalen accountants- en administratiekosten | C55: -22500 | D55: 0 | E55: 0 | F55: 0 | G55: 0 | H55: =SUM(C55:G55) -> -22500
A56: 2740600 | B56: KLS Te betalen rente | C56: -503883 | D56: 503883 | E56: 0 | F56: 0 | G56: -457533 | H56: =SUM(C56:G56) -> -457533
A57: 2740700 | B57: KLS Te betalen verzekeringen | C57: 47712 | D57: -15904 | E57: -15903 | F57: -15903 | G57: 0 | H57: =SUM(C57:G57) -> 2
A58: 2741000 | B58: KLS Te betalen servicekosten | C58: 8500 | D58: -8500 | E58: 0 | F58: 0 | G58: 0 | H58: =SUM(C58:G58) -> 0
A59: 2741001 | B59: KLS Te betalen exploitatiekosten | C59: 0 | D59: 0 | E59: 0 | F59: -2118 | G59: 0 | H59: =SUM(C59:G59) -> -2118
A60: 2741002 | B60: KLS Te betalen VVE | C60: 0 | D60: 0 | E60: 0 | F60: -1846 | G60: 0 | H60: =SUM(C60:G60) -> -1846
A61: 2741004 | B61: KLS Te betalen Hoen | C61: -80046 | D61: 487 | E61: 38680 | F61: 61 | G61: 483 | H61: =SUM(C61:G61) -> -40335
A62: 2741005 | B62: KLS Te betalen managementvergoedingen | C62: 0 | D62: 0 | E62: 0 | F62: 0 | G62: 0 | H62: =SUM(C62:G62) -> 0
A63: 2741200 | B63: KLS Te betalen overige kosten | C63: 0 | D63: 0 | E63: 20000 | F63: -1083 | G63: 0 | H63: =SUM(C63:G63) -> 18917
A64: 2741900 | B64: KLS Nog uit te zoeken posten MT940 | D64: 163 | E64: 0 | F64: -162 | G64: 851 | H64: =SUM(C64:G64) -> 852
A65: 2742200 | B65: KLS Vooruitontvangen bedragen | C65: -114628 | D65: 5210 | E65: =-20427-5 -> -20432 | F65: -17605 | G65: -5561 | H65: =SUM(C65:G65) -> -153016
A66: Totaal Overige schulden
A69: Winst- en verliesrekening (baten zijn positief, kosten negatief)
A70: 8000003 | B70: OPB Netto-omzet Theoretische huuropbrengsten | D70: -2785968 | E70: -2864512 | F70: -2858133 | G70: -2847208 | H70: =SUM(C70:G70) -> -11355821
A71: 8000004 | B71: OPB Netto-omzet Leegstand huuropbrengsten | D71: 52029 | E71: 66870 | F71: 63770 | G71: 69125 | H71: =SUM(C71:G71) -> 251794
A72: Totaal Netto-omzet | D72: =SUM(D70:D71) -> -2733939 | E72: =SUM(E70:E71) -> -2797642 | F72: =SUM(F70:F71) -> -2794363 | G72: =SUM(G70:G71) -> -2778083 | H72: =SUM(C72:G72) -> -11104027
A74: 8400600 | B74: OPB Overige bedrijfsopbrengsten Totale servicekosten | D74: -175044 | E74: -173416 | F74: -173087 | G74: -172417 | H74: =SUM(C74:G74) -> -693964
A75: 8400700 | B75: OPB Overige bedrijfsopbrengsten Servicekosten leegstand | D75: 8634 | E75: 8357 | F75: 29682 | G75: 10767 | H75: =SUM(C75:G75) -> 57440
A76: 8400800 | B76: OPB Overige bedrijfsopbrengsten Gerealiseerde servicekosten | D76: 181608 | E76: 162849 | F76: 86991 | G76: 133343 | H76: =SUM(C76:G76) -> 564791
A77: Totaal Overige bedrijfsopbrengsten | D77: =SUM(D74:D76) -> 15198 | E77: =SUM(E74:E76) -> -2210 | F77: =SUM(F74:F76) -> -56414 | G77: =SUM(G74:G76) -> -28307 | H77: =SUM(C77:G77) -> -71733
A79: 4051400 | B79: KN Diensten door derden | D79: 118277 | E79: 121669 | F79: 121336 | G79: 120736 | H79: =SUM(C79:G79) -> 482018
A80: Totaal overige personeelskosten | D80: =SUM(D79) -> 118277 | E80: =SUM(E79) -> 121669 | F80: =SUM(F79) -> 121336 | G80: =SUM(G79) -> 120736 | H80: =SUM(C80:G80) -> 482018
A82: 4730000 | B82: AFKN Afschrijvingskosten Vastgoedbeleggingen | D82: 650161 | E82: 653662 | F82: 656408 | G82: 642938 | H82: =SUM(C82:G82) -> 2603169
A83: 4730200 | B83: AFKN Boekresultaat Vastgoedbeleggingen | D83: -899982 | E83: -485647 | F83: -1058583 | G83: -987433 | H83: =SUM(C83:G83) -> -3431645
A84: Totaal Afschrijvingen vastgoedbeleggingen | D84: =SUM(D82:D83) -> -249821 | E84: =SUM(E82:E83) -> 168015 | F84: =SUM(F82:F83) -> -402175 | G84: =SUM(G82:G83) -> -344495 | H84: =SUM(C84:G84) -> -828476
A86: 4100400 | B86: KN Onderhoud gebouwen | D86: 364950 | E86: 473207 | F86: 577916 | G86: 491958 | H86: =SUM(C86:G86) -> 1908031
A87: 4100410 | B87: Verhuurdersheffing | D87: 671 | E87: 526216 | F87: 0 | G87: 0 | H87: =SUM(C87:G87) -> 526887
A88: 4100900 | B88: KN Onroerende zaakbelasting | D88: 82857 | E88: 65301 | F88: 65007 | G88: 47461 | H88: =SUM(C88:G88) -> 260626
A89: 4101000 | B89: KN VvE-kosten | D89: 166785 | E89: 143177 | F89: 5404 | G89: 96652 | H89: =SUM(C89:G89) -> 412018
A90: 4101010 | B90: Gemeentelijke belastingen | D90: 41233 | E90: 29292 | F90: 29292 | G90: 39392 | H90: =SUM(C90:G90) -> 139209
A91: 4101020 | B91: Waterschapsbelasting | D91: 48210 | E91: 18196 | F91: 1661 | G91: 250 | H91: =SUM(C91:G91) -> 68317
A92: 4101300 | B92: KN Servicekosten leegstand | D92: 41592 | E92: 10273 | F92: 35598 | G92: -799 | H92: =SUM(C92:G92) -> 86664
A93: 4109800 | B93: KN Overige huisvestingskosten | D93: 39569 | E93: 0 | F93: 2153 | G93: 0 | H93: =SUM(C93:G93) -> 41722
A94: Totaal Huisvestingskosten | D94: =SUM(D86:D93) -> 785867 | E94: =SUM(E86:E93) -> 1265662 | F94: =SUM(F86:F93) -> 717031 | G94: =SUM(G86:G93) -> 674914 | H94: =SUM(C94:G94) -> 3443474
A96: 4500400 | B96: KN Representatiekosten | D96: 0 | E96: 4200 | F96: 0 | G96: 0 | H96: =SUM(C96:G96) -> 4200
A97: 4501200 | B97: KN Mutatie voorziening dubieuze debiteuren | D97: 0 | E97: 0 | F97: 0 | G97: 0 | H97: =SUM(C97:G97) -> 0
A98: 4501300 | B98: KN Afboeking dubieuze debiteuren | D98: -800 | E98: 2282 | F98: 28608 | G98: -164 | H98: =SUM(C98:G98) -> 29926
A99: Totaal Verkoopkosten | D99: =SUM(D96:D98) -> -800 | E99: =SUM(E96:E98) -> 6482 | F99: =SUM(F96:F98) -> 28608 | G99: =SUM(G96:G98) -> -164 | H99: =SUM(C99:G99) -> 34126
A101: 4300500 | B101: KN Incassokosten | D101: 0 | E101: 0 | F101: -590 | G101: 0 | H101: =SUM(C101:G101) -> -590
A102: Totaal Kantoorkosten | D102: 0 | E102: =SUM(E101) -> 0 | F102: =SUM(F101) -> -590 | G102: =SUM(G101) -> 0 | H102: =SUM(C102:G102) -> -590
A104: 4310000 | B104: KN Abonnementen en contributies | D104: 4385 | E104: 0 | F104: 0 | G104: 4406 | H104: =SUM(C104:G104) -> 8791
A105: 4310400 | B105: KN Assurantiepremie algemeen | D105: 28966 | E105: 28072 | F105: 13908 | G105: 321 | H105: =SUM(C105:G105) -> 71267
A106: 4310500 | B106: KN Managementvergoeding | D106: 5445 | E106: 5445 | F106: 5445 | G106: 5445 | H106: =SUM(C106:G106) -> 21780
A107: 4310600 | B107: KN Accountantskosten | D107: 54033 | E107: 16927 | F107: 21556 | G107: 6339 | H107: =SUM(C107:G107) -> 98855
A108: 4310700 | B108: KN Administratiekosten | D108: 378 | E108: 0 | F108: 1491 | G108: 1210 | H108: =SUM(C108:G108) -> 3079
A109: 4310800 | B109: KN Makelaarskosten | D109: 85400 | E109: 39079 | F109: 54700 | G109: 62550 | H109: =SUM(C109:G109) -> 241729
A110: 4311000 | B110: KN Juridische kosten | D110: 12796 | E110: 37004 | F110: 8809 | G110: 4418 | H110: =SUM(C110:G110) -> 63027
A111: 4311800 | B111: KN Advieskosten | D111: 0 | E111: 0 | F111: 0 | G111: 0 | H111: =SUM(C111:G111) -> 0
A112: 4311900 | B112: KN Bankkosten | D112: 1261 | E112: 1391 | F112: 1317 | G112: 1219 | H112: =SUM(C112:G112) -> 5188
A113: 4312600 | B113: KN Agent Fee facility | E113: 20000 | F113: 0 | G113: 0 | H113: =SUM(C113:G113) -> 20000
A114: 4319800 | B114: KN Overige algemene kosten | D114: 974 | E114: 1210 | F114: -1126 | G114: 0 | H114: =SUM(C114:G114) -> 1058
A115: Totaal Algemene kosten | D115: =SUM(D104:D114) -> 193638 | E115: =SUM(E104:E114)+2 -> 149130 | F115: =SUM(F104:F114) -> 106100 | G115: =SUM(G104:G114) -> 85908 | H115: =SUM(C115:G115) -> 534776
A117: 4623000 | B117: FINBL Rente ABN AMRO Bank NV leningen | D117: 0 | E117: 0 | F117: 0 | H117: =SUM(C117:G117) -> 0
A118: 4623001 | B118: FINBL Rente ABN AMRO Bank NV Senior Facility Agreement | D118: 513800 | E118: 486625 | F118: 473890 | G118: 457533 | H118: =SUM(C118:G118) -> 1931848
A119: 4628001 | B119: FINBL Rente LLS QSPESS Limited | D119: 0 | E119: 0 | F119: 0 | G119: 0 | H119: =SUM(C119:G119) -> 0
A120: 4630000 | B120: FINBL Rente belastingen | D120: 0 | E120: 0 | F120: 0 | G120: 0 | H120: =SUM(C120:G120) -> 0
...

Sheet BDO - Q2 2020
C1: Eindbalans 30-06-2019 | D1: Mutaties Q3 2019 | E1: Mutaties Q4 2019 | F1: Mutaties Q1 2020 | G1: Mutaties Q2 2020 | H1: Saldi per 30-06-2020
C2: =$C$4+SUM(C5:C7) -> 121763263 | D2: =$C$4+SUM($C$5:D7) -> 120681248 | E2: =$C$4+SUM($C$5:E7) -> 118697923 | F2: =$C$4+SUM($C$5:F7)+F4 -> 116969418 | G2: =$C$4+SUM($C$5:G7)+F4 -> 115573453
A3: Balans
A4: 1600200 | B4: VG Vastgoedbeleggingen Verkrijgings- of vervaardigingsprijs | C4: 132670468 | D4: 0 | F4: -3658477 | H4: =SUM(C4:G4) -> 129011991
A5: 1600200 | B5: VG Vastgoedbeleggingen Cum afschrijvingen en waardeverm | C5: -9266923 | D5: -653662 | E5: -656408 | F5: -380013 | G5: -630199 | H5: =SUM(C5:G5) -> -11587205 | J5: 540977
A6: 1610803 | B6: VG Comm VG in exploitatie Buitengebruikstellingen aanschaffingswaarde | C6: -1753104 | D6: -462286 | E6: -1443087 | F6: 2472387 | G6: -841866 | H6: =SUM(C6:G6) -> -2027956
A7: 1611003 | B7: VG Comm VG in exploitatie Buitengebruikstellingen cum. afschr. en waardeverm. | C7: 112822 | D7: 33933 | E7: 116170 | F7: -162402 | G7: 76100 | H7: =SUM(C7:G7) -> 176623
A8: Totaal Vastgoedbeleggingen | C8: 0
C9: 0
A10: 1790002 | B10: FVA Latente belastingvordering langlopend | C10: 2706901 | D10: 153794 | E10: -278091 | F10: -293081 | G10: 524916 | H10: =SUM(C10:G10) -> 2814439
A11: Totaal Financiële vaste activa | C11: 0
C12: 0
A13: 2000000 | B13: VOR Debiteuren | C13: 343593 | D13: -93669 | E13: -177050 | F13: 220477 | G13: -208231 | H13: =SUM(C13:G13) -> 85120
A14: 2000300 | B14: VOR Voorziening dubieuze debiteuren | C14: -64501 | D14: 0 | E14: 8960 | F14: 0 | H14: =SUM(C14:G14) -> -55541
A15: Totaal Debiteuren | C15: 0
C16: 0
A17: 2640000 | B17: RC Kortlopend DMRRP INV - I BV | C17: 110497 | D17: 0 | E17: -2023897 | H17: =SUM(C17:G17) -> -1913400
A18: Totaal Rekening-courant aandeelhouder | C18: 0
C19: 0
A20: 2040200 | B20: VOR Te vorderen waarborgsommen kortlopen | C20: 0 | D20: 0 | E20: 5000 | F20: 0 | H20: =SUM(C20:G20) -> 5000
A21: 2040700 | B21: VOR Vooruitbetaalde servicekosten | C21: 15594 | D21: 0 | E21: -11776 | F21: 0 | H21: =SUM(C21:G21) -> 3818
A22: 2040900 | B22: VOR Vooruitbetaalde overige kosten | C22: 0 | D22: 0 | E22: 425 | F22: 0 | G22: =I88+I90+I91+I105+I113 -> 407396 | H22: =SUM(C22:G22) -> 407821
A23: Totaal overige vorderingen | C23: 0
C24: 0
A25: 2300000 | B25: LM Kruisposten | C25: -3338 | D25: 3338 | E25: 0 | G25: 0 | H25: =SUM(C25:G25) -> 0
A26: 2400200 | B26: LM ABN AMRO Bank Disposal NL58 ABNA 0818 9180 39 | C26: 80041 | D26: 649658 | E26: 1729271 | F26: -1031638 | G26: -1408139 | H26: =SUM(C26:G26) -> 19193
A27: 2400201 | B27: LM ABN AMRO Bank Deposit NL57 ABNA 0541 6205 68 | C27: 759 | D27: 12154 | E27: 74896 | F27: 1058693 | G27: -1109732 | H27: =SUM(C27:G27) -> 36770
A28: 2400202 | B28: LM ABN AMRO Bank General NL93 ABNA 0541 6132 27 | C28: 6031 | D28: 785758 | E28: -19584 | F28: -29065 | G28: -50664 | H28: =SUM(C28:G28) -> 692476
A29: 2400203 | B29: LM ABN AMRO Bank Maintres NL04 ABNA 0541 6188 06 | C29: 646236 | D29: -62925 | E29: 66151 | F29: -46640 | G29: -159674 | H29: =SUM(C29:G29) -> 443148
A30: 2400204 | B30: LM ABN AMRO Bank Rent NL46 ABNA 0541 6088 35 | C30: 1028304 | D30: -364896 | E30: 1098220 | F30: -73423 | G30: -420964 | H30: =SUM(C30:G30) -> 1267241
A31: 2400205 | B31: LM ABN AMRO Bank SR EXP NL88 ABNA 0541 6205 92 | C31: 116539 | D31: -115700 | E31: 194761 | F31: 114437 | G31: -265290 | H31: =SUM(C31:G31) -> 44747
A32: Totaal Liquide middelen | C32: 0
C33: 0
A34: 1000002 | B34: EV Normale aandelen Saldo | C34: -1 | D34: 0 | E34: 0 | F34: 0 | H34: =SUM(C34:G34) -> -1
A35: 1100000 | B35: EV Agioreserve Agio aandelen | C35: -19431219 | D35: 0 | E35: 0 | F35: 100000 | H35: =SUM(C35:G35) -> -19331219
A36: 1160000 | B36: EV Overige reserve Reserve aandelen | C36: 13633366 | D36: 0 | E36: 0 | F36: 0 | H36: =SUM(C36:G36) -> 13633366
A37: 1160100 | B37: EV Overige reserve Dividenduitkeringen aandelen | C37: 535000 | D37: 285500 | E37: 235000 | F37: 1510938 | G37: 1397717 | H37: =SUM(C37:G37) -> 3964155
A38: Totaal Eigen vermogen | C38: 0
C39: 0
A40: 1930001 | B40: LLS Hoofdsom ABN AMRO Bank NV Senior Facility Agreement | C40: -130000000 | D40: 0 | E40: 0 | F40: 0 | H40: =SUM(C40:G40) -> -130000000
A41: 1930101 | B41: LLS Cum aflossingen ABN AMRO Bank NV Senior Facility Agreement | C41: 9763205 | D41: 601184 | E41: 601184 | F41: 2258971 | G41: 3569138 | H41: =SUM(C41:G41) -> 16793682
A42: 1930201 | B42: LLS Kortlopend deel ABN AMRO Bank NV Senior Facility Agreement | C42: 0 | D42: 0 | E42: 0 | F42: 0 | H42: =SUM(C42:G42) -> 0
A43: Totaal Langlopende schulden | C43: 0
C44: 0
A45: 2730000 | B45: KLS Crediteuren | C45: -201674 | D45: 28193 | E45: -55987 | F45: 17250 | G45: 900 | H45: =SUM(C45:G45) -> -211318
A46: 2730001 | B46: KLS Crediteuren intercompany | C46: 0 | D46: 0 | E46: 0 | F46: 0 | H46: =SUM(C46:F46) -> 0
A47: Totaal Crediteuren | C47: 0
C48: 0 | H48: =SUM(C48:E48) -> 0
A49: 2512100 | B49: BEL Afgedragen/ontvangen BTW | C49: -3707 | D49: -19 | E49: -204 | F49: 17 | G49: 271 | H49: =SUM(C49:G49) -> -3642
A50: 2530000 | B50: BEL Te betalen vennootschapsbelasting | C50: -363270 | D50: -74792 | E50: 438062 | F50: 0 | G50: 0 | H50: =SUM(C50:G50) -> 0
A51: 2550000 | B51: BEL Te betalen overige belastingen | C51: 189758 | D51: -94878 | E51: -94878 | F51: 0 | G51: 0 | H51: =SUM(C51:G51) -> 2
A52: Totaal Belastingen | C52: 0
C53: 0
A54: 2740300 | B54: KLS Te betalen waarborgsommen kortlopend | C54: -691871 | D54: -8607 | E54: -10299 | F54: 10687 | G54: -8611 | H54: =SUM(C54:G54) -> -708701
A55: 2740500 | B55: KLS Te betalen accountants- en administratiekosten | C55: -22500 | D55: 0 | E55: 0 | F55: 0 | H55: =SUM(C55:G55) -> -22500
A56: 2740600 | B56: KLS Te betalen rente | C56: 0 | D56: 0 | E56: 0 | F56: -457533 | G56: 457533 | H56: =SUM(C56:G56) -> 0
A57: 2740700 | B57: KLS Te betalen verzekeringen | C57: 31808 | D57: -15903 | E57: -15903 | F57: 0 | H57: =SUM(C57:G57) -> 2
A58: 2741000 | B58: KLS Te betalen servicekosten | C58: 0 | D58: 0 | E58: -29200 | F58: 0 | H58: =SUM(C58:G58) -> -29200
A59: 2741001 | B59: KLS Te betalen exploitatiekosten | C59: 0 | D59: 0 | E59: -2118 | F59: 0 | H59: =SUM(C59:G59) -> -2118
A60: 2741002 | B60: KLS Te betalen VVE | C60: 0 | D60: 0 | E60: -1846 | F60: 0 | H60: =SUM(C60:G60) -> -1846
A61: 2741004 | B61: KLS Te betalen Hoen | C61: -79559 | D61: 38680 | E61: 61 | F61: 483 | G61: 119 | H61: =SUM(C61:G61) -> -40216
A62: 2741005 | B62: KLS Te betalen managementvergoedingen | C62: 0 | D62: 0 | E62: 0 | F62: 0 | H62: =SUM(C62:G62) -> 0
A63: 2741200 | B63: KLS Te betalen overige kosten | C63: 0 | D63: 20000 | F63: 0 | G63: -40000 | H63: =SUM(C63:G63) -> -20000
A64: 2741900 | B64: KLS Nog uit te zoeken posten MT940 | C64: 163 | D64: 0 | E64: -162 | F64: 851 | G64: -16811 | H64: =SUM(C64:G64) -> -15959
A65: 2742200 | B65: KLS Vooruitontvangen bedragen | C65: -109418 | D65: =-20427-5 -> -20432 | E65: -17605 | F65: -5561 | G65: 21998 | H65: =SUM(C65:G65) -> -131018 | I65: =SUM(H4:H65)-'Management Cijfers - Q2 2025'!AA19 -> 1038930.7
A66: Totaal Overige schulden | C66: 0
G68: =G70*4 -> -11332784
A69: Winst- en verliesrekening (baten zijn positief, kosten negatief) | F69: =F72/F70-1 -> -0.02427817 | G69: =G72/G70-1 -> -0.025098864
A70: 8000003 | B70: OPB Netto-omzet Theoretische huuropbrengsten | D70: -2864512 | E70: -2858133 | F70: -2847208 | G70: -2833196 | H70: =SUM(C70:G70) -> -11403049
A71: 8000004 | B71: OPB Netto-omzet Leegstand huuropbrengsten | D71: 66870 | E71: 63770 | F71: 69125 | G71: 71110 | H71: =SUM(C71:G71) -> 270875
A72: Totaal Netto-omzet | D72: =SUM(D70:D71) -> -2797642 | E72: =SUM(E70:E71) -> -2794363 | F72: =SUM(F70:F71) -> -2778083 | G72: =SUM(G70:G71) -> -2762086 | H72: =SUM(C72:G72) -> -11132174
A74: 8400600 | B74: OPB Overige bedrijfsopbrengsten Totale servicekosten | D74: -173416 | E74: -173087 | F74: -172417 | G74: -171527 | H74: =SUM(C74:G74) -> -690447
A75: 8400700 | B75: OPB Overige bedrijfsopbrengsten Servicekosten leegstand | D75: 8357 | E75: 29682 | F75: 10767 | G75: 3357 | H75: =SUM(C75:G75) -> 52163
A76: 8400800 | B76: OPB Overige bedrijfsopbrengsten Gerealiseerde servicekosten | D76: 162849 | E76: 121812 | F76: 133343 | G76: 284624 | H76: =SUM(C76:G76) -> 702628
A77: Totaal Overige bedrijfsopbrengsten | D77: =SUM(D74:D76) -> -2210 | E77: =SUM(E74:E76) -> -21593 | F77: =SUM(F74:F76) -> -28307 | G77: =SUM(G74:G76) -> 116454 | H77: =SUM(C77:G77) -> 64344
A79: 4051400 | B79: KN Diensten door derden | D79: 121669 | E79: 121336 | F79: 120736 | G79: 120105 | H79: =SUM(C79:G79) -> 483846
A80: Totaal overige personeelskosten | D80: =SUM(D79) -> 121669 | E80: =SUM(E79) -> 121336 | F80: =SUM(F79) -> 120736 | G80: =SUM(G79) -> 120105 | H80: =SUM(C80:G80) -> 483846
A82: 4730000 | B82: AFKN Afschrijvingskosten Vastgoedbeleggingen | D82: 653662 | E82: 656408 | F82: 642938 | G82: =630199+I86 -> 783814.32 | H82: =SUM(C82:G82) -> 2736822.3
A83: 4730200 | B83: AFKN Boekresultaat Vastgoedbeleggingen | D83: -485647 | E83: -1058583 | F83: -1206433 | G83: -531244 | H83: =SUM(C83:G83) -> -3281907
A84: Totaal Afschrijvingen vastgoedbeleggingen | D84: =SUM(D82:D83) -> 168015 | E84: =SUM(E82:E83) -> -402175 | F84: =SUM(F82:F83) -> -563495 | G84: =SUM(G82:G83) -> 252570.32 | H84: =SUM(C84:G84) -> -545084.68
A86: 4100400 | B86: KN Onderhoud gebouwen | D86: 473207 | E86: =38004+J5 -> 578981 | F86: 491958 | G86: =609565-I86 -> 455949.68 | H86: =SUM(C86:G86) -> 2000095.7 | I86: 153615.32 | J86: Correctie ketels
A87: 4100410 | B87: Verhuurdersheffing | D87: 526216 | E87: 0 | F87: 0 | H87: =SUM(C87:G87) -> 526216
A88: 4100900 | B88: KN Onroerende zaakbelasting | D88: 65301 | E88: 65007 | F88: 47171 | G88: =267546/4 -> 66886.5 | H88: =SUM(C88:G88) -> 244365.5 | I88: =G88*3 -> 200659.5
A89: 4101000 | B89: KN VvE-kosten | D89: 143177 | E89: 5404 | F89: 96652 | G89: 197933 | H89: =SUM(C89:G89) -> 443166
A90: 4101010 | B90: Gemeentelijke belastingen | D90: 29292 | E90: 29292 | F90: 39392 | G90: =90134/4 -> 22533.5 | H90: =SUM(C90:G90) -> 120509.5 | I90: =G90*3 -> 67600.5
A91: 4101020 | B91: Waterschapsbelasting | D91: 18196 | E91: 1661 | F91: 250 | G91: =54928/4 -> 13732 | H91: =SUM(C91:G91) -> 33839 | I91: =G91*3 -> 41196
A92: 4101300 | B92: KN Servicekosten leegstand | D92: 10273 | E92: 18836 | F92: -799 | G92: -820 | H92: =SUM(C92:G92) -> 27490
A93: 4109800 | B93: KN Overige huisvestingskosten | D93: 0 | E93: 2153 | F93: 0 | H93: =SUM(C93:G93) -> 2153
A94: Totaal Huisvestingskosten | D94: =SUM(D86:D93) -> 1265662 | E94: =SUM(E86:E93) -> 701334 | F94: =SUM(F86:F93) -> 674624 | G94: =SUM(G86:G93) -> 756214.68 | H94: =SUM(C94:G94) -> 3397834.7
A96: 4500400 | B96: KN Representatiekosten | D96: 4200 | E96: 0 | F96: 0 | H96: =SUM(C96:G96) -> 4200
A97: 4501200 | B97: KN Mutatie voorziening dubieuze debiteuren | D97: 0 | E97: -8960 | F97: 0 | H97: =SUM(C97:G97) -> -8960
A98: 4501300 | B98: KN Afboeking dubieuze debiteuren | D98: 2282 | E98: 28608 | F98: -164 | G98: 1941 | H98: =SUM(C98:G98) -> 32667
A99: Totaal Verkoopkosten | D99: =SUM(D96:D98) -> 6482 | E99: =SUM(E96:E98) -> 19648 | F99: =SUM(F96:F98) -> -164 | G99: =SUM(G96:G98) -> 1941 | H99: =SUM(C99:G99) -> 27907
A101: 4300500 | B101: KN Incassokosten | D101: 0 | E101: -590 | F101: 0 | H101: =SUM(C101:G101) -> -590
A102: Totaal Kantoorkosten | D102: =SUM(D101) -> 0 | E102: =SUM(E101) -> -590 | F102: =SUM(F101) -> 0 | G102: =SUM(G101) -> 0 | H102: =SUM(C102:G102) -> -590
A104: 4310000 | B104: KN Abonnementen en contributies | D104: 0 | E104: 0 | F104: 4406 | H104: =SUM(C104:G104) -> 4406
A105: 4310400 | B105: KN Assurantiepremie algemeen | D105: 28072 | E105: 13908 | F105: 321 | G105: =103920/4 -> 25980 | H105: =SUM(C105:G105) -> 68281 | I105: =G105*3 -> 77940
A106: 4310500 | B106: KN Managementvergoeding | D106: 5445 | E106: 5445 | F106: 5445 | G106: 5445 | H106: =SUM(C106:G106) -> 21780
A107: 4310600 | B107: KN Accountantskosten | D107: 16927 | E107: 21556 | F107: 6339 | G107: 44292 | H107: =SUM(C107:G107) -> 89114
A108: 4310700 | B108: KN Administratiekosten | D108: 0 | E108: 1491 | F108: 1210 | H108: =SUM(C108:G108) -> 2701
...

Sheet BDO - Q3 2020
C1: Eindbalans 30-09-2019 | D1: Mutaties Q4 2019 | E1: Mutaties Q1 2020 | F1: Mutaties Q2 2020 | G1: Mutaties Q3 | H1: Saldi per 30-09-2020
A3: Balans
A4: 1600200 | B4: VG Vastgoedbeleggingen Verkrijgings- of vervaardigingsprijs | C4: 132670468 | E4: -3658477 | F4: 153567 | H4: =SUM(C4:G4) -> 129165558 | I4: V
A5: 1600200 | B5: VG Vastgoedbeleggingen Cum afschrijvingen en waardeverm | C5: -9920585 | D5: -656408 | E5: -380013 | F5: =-630199 -> -630199 | G5: -653151 | H5: =SUM(C5:G5) -> -12240356 | I5: V
A6: 1610803 | B6: VG Comm VG in exploitatie Buitengebruikstellingen aanschaffingswaarde | C6: -2215390 | D6: -1443087 | E6: 2472387 | F6: -841866 | G6: -947310 | H6: =SUM(C6:G6) -> -2975266 | I6: V
A7: 1611003 | B7: VG Comm VG in exploitatie Buitengebruikstellingen cum. afschr. en waardeverm. | C7: 146755 | D7: 116170 | E7: -162402 | F7: 76100 | G7: 90299 | H7: =SUM(C7:G7) -> 266922 | I7: V
A8: Totaal Vastgoedbeleggingen | C8: 0
C9: 0
A10: 1790002 | B10: FVA Latente belastingvordering langlopend | C10: 2860695 | D10: -278091 | E10: -293081 | F10: 524916 | G10: 118583 | H10: =SUM(C10:G10) -> 2933022 | I10: V
A11: Totaal Financiële vaste activa | C11: 0
C12: 0
A13: 2000000 | B13: VOR Debiteuren | C13: 249924 | D13: -177050 | E13: 220477 | F13: -208231 | G13: 316526 | H13: =SUM(C13:G13) -> 401646 | I13: V
A14: 2000300 | B14: VOR Voorziening dubieuze debiteuren | C14: -64501 | D14: 8960 | E14: 0 | H14: =SUM(C14:F14) -> -55541 | I14: V
A15: Totaal Debiteuren | C15: 0
C16: 0
A17: 2640000 | B17: RC Kortlopend DMRRP INV - I BV | C17: 110497 | D17: -2023897 | G17: 1642583 | H17: =SUM(C17:G17) -> -270817 | I17: V
A18: Totaal Rekening-courant aandeelhouder | C18: 0
C19: 0
A20: 2040200 | B20: VOR Te vorderen waarborgsommen kortlopen | C20: 0 | D20: 5000 | E20: 0 | H20: =SUM(C20:F20) -> 5000 | I20: V
A21: 2040700 | B21: VOR Vooruitbetaalde servicekosten | C21: 15594 | D21: -11776 | E21: 0 | H21: =SUM(C21:F21) -> 3818 | I21: V
A22: 2040900 | B22: VOR Vooruitbetaalde overige kosten | C22: 0 | D22: 425 | E22: -65069 | F22: 360152 | G22: -139615 | H22: =SUM(C22:G22) -> 155893 | I22: V
A23: Totaal overige vorderingen | C23: 0
C24: 0
A25: 2300000 | B25: LM Kruisposten | C25: 0 | D25: 0 | F25: 0 | H25: =SUM(C25:F25) -> 0
A26: 2400200 | B26: LM ABN AMRO Bank Disposal NL58 ABNA 0818 9180 39 | C26: 729699 | D26: 1729271 | E26: -1031638 | F26: -1408139 | G26: -18700 | H26: =SUM(C26:G26) -> 493
A27: 2400201 | B27: LM ABN AMRO Bank Deposit NL57 ABNA 0541 6205 68 | C27: 12913 | D27: 74896 | E27: 1058693 | F27: -1109732 | G27: -19 | H27: =SUM(C27:G27) -> 36751
A28: 2400202 | B28: LM ABN AMRO Bank General NL93 ABNA 0541 6132 27 | C28: 791789 | D28: -19584 | E28: -29065 | F28: -50664 | G28: -417400 | H28: =SUM(C28:G28) -> 275076
A29: 2400203 | B29: LM ABN AMRO Bank Maintres NL04 ABNA 0541 6188 06 | C29: 583311 | D29: 66151 | E29: -46640 | F29: -159674 | G29: 145814 | H29: =SUM(C29:G29) -> 588962
A30: 2400204 | B30: LM ABN AMRO Bank Rent NL46 ABNA 0541 6088 35 | C30: 663408 | D30: 1098220 | E30: -73423 | F30: -420964 | G30: -850699 | H30: =SUM(C30:G30) -> 416542
A31: 2400205 | B31: LM ABN AMRO Bank SR EXP NL88 ABNA 0541 6205 92 | C31: 839 | D31: 194761 | E31: 114437 | F31: -265290 | G31: 133175 | H31: =SUM(C31:G31) -> 177922
A32: Totaal Liquide middelen | C32: 0
C33: 0
A34: 1000002 | B34: EV Normale aandelen Saldo | C34: -1 | D34: 0 | E34: 0 | H34: =SUM(C34:F34) -> -1 | I34: V
A35: 1100000 | B35: EV Agioreserve Agio aandelen | C35: -19431219 | D35: 0 | E35: 100000 | H35: =SUM(C35:F35) -> -19331219 | I35: V
A36: 1160000 | B36: EV Overige reserve Reserve aandelen | C36: 12988943 | D36: 0 | E36: 0 | H36: =SUM(C36:F36) -> 12988943 | I36: V
A37: 1160100 | B37: EV Overige reserve Dividenduitkeringen aandelen | C37: 820500 | D37: 235000 | E37: 1510938 | F37: 1397717 | G37: 207000 | H37: =SUM(C37:G37) -> 4171155 | I37: V
A38: Totaal Eigen vermogen | C38: 0
C39: 0
A40: 1930001 | B40: LLS Hoofdsom ABN AMRO Bank NV Senior Facility Agreement | C40: -130000000 | D40: 0 | E40: 0 | H40: =SUM(C40:F40) -> -130000000 | I40: V
A41: 1930101 | B41: LLS Cum aflossingen ABN AMRO Bank NV Senior Facility Agreement | C41: 10364389 | D41: 601184 | E41: 2258971 | F41: 3569138 | G41: 1387184 | H41: =SUM(C41:G41) -> 18180866 | I41: V
A42: 1930201 | B42: LLS Kortlopend deel ABN AMRO Bank NV Senior Facility Agreement | C42: 0 | D42: 0 | E42: 0 | H42: =SUM(C42:F42) -> 0
A43: Totaal Langlopende schulden | C43: 0
C44: 0
A45: 2730000 | B45: KLS Crediteuren | C45: -173481 | D45: -55987 | E45: 17250 | F45: 900 | G45: -11928 | H45: =SUM(C45:G45) -> -223246
A46: 2730001 | B46: KLS Crediteuren intercompany | C46: 0 | D46: 0 | E46: 0 | H46: =SUM(C46:E46) -> 0
A47: Totaal Crediteuren | C47: 0
C48: 0 | H48: =SUM(C48:D48) -> 0
A49: 2512100 | B49: BEL Afgedragen/ontvangen BTW | C49: -3726 | D49: -204 | E49: 17 | F49: 271 | G49: -22 | H49: =SUM(C49:G49) -> -3664 | I49: V
A50: 2530000 | B50: BEL Te betalen vennootschapsbelasting | C50: -438062 | D50: 438062 | E50: 0 | F50: 0 | H50: =SUM(C50:F50) -> 0
A51: 2550000 | B51: BEL Te betalen overige belastingen | C51: 94880 | D51: -94878 | E51: 0 | F51: 0 | H51: 4 | I51: V
A52: Totaal Belastingen | C52: 0
C53: 0
A54: 2740300 | B54: KLS Te betalen waarborgsommen kortlopend | C54: -700478 | D54: -10299 | E54: 10687 | F54: -8611 | G54: -21291 | H54: =SUM(C54:G54) -> -729992 | I54: V
A55: 2740500 | B55: KLS Te betalen accountants- en administratiekosten | C55: -22500 | D55: 0 | E55: 0 | H55: =SUM(C55:F55) -> -22500
A56: 2740600 | B56: KLS Te betalen rente | C56: 0 | D56: 0 | E56: -457533 | F56: 457533 | H56: =SUM(C56:F56) -> 0
A57: 2740700 | B57: KLS Te betalen verzekeringen | C57: 15905 | D57: -15903 | E57: 0 | H57: 0
A58: 2741000 | B58: KLS Te betalen servicekosten | C58: 0 | D58: -29200 | E58: 0 | H58: =SUM(C58:F58) -> -29200
A59: 2741001 | B59: KLS Te betalen exploitatiekosten | C59: 0 | D59: -2118 | E59: 0 | H59: =SUM(C59:F59) -> -2118
A60: 2741002 | B60: KLS Te betalen VVE | C60: 0 | D60: -1846 | E60: 0 | H60: =SUM(C60:F60) -> -1846
A61: 2741004 | B61: KLS Te betalen Hoen | C61: -40879 | D61: 61 | E61: 483 | F61: 119 | G61: -40364 | H61: =SUM(C61:G61) -> -80580
A62: 2741005 | B62: KLS Te betalen managementvergoedingen | C62: 0 | D62: 0 | E62: 0 | H62: =SUM(C62:F62) -> 0
A63: 2741200 | B63: KLS Te betalen overige kosten | C63: 20000 | E63: 0 | F63: -20000 | G63: 20000 | H63: =SUM(C63:G63) -> 20000
A64: 2741900 | B64: KLS Nog uit te zoeken posten MT940 | C64: 163 | D64: -162 | E64: 851 | F64: -16811 | G64: 15046 | H64: =SUM(C64:G64) -> -913
A65: 2742200 | B65: KLS Vooruitontvangen bedragen | C65: -129850 | D65: -17605 | E65: -5561 | F65: 21998 | G65: -5661 | H65: =SUM(C65:G65) -> -136679 | I65: V
A66: Totaal Overige schulden | C66: 0
E68: =E70*4 -> -11388832 | F68: =F70*4 -> -11332784 | G68: =G70*4 -> -11305856 | H68: =-11610000/4 -> -2902500
A69: Winst- en verliesrekening (baten zijn positief, kosten negatief)
A70: 8000003 | B70: OPB Netto-omzet Theoretische huuropbrengsten | D70: -2858133 | E70: -2847208 | F70: -2833196 | G70: -2826464 | H70: =SUM(C70:G70) -> -11365001
A71: 8000004 | B71: OPB Netto-omzet Leegstand huuropbrengsten | D71: 63770 | E71: 69125 | F71: 71110 | G71: 63061 | H71: =SUM(C71:G71) -> 267066
A72: Totaal Netto-omzet | D72: =SUM(D70:D71) -> -2794363 | E72: =SUM(E70:E71) -> -2778083 | F72: =SUM(F70:F71) -> -2762086 | G72: =SUM(G70:G71) -> -2763403 | H72: =SUM(H70:H71) -> -11097935
E73: =1-(E72/E70) -> 0.02427817
A74: 8400600 | B74: OPB Overige bedrijfsopbrengsten Totale servicekosten | D74: -173087 | E74: -172417 | F74: -171527 | G74: -172398 | H74: =SUM(C74:G74) -> -689429
A75: 8400700 | B75: OPB Overige bedrijfsopbrengsten Servicekosten leegstand | D75: 29682 | E75: 10767 | F75: 3357 | G75: 7281 | H75: =SUM(C75:G75) -> 51087
A76: 8400800 | B76: OPB Overige bedrijfsopbrengsten Gerealiseerde servicekosten | D76: 121812 | E76: 133343 | F76: 284624 | G76: 127725 | H76: =SUM(C76:G76) -> 667504
A77: Totaal Overige bedrijfsopbrengsten | D77: =SUM(D74:D76) -> -21593 | E77: =SUM(E74:E76) -> -28307 | F77: =SUM(F74:F76) -> 116454 | G77: =SUM(G74:G76) -> -37392 | H77: =SUM(H74:H76) -> 29162
A79: 4051400 | B79: KN Diensten door derden | D79: 121336 | E79: 120736 | F79: 120105 | G79: 119839 | H79: =SUM(C79:G79) -> 482016
A80: Totaal overige personeelskosten | D80: =SUM(D79) -> 121336 | E80: =SUM(E79) -> 120736 | F80: =SUM(F79) -> 120105 | G80: =SUM(G79) -> 119839 | H80: =SUM(H79) -> 482016
A82: 4730000 | B82: AFKN Afschrijvingskosten Vastgoedbeleggingen | D82: 656408 | E82: 642938 | F82: =630199 -> 630199 | G82: 653151 | H82: =SUM(C82:G82) -> 2582696
A83: 4730200 | B83: AFKN Boekresultaat Vastgoedbeleggingen | D83: -1058583 | E83: -1206433 | F83: -531244 | G83: -636242 | H83: =SUM(C83:G83) -> -3432502
A84: Totaal Afschrijvingen vastgoedbeleggingen | D84: =SUM(D82:D83) -> -402175 | E84: =SUM(E82:E83) -> -563495 | F84: =SUM(F82:F83) -> 98955 | G84: =SUM(G82:G83) -> 16909 | H84: =SUM(H82:H83) -> -849806
A86: 4100400 | B86: KN Onderhoud gebouwen | D86: =38004+540977 -> 578981 | E86: 491958 | F86: =455997 -> 455997 | G86: 204327 | H86: =SUM(C86:G86) -> 1731263
A87: 4100410 | B87: Verhuurdersheffing | D87: 0 | G87: 531958 | H87: =SUM(C87:G87) -> 531958
A88: 4100900 | B88: KN Onroerende zaakbelasting | D88: 65007 | E88: 75792 | F88: 79670 | G88: 78467 | H88: =SUM(C88:G88) -> 298936
A89: 4101000 | B89: KN VvE-kosten | D89: 5404 | E89: 96652 | F89: 197933 | G89: 136830 | H89: =SUM(C89:G89) -> 436819
A90: 4101010 | B90: Gemeentelijke belastingen | D90: 29292 | E90: 32166 | F90: 33030 | G90: 32166 | H90: =SUM(C90:G90) -> 126654
A91: 4101020 | B91: Waterschapsbelasting | D91: 1661 | E91: 17945 | F91: 17695 | G91: 19123 | H91: =SUM(C91:G91) -> 56424
A92: 4101300 | B92: KN Servicekosten leegstand | D92: 18836 | E92: -801 | F92: -820 | G92: 45430 | H92: =SUM(C92:G92) -> 62645
A93: 4109800 | B93: KN Overige huisvestingskosten | D93: 2153 | E93: 0 | H93: =SUM(C93:F93) -> 2153
A94: Totaal Huisvestingskosten | D94: =SUM(D86:D93) -> 701334 | E94: =SUM(E86:E93) -> 713712 | F94: =SUM(F86:F93) -> 783505 | G94: =SUM(G86:G93) -> 1048301 | H94: =SUM(H86:H93) -> 3246852
A96: 4500400 | B96: KN Representatiekosten | D96: 0 | E96: 0 | H96: =SUM(C96:F96) -> 0
A97: 4501200 | B97: KN Mutatie voorziening dubieuze debiteuren | D97: -8960 | E97: 0 | H97: =SUM(C97:G97) -> -8960
A98: 4501300 | B98: KN Afboeking dubieuze debiteuren | D98: 28608 | E98: -164 | F98: 1941 | G98: 4198 | H98: =SUM(C98:G98) -> 34583
A99: Totaal Verkoopkosten | D99: =SUM(D96:D98) -> 19648 | E99: =SUM(E96:E98) -> -164 | F99: =SUM(F96:F98) -> 1941 | G99: =SUM(G96:G98) -> 4198 | H99: =SUM(H96:H98) -> 25623
A101: 4300500 | B101: KN Incassokosten | D101: -590 | E101: 0 | G101: 950 | H101: =SUM(C101:G101) -> 360
A102: Totaal Kantoorkosten | D102: =SUM(D101) -> -590 | E102: =SUM(E101) -> 0 | F102: =SUM(F101) -> 0 | G102: =SUM(G101) -> 950 | H102: =SUM(H101) -> 360
A104: 4310000 | B104: KN Abonnementen en contributies | D104: 0 | E104: 4406 | H104: =SUM(C104:F104) -> 4406
A105: 4310400 | B105: KN Assurantiepremie algemeen | D105: 13908 | E105: 26301 | F105: 25980 | G105: 25980 | H105: =SUM(C105:G105) -> 92169
A106: 4310500 | B106: KN Managementvergoeding | D106: 5445 | E106: 5445 | F106: 5445 | G106: 5445 | H106: =SUM(C106:G106) -> 21780
A107: 4310600 | B107: KN Accountantskosten | D107: 21556 | E107: 6339 | F107: 44292 | G107: 24945 | H107: =SUM(C107:G107) -> 97132
A108: 4310700 | B108: KN Administratiekosten | D108: 1491 | E108: 1210 | G108: 2420 | H108: =SUM(C108:G108) -> 5121
...

Sheet BDO - Q4 2020
C1: Eindbalans 31-12-2019 | D1: Mutaties Q1 2020 | E1: Mutaties Q2 2020 | F1: Mutaties Q3 | G1: Mutaties Q4 | H1: Saldi per 31-12-2020
A3: Balans
A4: 1600200 | B4: VG Vastgoedbeleggingen Verkrijgings- of vervaardigingsprijs | C4: 133211445 | D4: -3658477 | E4: 153567 | G4: 74328 | H4: =SUM(C4:G4) -> 129780863
A5: 1600200 | B5: VG Vastgoedbeleggingen Cum afschrijvingen en waardeverm | C5: -10576993 | D5: -380013 | E5: =-630199 -> -630199 | F5: -653151 | G5: -654632 | H5: =SUM(C5:G5) -> -12894988
A6: 1610803 | B6: VG Comm VG in exploitatie Buitengebruikstellingen aanschaffingswaarde | C6: -3658477 | D6: 2472387 | E6: -841866 | F6: -947310 | G6: -1073484 | H6: =SUM(C6:G6) -> -4048750
A7: 1611003 | B7: VG Comm VG in exploitatie Buitengebruikstellingen cum. afschr. en waardeverm. | C7: 262925 | D7: -162402 | E7: 76100 | F7: 90299 | G7: 110448 | H7: =SUM(C7:G7) -> 377370
A8: Totaal Vastgoedbeleggingen
A10: 1790002 | B10: FVA Latente belastingvordering langlopend | C10: 2582604 | D10: -293081 | E10: 524916 | F10: 118583 | G10: 576960 | H10: =SUM(C10:G10) -> 3509982
A11: Totaal Financiële vaste activa
A13: 2000000 | B13: VOR Debiteuren | C13: 72874 | D13: 220477 | E13: -208231 | F13: 316526 | G13: -108369 | H13: =SUM(C13:G13) -> 293277
A14: 2000300 | B14: VOR Voorziening dubieuze debiteuren | C14: -55541 | D14: 0 | G14: 0 | H14: =SUM(C14:G14) -> -55541
A15: Totaal Debiteuren
A17: 2640000 | B17: RC Kortlopend DMRRP INV - I BV | C17: -1913400 | F17: 1642583 | G17: 1116604 | H17: =SUM(C17:G17) -> 845787
A18: Totaal Rekening-courant aandeelhouder
A20: 2040200 | B20: VOR Te vorderen waarborgsommen kortlopen | C20: 5000 | D20: 0 | H20: =SUM(C20:G20) -> 5000
A21: 2040700 | B21: VOR Vooruitbetaalde servicekosten | C21: 3818 | D21: 0 | H21: =SUM(C21:G21) -> 3818
A22: 2040900 | B22: VOR Vooruitbetaalde overige kosten | C22: 425 | D22: -65069 | E22: 360152 | F22: -139615 | G22: -155468 | H22: =SUM(C22:G22) -> 425
A23: Totaal overige vorderingen
A25: 2300000 | B25: LM Kruisposten | C25: 0 | E25: 0 | H25: =SUM(C25:G25) -> 0
A26: 2400200 | B26: LM ABN AMRO Bank Disposal NL58 ABNA 0818 9180 39 | C26: 2458970 | D26: -1031638 | E26: -1408139 | F26: -18700 | G26: -482 | H26: =SUM(C26:G26) -> 11
A27: 2400201 | B27: LM ABN AMRO Bank Deposit NL57 ABNA 0541 6205 68 | C27: 87809 | D27: 1058693 | E27: -1109732 | F27: -19 | G27: -19 | H27: =SUM(C27:G27) -> 36732
A28: 2400202 | B28: LM ABN AMRO Bank General NL93 ABNA 0541 6132 27 | C28: 772205 | D28: -29065 | E28: -50664 | F28: -417400 | G28: -13600 | H28: =SUM(C28:G28) -> 261476
A29: 2400203 | B29: LM ABN AMRO Bank Maintres NL04 ABNA 0541 6188 06 | C29: 649462 | D29: -46640 | E29: -159674 | F29: 145814 | G29: -495089 | H29: =SUM(C29:G29) -> 93873
A30: 2400204 | B30: LM ABN AMRO Bank Rent NL46 ABNA 0541 6088 35 | C30: 1761630 | D30: -73423 | E30: -420964 | F30: -850699 | G30: 550068 | H30: =SUM(C30:G30) -> 966612
A31: 2400205 | B31: LM ABN AMRO Bank SR EXP NL88 ABNA 0541 6205 92 | C31: 195600 | D31: 114437 | E31: -265290 | F31: 133175 | G31: -24647 | H31: =SUM(C31:G31) -> 153275
A32: Totaal Liquide middelen
A34: 1000002 | B34: EV Normale aandelen Saldo | C34: -1 | D34: 0 | G34: 0 | H34: =SUM(C34:G34) -> -1
A35: 1100000 | B35: EV Agioreserve Agio aandelen | C35: -19431219 | D35: 100000 | G35: 0 | H35: =SUM(C35:G35) -> -19331219
A36: 1160000 | B36: EV Overige reserve Reserve aandelen | C36: 12717900 | D36: 0 | G36: 0 | H36: =SUM(C36:G36) -> 12717900
A37: 1160100 | B37: EV Overige reserve Dividenduitkeringen aandelen | C37: 1055500 | D37: 1510938 | E37: 1397717 | F37: 207000 | G37: 0 | H37: =SUM(C37:G37) -> 4171155
A38: Totaal Eigen vermogen
A40: 1930001 | B40: LLS Hoofdsom ABN AMRO Bank NV Senior Facility Agreement | C40: -130000000 | D40: 0 | E40: 0 | F40: 0 | G40: 0 | H40: =SUM(C40:G40) -> -130000000
A41: 1930101 | B41: LLS Cum aflossingen ABN AMRO Bank NV Senior Facility Agreement | C41: 10965573 | D41: 2258971 | E41: 3569138 | F41: 1387184 | G41: 1984184 | H41: =SUM(C41:G41) -> 20165050
A42: Totaal Langlopende schulden
A44: 2730000 | B44: KLS Crediteuren | C44: -229468 | D44: 17250 | E44: 900 | F44: -11928 | G44: 0 | H44: =SUM(C44:G44) -> -223246
A45: 2730001 | B45: KLS Crediteuren intercompany | C45: 0 | D45: 0 | E45: 0 | F45: 0 | G45: 0 | H45: =SUM(C45:G45) -> 0
A46: Totaal Crediteuren
A48: 2512100 | B48: BEL Afgedragen/ontvangen BTW | C48: -3930 | D48: 17 | E48: 271 | F48: -22 | G48: 2114 | H48: =SUM(C48:G48) -> -1550
A49: 2530000 | B49: BEL Te betalen vennootschapsbelasting | C49: 0 | D49: 0 | E49: 0 | F49: 0 | G49: 0 | H49: =SUM(C49:G49) -> 0
A50: 2550000 | B50: BEL Te betalen overige belastingen | C50: 0 | D50: 0 | E50: 0 | F50: 0 | G50: 0 | H50: =SUM(C50:G50) -> 0
A51: Totaal Belastingen
A53: 2740300 | B53: KLS Te betalen waarborgsommen kortlopend | C53: -710777 | D53: 10687 | E53: -8611 | F53: -21291 | G53: -37329 | H53: =SUM(C53:G53) -> -767321
A54: 2740500 | B54: KLS Te betalen accountants- en administratiekosten | C54: -22500 | D54: 0 | G54: 0 | H54: =SUM(C54:G54) -> -22500
A55: 2740600 | B55: KLS Te betalen rente | C55: 0 | D55: -457533 | E55: 457533 | G55: 0 | H55: =SUM(C55:G55) -> 0
A56: 2740700 | B56: KLS Te betalen verzekeringen | C56: 2 | D56: 0 | G56: -2 | H56: =SUM(C56:G56) -> 0
A57: 2741000 | B57: KLS Te betalen servicekosten | C57: -29200 | D57: 0 | G57: 0 | H57: =SUM(C57:G57) -> -29200
A58: 2741001 | B58: KLS Te betalen exploitatiekosten | C58: -2118 | D58: 0 | G58: 0 | H58: =SUM(C58:G58) -> -2118
A59: 2741002 | B59: KLS Te betalen VVE | C59: -1846 | D59: 0 | G59: 0 | H59: =SUM(C59:G59) -> -1846
A60: 2741004 | B60: KLS Te betalen Hoen | C60: -40818 | D60: 483 | E60: 119 | F60: -40364 | G60: 41453 | H60: =SUM(C60:G60) -> -39127
A61: 2741005 | B61: KLS Te betalen managementvergoedingen | C61: 0 | D61: 0 | E61: 0 | F61: 0 | G61: -2445 | H61: =SUM(C61:G61) -> -2445
A62: 2741200 | B62: KLS Te betalen overige kosten | C62: 20000 | D62: 0 | E62: -20000 | F62: 20000 | G62: 0 | H62: =SUM(C62:G62) -> 20000
A63: 2741900 | B63: KLS Nog uit te zoeken posten MT940 | C63: 1 | D63: 851 | E63: -16811 | F63: 15046 | G63: 913 | H63: =SUM(C63:G63) -> 0
A64: 2742200 | B64: KLS Vooruitontvangen bedragen | C64: -147455 | D64: -5561 | E64: 21998 | F64: -5661 | G64: -9926 | H64: =SUM(C64:G64) -> -146605 | I64: =SUM(H4:H64) -> 5836149
A65: Totaal Overige schulden
A68: Winst- en verliesrekening (baten zijn positief, kosten negatief)
A69: 8000003 | B69: OPB Netto-omzet Theoretische huuropbrengsten | D69: -2847208 | E69: -2833196 | F69: -2826464 | G69: -2904099 | H69: =SUM(C69:G69) -> -11410967
A70: 8000004 | B70: OPB Netto-omzet Leegstand huuropbrengsten | D70: 69125 | E70: 71110 | F70: 63061 | G70: 64143 | H70: =SUM(C70:G70) -> 267439
A71: Totaal Netto-omzet | D71: =SUM(D69:D70) -> -2778083 | E71: =SUM(E69:E70) -> -2762086 | F71: =SUM(F69:F70) -> -2763403 | G71: =SUM(G69:G70) -> -2839956 | H71: =SUM(H69:H70) -> -11143528
A73: 8400600 | B73: OPB Overige bedrijfsopbrengsten Totale servicekosten | D73: -172417 | E73: -171527 | F73: -172398 | G73: -170326 | H73: =SUM(C73:G73) -> -686668
A74: 8400700 | B74: OPB Overige bedrijfsopbrengsten Servicekosten leegstand | D74: 10767 | E74: 3357 | F74: 7281 | G74: 6641 | H74: =SUM(C74:G74) -> 28046
A75: 8400800 | B75: OPB Overige bedrijfsopbrengsten Gerealiseerde servicekosten | D75: 133343 | E75: 284624 | F75: 127725 | G75: 171365 | H75: =SUM(C75:G75) -> 717057
A76: Totaal Overige bedrijfsopbrengsten | D76: =SUM(D73:D75) -> -28307 | E76: =SUM(E73:E75) -> 116454 | F76: =SUM(F73:F75) -> -37392 | G76: =SUM(G73:G75) -> 7680 | H76: =SUM(H73:H75) -> 58435
A78: 4051400 | B78: KN Diensten door derden | D78: 120736 | E78: 120105 | F78: 119839 | G78: 123182 | H78: =SUM(C78:G78) -> 483862
A79: Totaal overige personeelskosten | D79: =SUM(D78) -> 120736 | E79: =SUM(E78) -> 120105 | F79: =SUM(F78) -> 119839 | G79: =SUM(G78) -> 123182 | H79: =SUM(H78) -> 483862
A81: 4730000 | B81: AFKN Afschrijvingskosten Vastgoedbeleggingen | D81: 642938 | E81: =630199 -> 630199 | F81: 653151 | G81: 654632 | H81: =SUM(C81:G81) -> 2580920
A82: 4730200 | B82: AFKN Boekresultaat Vastgoedbeleggingen | D82: -1206433 | E82: -531244 | F82: -636242 | G82: -812075 | H82: =SUM(C82:G82) -> -3185994
D83: =SUM(D81:D82) -> -563495 | E83: =SUM(E81:E82) -> 98955 | F83: =SUM(F81:F82) -> 16909 | G83: =SUM(G81:G82) -> -157443 | H83: =SUM(H81:H82) -> -605074
A85: 4100400 | B85: KN Onderhoud gebouwen | D85: 491958 | E85: =455997 -> 455997 | F85: 204327 | G85: 637420 | H85: =SUM(C85:G85) -> 1789702
A86: 4100410 | B86: Verhuurdersheffing | D86: 0 | E86: 0 | F86: 531958 | G86: 2047 | H86: =SUM(C86:G86) -> 534005
A87: 4100900 | B87: KN Onroerende zaakbelasting | D87: 75792 | E87: 79670 | F87: 78467 | G87: 79424 | H87: =SUM(C87:G87) -> 313353
A88: 4101000 | B88: KN VvE-kosten | D88: 96652 | E88: 197933 | F88: 136830 | G88: 153831 | H88: =SUM(C88:G88) -> 585246
A89: 4101010 | B89: Gemeentelijke belastingen | D89: 32166 | E89: 33030 | F89: 32166 | G89: 32352 | H89: =SUM(C89:G89) -> 129714
A90: 4101020 | B90: Waterschapsbelasting | D90: 17945 | E90: 17695 | F90: 19123 | G90: 20143 | H90: =SUM(C90:G90) -> 74906
A91: 4101300 | B91: KN Servicekosten leegstand | D91: -801 | E91: -820 | F91: 45430 | G91: 5515 | H91: =SUM(C91:G91) -> 49324
A92: 4109800 | B92: KN Overige huisvestingskosten | D92: 0 | G92: 0 | H92: =SUM(C92:G92) -> 0
A93: Totaal Huisvestingskosten | D93: =SUM(D85:D92) -> 713712 | E93: =SUM(E85:E92) -> 783505 | F93: =SUM(F85:F92) -> 1048301 | G93: =SUM(G85:G92) -> 930732 | H93: =SUM(H85:H92) -> 3476250
A95: 4500400 | B95: KN Representatiekosten | D95: 0 | E95: 0 | F95: 0 | G95: 0 | H95: =SUM(C95:G95) -> 0
A96: 4501200 | B96: KN Mutatie voorziening dubieuze debiteuren | D96: 0 | E96: 0 | F96: 0 | G96: 0 | H96: =SUM(C96:G96) -> 0
A97: 4501300 | B97: KN Afboeking dubieuze debiteuren | D97: -164 | E97: 1941 | F97: 4198 | G97: 15255 | H97: =SUM(C97:G97) -> 21230
A98: Totaal Verkoopkosten | D98: =SUM(D95:D97) -> -164 | E98: =SUM(E95:E97) -> 1941 | F98: =SUM(F95:F97) -> 4198 | G98: =SUM(G95:G97) -> 15255 | H98: =SUM(H95:H97) -> 21230
A100: 4300500 | B100: KN Incassokosten | D100: 0 | F100: 950 | G100: 0 | H100: =SUM(C100:G100) -> 950
A101: Totaal Kantoorkosten | D101: =SUM(D100) -> 0 | E101: =SUM(E100) -> 0 | F101: =SUM(F100) -> 950 | G101: =SUM(G100) -> 0 | H101: =SUM(H100) -> 950
A103: 4310000 | B103: KN Abonnementen en contributies | D103: 4406 | E103: 0 | F103: 0 | G103: 0 | H103: =SUM(C103:G103) -> 4406
A104: 4310400 | B104: KN Assurantiepremie algemeen | D104: 26301 | E104: 25980 | F104: 25980 | G104: 22776 | H104: =SUM(C104:G104) -> 101037
A105: 4310500 | B105: KN Managementvergoeding | D105: 5445 | E105: 5445 | F105: 5445 | G105: 5445 | H105: =SUM(C105:G105) -> 21780
A106: 4310600 | B106: KN Accountantskosten | D106: 6339 | E106: 44292 | F106: 24945 | G106: 6639 | H106: =SUM(C106:G106) -> 82215
A107: 4310700 | B107: KN Administratiekosten | D107: 1210 | F107: 2420 | G107: 0 | H107: =SUM(C107:G107) -> 3630
A108: 4310800 | B108: KN Makelaarskosten | D108: 66525 | E108: 57342 | F108: 61064 | G108: 77632 | H108: =SUM(C108:G108) -> 262563
A109: 4311000 | B109: KN Juridische kosten | D109: 4570 | E109: 3745 | F109: -2123 | G109: 5528 | H109: =SUM(C109:G109) -> 11720
A110: 4311800 | B110: KN Advieskosten | D110: 0 | E110: 28435 | G110: 0 | H110: =SUM(C110:G110) -> 28435
A111: 4311900 | B111: KN Bankkosten | D111: 1219 | E111: 1232 | F111: 1227 | G111: 3761 | H111: =SUM(C111:G111) -> 7439
A112: 4312600 | B112: KN Agent Fee facility | D112: 0 | E112: 20000 | F112: 20000 | G112: 0 | H112: =SUM(C112:G112) -> 40000
A113: 4319800 | B113: KN Overige algemene kosten | D113: 0 | E113: 358 | F113: 477 | G113: -922 | H113: =SUM(C113:G113) -> -87
A114: Totaal Algemene kosten | D114: =SUM(D103:D113) -> 116015 | E114: =SUM(E103:E113) -> 186829 | F114: =SUM(F103:F113) -> 139435 | G114: =SUM(G103:G113) -> 120859 | H114: =SUM(H103:H113) -> 563138
A116: 4623001 | B116: FINBL Rente ABN AMRO Bank NV Senior Facility Agreement | D116: 457533 | E116: 450998 | F116: 448423 | G116: 442928 | H116: =SUM(C116:G116) -> 1799882
A117: 4630000 | B117: FINBL Rente belastingen | D117: 0 | E117: 0 | F117: 8219 | G117: 0 | H117: =SUM(C117:G117) -> 8219
A118: 4643000 | B118: FINBL Overige rentelasten | D118: 106683 | E118: 105985 | F118: 106445 | G118: 105740 | H118: =SUM(C118:G118) -> 424853
A119: 4642000 | B119: FINBL overige rentebaten | D119: 0 | E119: 0 | F119: 3012 | G119: 0 | H119: =SUM(C119:G119) -> 3012
A120: Totaal Financiële baten en lasten | D120: =SUM(D116:D119) -> 564216 | E120: =SUM(E116:E119) -> 556983 | F120: =SUM(F116:F119) -> 566099 | G120: =SUM(G116:G119) -> 548668 | H120: =SUM(H116:H119) -> 2235966
A122: 9500000 | B122: VPB Vennootschapsbelasting VPB Huidg jaar | D122: 0 | E122: 0 | F122: 0 | G122: 0 | H122: =SUM(C122:G122) -> 0
...

Sheet BDO - Q1 2021
C1: Eindbalans 31-01-2020 | D1: Mutaties Q2 2020 | E1: Mutaties Q3 2020 | F1: Mutaties Q4 2020 | G1: Mutaties Q1 2021 | H1: Saldi per 31-03-2021
A3: Balans | J3: 449927 | K3: Q4
A4: 1600200 | B4: VG Vastgoedbeleggingen Verkrijgings- of vervaardigingsprijs | C4: 129552968 | D4: 153567 | H4: =SUM(C4:G4) -> 129706535 | J4: 172507 | K4: Q3
A5: 1600200 | B5: VG Vastgoedbeleggingen Cum afschrijvingen en waardeverm | C5: -10957006 | D5: =-630199 -> -630199 | E5: -653151 | F5: -654632 | G5: -277132 | H5: =SUM(C5:G5) -> -13172120
A6: 1610803 | B6: VG Comm VG in exploitatie Buitengebruikstellingen aanschaffingswaarde | C6: -1186090 | D6: -841866 | E6: -947310 | F6: -1073484 | G6: -706761 | H6: =SUM(C6:G6) -> -4755511
A7: 1611003 | B7: VG Comm VG in exploitatie Buitengebruikstellingen cum. afschr. en waardeverm. | C7: 100523 | D7: 76100 | E7: 90299 | F7: 110448 | G7: -303581 | H7: =SUM(C7:G7) -> 73789
A8: Totaal Vastgoedbeleggingen
A10: 1790002 | B10: FVA Latente belastingvordering langlopend | C10: 2289523 | D10: 524916 | E10: 118583 | F10: 576960 | G10: 142740 | H10: =SUM(C10:G10) -> 3652722
A11: Totaal Financiële vaste activa
A13: 2000000 | B13: VOR Debiteuren | C13: 293351 | D13: -208231 | E13: 316526 | F13: -108371 | G13: -341343 | H13: =SUM(C13:G13) -> -48068
A14: 2000300 | B14: VOR Voorziening dubieuze debiteuren | C14: -55541 | F14: 0 | G14: 0 | H14: =SUM(C14:G14) -> -55541
A15: Totaal Debiteuren | J15: =SUM(H4:H31) -> 119283553
J16: =SUM('Management Cijfers - Q2 2025'!AA3:AA9)+'Management Cijfers - Q2 2025'!AA11 -> 1.4800904e+08
A17: 2640000 | B17: RC Kortlopend DMRRP INV - I BV | C17: -1913400 | E17: 1642583 | F17: 1046231 | G17: 436656 | H17: =SUM(C17:G17) -> 1212070 | J17: =J16-J15 -> 28725487
A18: Totaal Rekening-courant aandeelhouder
A20: 2040200 | B20: VOR Te vorderen waarborgsommen kortlopen | C20: 5000 | H20: =SUM(C20:G20) -> 5000
A21: 2040700 | B21: VOR Vooruitbetaalde servicekosten | C21: 3818 | F21: -1022 | G21: -2796 | H21: =SUM(C21:G21) -> 0
A22: 2040900 | B22: VOR Vooruitbetaalde overige kosten | C22: -64644 | D22: 360152 | E22: -139615 | F22: -155413 | G22: 342768 | H22: =SUM(C22:G22) -> 343248
A23: Totaal overige vorderingen
A25: 2300000 | B25: LM Kruisposten | D25: 0 | G25: -343 | H25: =SUM(C25:G25) -> -343
A26: 2400200 | B26: LM ABN AMRO Bank Disposal NL58 ABNA 0818 9180 39 | C26: 1427332 | D26: -1408139 | E26: -18700 | F26: -482 | G26: -11 | H26: =SUM(C26:G26) -> 0
A27: 2400201 | B27: LM ABN AMRO Bank Deposit NL57 ABNA 0541 6205 68 | C27: 1146502 | D27: -1109732 | E27: -19 | F27: -19 | G27: 0 | H27: =SUM(C27:G27) -> 36732
A28: 2400202 | B28: LM ABN AMRO Bank General NL93 ABNA 0541 6132 27 | C28: 743140 | D28: -50664 | E28: -417400 | F28: -13600 | G28: -7131 | H28: =SUM(C28:G28) -> 254345
A29: 2400203 | B29: LM ABN AMRO Bank Maintres NL04 ABNA 0541 6188 06 | C29: 602822 | D29: -159674 | E29: 145814 | F29: -393791 | G29: -99389 | H29: =SUM(C29:G29) -> 95782
A30: 2400204 | B30: LM ABN AMRO Bank Rent NL46 ABNA 0541 6088 35 | C30: 1688207 | D30: -420964 | E30: -850699 | F30: 550068 | G30: 854946 | H30: =SUM(C30:G30) -> 1821558
A31: 2400205 | B31: LM ABN AMRO Bank SR EXP NL88 ABNA 0541 6205 92 | C31: 310037 | D31: -265290 | E31: 133175 | F31: -125945 | G31: 61378 | H31: =SUM(C31:G31) -> 113355
A32: Totaal Liquide middelen
A34: 1000002 | B34: EV Normale aandelen Saldo | C34: -1 | F34: 0 | G34: 0 | H34: =SUM(C34:G34) -> -1
A35: 1100000 | B35: EV Agioreserve Agio aandelen | C35: -19331219 | D35: 100000 | F35: 0 | G35: 0 | H35: =SUM(C35:G35) -> -19231219
A36: 1160000 | B36: EV Overige reserve Reserve aandelen | C36: 11155611 | F36: 0 | G36: 0 | H36: =SUM(C36:G36) -> 11155611
A37: 1160100 | B37: EV Overige reserve Dividenduitkeringen aandelen | C37: 2566438 | D37: 1297717 | E37: 207000 | F37: 0 | G37: 0 | H37: =SUM(C37:G37) -> 4071155
A38: Totaal Eigen vermogen
A40: 1930001 | B40: LLS Hoofdsom ABN AMRO Bank NV Senior Facility Agreement | C40: -130000000 | D40: 0 | E40: 0 | F40: 0 | G40: 0 | H40: =SUM(C40:G40) -> -130000000
A41: 1930101 | B41: LLS Cum aflossingen ABN AMRO Bank NV Senior Facility Agreement | C41: 13224544 | D41: 3569138 | E41: 1387184 | F41: 1984184 | G41: 1540803 | H41: =SUM(C41:G41) -> 21705853
A42: Totaal Langlopende schulden
A44: 2730000 | B44: KLS Crediteuren | C44: -212218 | D44: 900 | F44: -256418.18 | G44: 37465.18 | H44: =SUM(C44:G44) -> -430271
A45: 2730001 | B45: KLS Crediteuren intercompany | C45: 0 | D45: 0 | E45: 0 | F45: 0 | G45: 0 | H45: =SUM(C45:G45) -> 0
A46: Totaal Crediteuren
A48: 2512100 | B48: BEL Afgedragen/ontvangen BTW | C48: -3913 | D48: 271 | E48: -22 | F48: 2114 | G48: 1550 | H48: =SUM(C48:G48) -> 0
A49: 2530000 | B49: BEL Te betalen vennootschapsbelasting | C49: 0 | D49: 0 | E49: 0 | F49: 0 | G49: 0 | H49: =SUM(C49:G49) -> 0
A50: 2550000 | B50: BEL Te betalen overige belastingen | C50: 0 | D50: 0 | E50: 0 | F50: 0 | G50: 0 | H50: =SUM(C50:G50) -> 0
A51: Totaal Belastingen
A53: 2740300 | B53: KLS Te betalen waarborgsommen kortlopend | C53: -700090 | D53: -8611 | E53: -21291 | F53: -37329 | G53: =5524-4 -> 5520 | H53: =SUM(C53:G53) -> -761801
A54: 2740500 | B54: KLS Te betalen accountants- en administratiekosten | C54: -22500 | F54: 0 | G54: 0 | H54: =SUM(C54:G54) -> -22500
A55: 2740600 | B55: KLS Te betalen rente | C55: -457533 | D55: 457533 | F55: 0 | G55: 0 | H55: =SUM(C55:G55) -> 0
A56: 2740700 | B56: KLS Te betalen verzekeringen | C56: 2 | F56: -2 | G56: 0 | H56: =SUM(C56:G56) -> 0
A57: 2741000 | B57: KLS Te betalen servicekosten | C57: -29200 | F57: 10529 | G57: 18671 | H57: =SUM(C57:G57) -> 0
A58: 2741001 | B58: KLS Te betalen exploitatiekosten | C58: -2118 | F58: -4949 | G58: 7067 | H58: =SUM(C58:G58) -> 0
A59: 2741002 | B59: KLS Te betalen VVE | C59: -1846 | F59: 440 | G59: 1406 | H59: =SUM(C59:G59) -> 0
A60: 2741004 | B60: KLS Te betalen Hoen | C60: -40335 | D60: 119 | E60: -40364 | F60: 39007 | G60: -82495 | H60: =SUM(C60:G60) -> -124068
A61: 2741005 | B61: KLS Te betalen managementvergoedingen | C61: 0 | D61: 0 | E61: 0 | F61: 0 | G61: 0 | H61: =SUM(C61:G61) -> 0
A62: 2741200 | B62: KLS Te betalen overige kosten | C62: 20000 | D62: -20000 | E62: 20000 | F62: 0 | G62: 0 | H62: =SUM(C62:G62) -> 20000
A63: 2741900 | B63: KLS Nog uit te zoeken posten MT940 | C63: 852 | D63: -16811 | E63: 15046 | F63: 913 | G63: 0 | H63: =SUM(C63:G63) -> 0
A64: 2742200 | B64: KLS Vooruitontvangen bedragen | C64: -153016 | D64: 21998 | E64: -5661 | F64: -9926 | G64: 146605 | H64: =SUM(C64:G64) -> 0
A65: Totaal Overige schulden
A68: Winst- en verliesrekening (baten zijn positief, kosten negatief)
A69: 8000003 | B69: OPB Netto-omzet Theoretische huuropbrengsten | D69: -2833196 | E69: -2826464 | F69: -2904386 | G69: -2904374 | H69: =SUM(C69:G69) -> -11468420
A70: 8000004 | B70: OPB Netto-omzet Leegstand huuropbrengsten | D70: 71110 | E70: 63061 | F70: 64137 | G70: 54882 | H70: =SUM(C70:G70) -> 253190
A71: Totaal Netto-omzet | D71: =SUM(D69:D70) -> -2762086 | E71: =SUM(E69:E70) -> -2763403 | F71: =SUM(F69:F70) -> -2840249 | G71: =SUM(G69:G70) -> -2849492 | H71: =SUM(H69:H70) -> -11215230
A73: 8400600 | B73: OPB Overige bedrijfsopbrengsten Totale servicekosten | D73: -171527 | E73: -172398 | F73: -168131 | G73: -172328 | H73: =SUM(C73:G73) -> -684384
A74: 8400700 | B74: OPB Overige bedrijfsopbrengsten Servicekosten leegstand | D74: 3357 | E74: 7281 | F74: 21484 | G74: 10569 | H74: =SUM(C74:G74) -> 42691
A75: 8400800 | B75: OPB Overige bedrijfsopbrengsten Gerealiseerde servicekosten | D75: 284624 | E75: 127725 | F75: 95892 | G75: 166069 | H75: =SUM(C75:G75) -> 674310
A76: Totaal Overige bedrijfsopbrengsten | D76: =SUM(D73:D75) -> 116454 | E76: =SUM(E73:E75) -> -37392 | F76: =SUM(F73:F75) -> -50755 | G76: =SUM(G73:G75) -> 4310 | H76: =SUM(H73:H75) -> 32617
A78: 4051400 | B78: KN Diensten door derden | D78: 120105 | E78: 119839 | F78: 123182 | G78: 122866 | H78: =SUM(C78:G78) -> 485992
A79: Totaal overige personeelskosten | D79: =SUM(D78) -> 120105 | E79: =SUM(E78) -> 119839 | F79: =SUM(F78) -> 123182 | G79: =SUM(G78) -> 122866 | H79: =SUM(H78) -> 485992
A81: 4730000 | B81: AFKN Afschrijvingskosten Vastgoedbeleggingen | D81: =630199 -> 630199 | E81: 653151 | F81: 654632 | G81: 654502 | H81: =SUM(C81:G81) -> 2592484
A82: 4730200 | B82: AFKN Boekresultaat Vastgoedbeleggingen | D82: -531244 | E82: -636242 | F82: -812075 | G82: -746028 | H82: =SUM(C82:G82) -> -2725589
A83: Totaal Afschrijvingen vastgoedbeleggingen | D83: =SUM(D81:D82) -> 98955 | E83: =SUM(E81:E82) -> 16909 | F83: =SUM(F81:F82) -> -157443 | G83: =SUM(G81:G82) -> -91526 | H83: =SUM(H81:H82) -> -133105
A85: 4100400 | B85: KN Onderhoud gebouwen | D85: =455997 -> 455997 | E85: 204327 | F85: =458728+J3 -> 908655 | G85: =92418+J4 -> 264925 | H85: =SUM(C85:G85) -> 1833904
A86: 4100410 | B86: Verhuurdersheffing | D86: 0 | E86: 531958 | F86: 2047 | H86: =SUM(C86:G86) -> 534005
A87: 4100900 | B87: KN Onroerende zaakbelasting | D87: 79670 | E87: 78467 | F87: 80316 | G87: 83330 | H87: =SUM(C87:G87) -> 321783
A88: 4101000 | B88: KN VvE-kosten | D88: 197933 | E88: 136830 | F88: 224083 | G88: 173622.82 | H88: =SUM(C88:G88) -> 732468.82
A89: 4101010 | B89: Gemeentelijke belastingen | D89: 33030 | E89: 32166 | F89: 32352 | G89: 31087 | H89: =SUM(C89:G89) -> 128635
A90: 4101020 | B90: Waterschapsbelasting | D90: 17695 | E90: 19123 | F90: 19893 | G90: 4273 | H90: =SUM(C90:G90) -> 60984
A91: 4101300 | B91: KN Servicekosten leegstand | D91: -820 | E91: 45430 | F91: 13605.18 | G91: -90 | H91: =SUM(C91:G91) -> 58125.18
A92: 4109800 | B92: KN Overige huisvestingskosten | F92: 0 | H92: =SUM(C92:G92) -> 0
A93: Totaal Huisvestingskosten | D93: =SUM(D85:D92) -> 783505 | E93: =SUM(E85:E92) -> 1048301 | F93: =SUM(F85:F92) -> 1280951.2 | G93: =SUM(G85:G92) -> 557147.82 | H93: =SUM(H85:H92) -> 3669905
A95: 4500400 | B95: KN Representatiekosten | D95: 0 | E95: 0 | F95: 0 | G95: 0 | H95: =SUM(C95:G95) -> 0
A96: 4501200 | B96: KN Mutatie voorziening dubieuze debiteuren | D96: 0 | E96: 0 | F96: 0 | G96: 0 | H96: =SUM(C96:G96) -> 0
A97: 4501300 | B97: KN Afboeking dubieuze debiteuren | D97: 1941 | E97: 4198 | F97: 15255 | G97: -90 | H97: =SUM(C97:G97) -> 21304
A98: Totaal Verkoopkosten | D98: =SUM(D95:D97) -> 1941 | E98: =SUM(E95:E97) -> 4198 | F98: =SUM(F95:F97) -> 15255 | G98: =SUM(G95:G97) -> -90 | H98: =SUM(H95:H97) -> 21304
A100: 4300500 | B100: KN Incassokosten | D100: 0 | E100: 950 | F100: 990 | G100: 0 | H100: =SUM(C100:G100) -> 1940
A101: Totaal Kantoorkosten | D101: =SUM(D100) -> 0 | E101: =SUM(E100) -> 950 | F101: =SUM(F100) -> 990 | G101: =SUM(G100) -> 0 | H101: =SUM(H100) -> 1940
A103: 4310000 | B103: KN Abonnementen en contributies | D103: 0 | E103: 0 | F103: 0 | H103: =SUM(C103:G103) -> 0
A104: 4310400 | B104: KN Assurantiepremie algemeen | D104: 25980 | E104: 25980 | F104: 22455 | G104: 11205 | H104: =SUM(C104:G104) -> 85620
A105: 4310500 | B105: KN Managementvergoeding | D105: 5445 | E105: 5445 | F105: 5445 | G105: 5445 | H105: =SUM(C105:G105) -> 21780
A106: 4310600 | B106: KN Accountantskosten | D106: 44292 | E106: 13017 | F106: 6639 | G106: 31618 | H106: =SUM(C106:G106) -> 95566
A107: 4310700 | B107: KN Administratiekosten | D107: 0 | E107: 2420 | F107: 0 | G107: 2420 | H107: =SUM(C107:G107) -> 4840
A108: 4310800 | B108: KN Makelaarskosten | D108: 57342 | E108: 61064 | F108: 109673 | G108: 40646 | H108: =SUM(C108:G108) -> 268725
A109: 4311000 | B109: KN Juridische kosten | D109: 3745 | E109: -2123 | F109: 7035 | G109: 2261 | H109: =SUM(C109:G109) -> 10918
A110: 4311800 | B110: KN Advieskosten | D110: 28435 | E110: 0 | F110: 0 | G110: 0 | H110: =SUM(C110:G110) -> 28435
A111: 4311900 | B111: KN Bankkosten | D111: 1232 | E111: 1227 | F111: 3761 | G111: 2007 | H111: =SUM(C111:G111) -> 8227
A112: 4312600 | B112: KN Agent Fee facility | D112: 20000 | E112: 20000 | F112: 0 | G112: 0 | H112: =SUM(C112:G112) -> 40000
A113: 4319800 | B113: KN Overige algemene kosten | D113: 358 | E113: 477 | F113: -934 | G113: -1065 | H113: =SUM(C113:G113) -> -1164
A114: Totaal Algemene kosten | D114: =SUM(D103:D113) -> 186829 | E114: =SUM(E103:E113) -> 127507 | F114: =SUM(F103:F113) -> 154074 | G114: =SUM(G103:G113) -> 94537 | H114: =SUM(H103:H113) -> 562947
G115: 0
A116: 4623001 | B116: FINBL Rente ABN AMRO Bank NV Senior Facility Agreement | D116: 450998 | E116: 448423 | F116: 442928 | G116: 425610 | H116: =SUM(C116:G116) -> 1767959
A117: 4611000 | B117: FINBL Rente RC DMRRP INV - I BV | F117: 70373 | G117: 0 | H117: =SUM(C117:G117) -> 70373
A118: 4630000 | B118: FINBL Rente belastingen | D118: 0 | E118: 8219 | F118: 0 | G118: 0 | H118: =SUM(C118:G118) -> 8219
A119: 4643000 | B119: FINBL Overige rentelasten | D119: 105985 | E119: 106445 | F119: 105740 | G119: 102784 | H119: =SUM(C119:G119) -> 420954
...

Sheet BDO - Q2 2021
C1: Eindbalans per 30-06-2020 | D1: Mutaties Q3 2020 | E1: Mutaties Q4 2020 | F1: Mutaties Q1 2021 | G1: Mutaties Q2 2021 | H1: Saldi per 30-06-2021 | K1: Mutaties Q4 2020 | L1: Mutaties Q1 2021 | M1: Mutaties Q2 2021
A3: Balans
A4: 1600200 | B4: VG Vastgoedbeleggingen Verkrijgings- of vervaardigingsprijs | C4: 129706535 | H4: =SUM(C4:G4)-4048750 -> 125657785 | K4: 977050 | L4: 172507 | M4: 238485
A5: 1600200 | B5: VG Vastgoedbeleggingen Cum afschrijvingen en waardeverm | C5: -11587205 | D5: -653151 | E5: -683661 | F5: -277132 | G5: -667313 | H5: =SUM(C5:G5) -> -13868462
A6: 1610803 | B6: VG Comm VG in exploitatie Buitengebruikstellingen aanschaffingswaarde | C6: -2027956 | D6: -947310 | E6: -1073484 | F6: -706761 | G6: -1597299 | H6: =SUM(C6:G6)+4048750 -> -2304060
A7: 1611003 | B7: VG Comm VG in exploitatie Buitengebruikstellingen cum. afschr. en waardeverm. | C7: 176623 | D7: 90299 | E7: 110448 | F7: -303581 | G7: 170229 | H7: =SUM(C7:G7) -> 244018
A8: Totaal Vastgoedbeleggingen
A10: 1790002 | B10: FVA Latente belastingvordering langlopend | C10: 2814439 | D10: 118583 | E10: 631191 | F10: 142740 | G10: 120923 | H10: =SUM(C10:G10) -> 3827876
A11: Totaal Financiële vaste activa
A13: 2000000 | B13: VOR Debiteuren | C13: 85120 | D13: 316526 | E13: -108371 | F13: -341343 | G13: 281344 | H13: =SUM(C13:G13) -> 233276
A14: 2000300 | B14: VOR Voorziening dubieuze debiteuren | C14: -55541 | E14: 23626 | F14: 0 | G14: 0 | H14: =SUM(C14:G14) -> -31915
A15: Totaal Debiteuren
A17: 2640000 | B17: RC Kortlopend DMRRP INV - I BV | C17: -1913400 | D17: 1642583 | E17: -859900 | F17: 436656 | G17: 550984 | H17: =SUM(C17:G17) -> -143077
A18: Totaal Rekening-courant aandeelhouder
A20: 2040200 | B20: VOR Te vorderen waarborgsommen kortlopen | C20: 5000 | D20: 0 | E20: 0 | F20: 0 | G20: 0 | H20: =SUM(C20:G20) -> 5000
A21: 2040700 | B21: VOR Vooruitbetaalde servicekosten | C21: 3818 | E21: -1022 | F21: -2796 | G21: 0 | H21: =SUM(C21:G21) -> 0
A22: 2040900 | B22: VOR Vooruitbetaalde overige kosten | C22: 295508 | D22: -139615 | E22: -155413 | F22: 342768 | G22: -114416 | H22: =SUM(C22:G22) -> 228832
A23: Totaal overige vorderingen
A25: 2300000 | B25: LM Kruisposten | C25: 0 | F25: -343 | G25: -3777 | H25: =SUM(C25:G25) -> -4120
A26: 2400200 | B26: LM ABN AMRO Bank Disposal NL58 ABNA 0818 9180 39 | C26: 19193 | D26: -18700 | E26: -482 | F26: -11 | G26: 0 | H26: =SUM(C26:G26) -> 0
A27: 2400201 | B27: LM ABN AMRO Bank Deposit NL57 ABNA 0541 6205 68 | C27: 36770 | D27: -19 | E27: -19 | F27: -19 | G27: -19 | H27: =SUM(C27:G27) -> 36694
A28: 2400202 | B28: LM ABN AMRO Bank General NL93 ABNA 0541 6132 27 | C28: 692476 | D28: -417400 | E28: -13600 | F28: -7131 | G28: -37180 | H28: =SUM(C28:G28) -> 217165
A29: 2400203 | B29: LM ABN AMRO Bank Maintres NL04 ABNA 0541 6188 06 | C29: 443148 | D29: 145814 | E29: -393791 | F29: -99389 | G29: 8473 | H29: =SUM(C29:G29) -> 104255
A30: 2400204 | B30: LM ABN AMRO Bank Rent NL46 ABNA 0541 6088 35 | C30: 1267243 | D30: -850699 | E30: 550068 | F30: 854946 | G30: -722443 | H30: =SUM(C30:G30) -> 1099115
A31: 2400205 | B31: LM ABN AMRO Bank SR EXP NL88 ABNA 0541 6205 92 | C31: 44747 | D31: 133175 | E31: -125945 | F31: 61378 | G31: -72522 | H31: =SUM(C31:G31) -> 40833
A32: Totaal Liquide middelen
A34: 1000002 | B34: EV Normale aandelen Saldo | C34: -1 | E34: 0 | F34: 0 | H34: =SUM(C34:G34) -> -1
A35: 1100000 | B35: EV Agioreserve Agio aandelen | C35: -19231219 | E35: 0 | F35: 0 | H35: =SUM(C35:G35) -> -19231219
A36: 1160000 | B36: EV Overige reserve Reserve aandelen | C36: =9733381+3864155 -> 13597536 | E36: 0 | F36: 0 | H36: =SUM(C36:G36) -> 13597536
A37: 1160100 | B37: EV Overige reserve Dividenduitkeringen aandelen | C37: 0 | D37: 207000 | E37: 0 | F37: 0 | G37: 2200000 | H37: =SUM(C37:G37) -> 2407000
A38: Totaal Eigen vermogen
A40: 1930001 | B40: LLS Hoofdsom ABN AMRO Bank NV Senior Facility Agreement | C40: -130000000 | D40: 0 | E40: 0 | F40: 0 | G40: 0 | H40: =SUM(C40:G40) -> -130000000
A41: 1930101 | B41: LLS Cum aflossingen ABN AMRO Bank NV Senior Facility Agreement | C41: 16793682 | D41: 1387184 | E41: 1984184 | F41: 1540803 | G41: 2253796 | H41: =SUM(C41:G41) -> 23959649
A42: Totaal Langlopende schulden
A44: 2730000 | B44: KLS Crediteuren | C44: -211318 | E44: =-342182+85763.82 -> -256418.18 | F44: =123229-85763.82 -> 37465.18 | G44: 411485 | H44: =SUM(C44:G44) -> -18786
A45: 2730001 | B45: KLS Crediteuren intercompany | C45: 0 | D45: 0 | E45: 0 | F45: 0 | G45: 0 | H45: =SUM(C45:G45) -> 0
A46: Totaal Crediteuren
A48: 2512100 | B48: BEL Afgedragen/ontvangen BTW | C48: -3642 | D48: -22 | E48: 2114 | F48: 1550 | G48: -3898 | H48: =SUM(C48:G48) -> -3898
A49: 2530000 | B49: BEL Te betalen vennootschapsbelasting | C49: 0 | D49: 0 | E49: 0 | F49: 0 | G49: 0 | H49: =SUM(C49:G49) -> 0
A50: 2550000 | B50: BEL Te betalen overige belastingen | C50: 0 | D50: 0 | E50: 0 | F50: 0 | G50: 0 | H50: =SUM(C50:G50) -> 0
A51: Totaal Belastingen
A53: 2740300 | B53: KLS Te betalen waarborgsommen kortlopend | C53: -708701 | D53: -21291 | E53: -37329 | F53: =5524-2 -> 5522 | G53: =-1404+2 -> -1402 | H53: =SUM(C53:G53) -> -763201
A54: 2740500 | B54: KLS Te betalen accountants- en administratiekosten | C54: -22500 | E54: 0 | F54: 0 | G54: 0 | H54: =SUM(C54:G54) -> -22500
A55: 2740600 | B55: KLS Te betalen rente | C55: 0 | E55: 0 | F55: 0 | G55: 0 | H55: =SUM(C55:G55) -> 0
A56: 2740700 | B56: KLS Te betalen verzekeringen | C56: 2 | E56: -2 | F56: -14411 | G56: 70849 | H56: =SUM(C56:G56) -> 56438
A57: 2741000 | B57: KLS Te betalen servicekosten | C57: -29200 | E57: 45129 | F57: -15929 | G57: 0 | H57: =SUM(C57:G57) -> 0
A58: 2741001 | B58: KLS Te betalen exploitatiekosten | C58: -2118 | E58: -4949 | F58: 7067 | G58: 0 | H58: =SUM(C58:G58) -> 0
A59: 2741002 | B59: KLS Te betalen VVE | C59: -1846 | E59: 440 | F59: 1406 | G59: 0 | H59: =SUM(C59:G59) -> 0
A60: 2741004 | B60: KLS Te betalen Hoen | C60: -40216 | D60: -40364 | E60: 39007 | F60: -82495 | G60: -122526 | H60: =SUM(C60:G60) -> -246594
A61: 2741005 | B61: KLS Te betalen managementvergoedingen | C61: 0 | D61: 0 | E61: 0 | F61: 0 | G61: 0 | H61: =SUM(C61:G61) -> 0
A62: 2741200 | B62: KLS Te betalen overige kosten | C62: 0 | D62: 20000 | E62: 0 | F62: 0 | G62: -20000 | H62: =SUM(C62:G62) -> 0
A63: 2741900 | B63: KLS Nog uit te zoeken posten MT940 | C63: -15959 | D63: 15046 | E63: 913 | F63: 0 | G63: 0 | H63: =SUM(C63:G63) -> 0
A64: 2742200 | B64: KLS Vooruitontvangen bedragen | C64: -131018 | D64: -5661 | E64: -9926 | F64: 146605 | G64: 0 | H64: =SUM(C64:G64) -> 0
A65: Totaal Overige schulden
A68: Winst- en verliesrekening (baten zijn positief, kosten negatief)
A69: 8000003 | B69: OPB Netto-omzet Theoretische huuropbrengsten | D69: -2826464 | E69: -2904386 | F69: -2904374 | G69: -2863530 | H69: =SUM(C69:G69) -> -11498754
A70: 8000004 | B70: OPB Netto-omzet Leegstand huuropbrengsten | D70: 63061 | E70: 64137 | F70: 54882 | G70: 62447 | H70: =SUM(C70:G70) -> 244527
A71: Totaal Netto-omzet | D71: =SUM(D69:D70) -> -2763403 | E71: =SUM(E69:E70) -> -2840249 | F71: =SUM(F69:F70) -> -2849492 | G71: =SUM(G69:G70) -> -2801083 | H71: =SUM(H69:H70) -> -11254227
A73: 8400600 | B73: OPB Overige bedrijfsopbrengsten Totale servicekosten | D73: -172398 | E73: -168131 | F73: -172328 | G73: -164913 | H73: =SUM(C73:G73) -> -677770
A74: 8400700 | B74: OPB Overige bedrijfsopbrengsten Servicekosten leegstand | D74: 7281 | E74: 21484 | F74: 10569 | G74: 5322 | H74: =SUM(C74:G74) -> 44656
A75: 8400800 | B75: OPB Overige bedrijfsopbrengsten Gerealiseerde servicekosten | D75: 127725 | E75: 95892 | F75: 200668 | G75: 155500 | H75: =SUM(C75:G75) -> 579785
A76: Totaal Overige bedrijfsopbrengsten | D76: =SUM(D73:D75) -> -37392 | E76: =SUM(E73:E75) -> -50755 | F76: =SUM(F73:F75) -> 38909 | G76: =SUM(G73:G75) -> -4091 | H76: =SUM(H73:H75) -> -53329
A78: 4051400 | B78: KN Diensten door derden | D78: 119839 | E78: 123182 | F78: 122866 | G78: 121422 | H78: =SUM(C78:G78) -> 487309
A79: Totaal overige personeelskosten | D79: =SUM(D78) -> 119839 | E79: =SUM(E78) -> 123182 | F79: =SUM(F78) -> 122866 | G79: =SUM(G78) -> 121422 | H79: =SUM(H78) -> 487309
A81: 4730000 | B81: AFKN Afschrijvingskosten Vastgoedbeleggingen | D81: 653151 | E81: 683661 | F81: 654502 | G81: 667313 | H81: =SUM(C81:G81) -> 2658627
A82: 4730200 | B82: AFKN Boekresultaat Vastgoedbeleggingen | D82: -636242 | E82: -812075 | F82: -746028 | G82: -1978183 | H82: =SUM(C82:G82) -> -4172528
A83: Totaal Afschrijvingen vastgoedbeleggingen | D83: =SUM(D81:D82) -> 16909 | E83: =SUM(E81:E82) -> -128414 | F83: =SUM(F81:F82) -> -91526 | G83: =SUM(G81:G82) -> -1310870 | H83: =SUM(H81:H82) -> -1513901
A85: 4100400 | B85: KN Onderhoud gebouwen | D85: 204327 | E85: =-68395+K4 -> 908655 | F85: =92418+L4 -> 264925 | G85: =194822+M4 -> 433307 | H85: =SUM(C85:G85) -> 1811214
A86: 4100410 | B86: Verhuurdersheffing | D86: 531958 | E86: 2047 | F86: 0 | G86: 0 | H86: =SUM(C86:G86) -> 534005
A87: 4100900 | B87: KN Onroerende zaakbelasting | D87: 78467 | E87: 80316 | F87: 83330 | G87: 80091 | H87: =SUM(C87:G87) -> 322204
A88: 4101000 | B88: KN VvE-kosten | D88: 136830 | E88: =52555+85763.82 -> 138318.82 | F88: =87859+85763.82 -> 173622.82 | G88: 157568 | H88: =SUM(C88:G88) -> 606339.64
A89: 4101010 | B89: Gemeentelijke belastingen | D89: 32166 | E89: 32352 | F89: 31087 | G89: 31441 | H89: =SUM(C89:G89) -> 127046
A90: 4101020 | B90: Waterschapsbelasting | D90: 19123 | E90: 19893 | F90: 4273 | G90: 9001 | H90: =SUM(C90:G90) -> 52290
A91: 4101300 | B91: KN Servicekosten leegstand | D91: 45430 | E91: =99369-34600 -> 64769 | F91: -90 | G91: -348 | H91: =SUM(C91:G91) -> 109761
A92: 4109800 | B92: KN Overige huisvestingskosten | D92: 0 | E92: 0 | F92: 0 | G92: 0 | H92: =SUM(C92:G92) -> 0
A93: Totaal Huisvestingskosten | D93: =SUM(D85:D92) -> 1048301 | E93: =SUM(E85:E92) -> 1246350.8 | F93: =SUM(F85:F92) -> 557147.82 | G93: =SUM(G85:G92) -> 711060 | H93: =SUM(H85:H92) -> 3562859.6
A95: 4500400 | B95: KN Representatiekosten | D95: 0 | E95: 0 | F95: 0 | H95: =SUM(C95:G95) -> 0
A96: 4501200 | B96: KN Mutatie voorziening dubieuze debiteuren | D96: 0 | E96: -23626 | F96: 0 | G96: 0 | H96: =SUM(C96:G96) -> -23626
A97: 4501300 | B97: KN Afboeking dubieuze debiteuren | D97: 4198 | E97: 15255 | F97: -90 | G97: -2606 | H97: =SUM(C97:G97) -> 16757
A98: Totaal Verkoopkosten | D98: =SUM(D95:D97) -> 4198 | E98: =SUM(E95:E97) -> -8371 | F98: =SUM(F95:F97) -> -90 | G98: =SUM(G95:G97) -> -2606 | H98: =SUM(H95:H97) -> -6869
A100: 4300500 | B100: KN Incassokosten | D100: 950 | E100: 990 | F100: 0 | G100: 300 | H100: =SUM(C100:G100) -> 2240
A101: Totaal Kantoorkosten | D101: =SUM(D100) -> 950 | E101: =SUM(E100) -> 990 | F101: =SUM(F100) -> 0 | G101: =SUM(G100) -> 300 | H101: =SUM(H100) -> 2240
A103: 4310000 | B103: KN Abonnementen en contributies | D103: 0 | E103: 0 | F103: 0 | G103: 0 | H103: =SUM(C103:G103) -> 0
A104: 4310400 | B104: KN Assurantiepremie algemeen | D104: 25980 | E104: 22455 | F104: 25616 | G104: 28130 | H104: =SUM(C104:G104) -> 102181
A105: 4310500 | B105: KN Managementvergoeding | D105: 5445 | E105: 5445 | F105: 5445 | G105: 5445 | H105: =SUM(C105:G105) -> 21780
A106: 4310600 | B106: KN Accountantskosten | D106: 13017 | E106: 6639 | F106: 31618 | G106: 31660 | H106: =SUM(C106:G106) -> 82934
A107: 4310700 | B107: KN Administratiekosten | D107: 2420 | E107: 0 | F107: 2420 | G107: 0 | H107: =SUM(C107:G107) -> 4840
A108: 4310800 | B108: KN Makelaarskosten | D108: 61064 | E108: 109673 | F108: 40646 | G108: 63411 | H108: =SUM(C108:G108) -> 274794
A109: 4311000 | B109: KN Juridische kosten | D109: -2123 | E109: 7035 | F109: 2261 | G109: 8170 | H109: =SUM(C109:G109) -> 15343
A110: 4311800 | B110: KN Advieskosten | D110: 0 | E110: 0 | F110: 0 | G110: 0 | H110: =SUM(C110:G110) -> 0
A111: 4311900 | B111: KN Bankkosten | D111: 1227 | E111: 3761 | F111: 2025 | G111: =1186-3 -> 1183 | H111: =SUM(C111:G111) -> 8196
A112: 4312600 | B112: KN Agent Fee facility | D112: 20000 | E112: 0 | F112: 0 | G112: 20000 | H112: =SUM(C112:G112) -> 40000
A113: 4319800 | B113: KN Overige algemene kosten | D113: 477 | E113: -934 | F113: -1065 | G113: 12363 | H113: =SUM(C113:G113) -> 10841
A114: Totaal Algemene kosten | D114: =SUM(D103:D113) -> 127507 | E114: =SUM(E103:E113) -> 154074 | F114: =SUM(F103:F113) -> 108966 | G114: =SUM(G103:G113) -> 170362 | H114: =SUM(H103:H113) -> 560909
F115: 0
A116: 4623001 | B116: FINBL Rente ABN AMRO Bank NV Senior Facility Agreement | D116: 448423 | E116: 442928 | F116: 425610 | G116: 424302 | H116: =SUM(C116:G116) -> 1741263
A117: 4611000 | B117: FINBL Rente RC DMRRP INV - I BV | E117: 70373 | F117: 0 | G117: 0 | H117: =SUM(C117:G117) -> 70373
A118: 4630000 | B118: FINBL Rente belastingen | D118: 8219 | E118: 0 | F118: 0 | G118: 0 | H118: =SUM(C118:G118) -> 8219
A119: 4643000 | B119: FINBL Overige rentelasten | D119: 106445 | E119: 105740 | F119: 102784 | G119: 103265 | H119: =SUM(C119:G119) -> 418234
A120: 4642000 | B120: FINBL overige rentebaten | D120: 3012 | E120: 0 | F120: 0 | G120: 3574 | H120: =SUM(C120:G120) -> 6586
...

Sheet BDO - Q3 2021
C1: Eindbalans per 30-09-2020 | D1: Mutaties Q4 2020 | E1: Mutaties Q1 2021 | F1: Mutaties Q2 2021 | G1: Mutaties Q3 2021 | H1: Saldi per 30-09-2021 | J1: Mutaties Q4 2020 | K1: Mutaties Q1 2021 | L1: Mutaties Q2 2021 | M1: Mutaties Q3 2021
A3: Balans
A4: 1600200 | B4: VG Vastgoedbeleggingen Verkrijgings- of vervaardigingsprijs | C4: 129706535 | H4: =SUM(C4:G4) -> 129706535 | J4: 977050 | K4: 172507 | L4: 238485 | M4: 230282.95
A5: 1600200 | B5: VG Vastgoedbeleggingen Cum afschrijvingen en waardeverm | C5: -12240356 | D5: -683661 | E5: -277132 | F5: -667313 | G5: -666766 | H5: =SUM(C5:G5) -> -14535228
A6: 1610803 | B6: VG Comm VG in exploitatie Buitengebruikstellingen aanschaffingswaarde | C6: -2975266 | D6: -1073484 | E6: -706761 | F6: -1597299 | G6: -144749 | H6: =SUM(C6:G6) -> -6497559
A7: 1611003 | B7: VG Comm VG in exploitatie Buitengebruikstellingen cum. afschr. en waardeverm. | C7: 266922 | D7: 110448 | E7: -303581 | F7: 170229 | G7: 16814 | H7: =SUM(C7:G7) -> 260832
A8: Totaal Vastgoedbeleggingen
A10: 1790002 | B10: FVA Latente belastingvordering langlopend | C10: 2933022 | D10: 631191 | E10: 142740 | F10: 120923 | G10: 161798 | H10: =SUM(C10:G10) -> 3989674
A11: Totaal Financiële vaste activa
A13: 2000000 | B13: VOR Debiteuren | C13: 401646 | D13: -108371 | E13: -341343 | F13: 281344 | G13: =748300.39+144357.64 -> 892658.03 | H13: =SUM(C13:G13) -> 1125934
B14: Vooruitontvangen op debiteuren | C14: 0 | D14: 0 | E14: 0 | F14: 0 | G14: -144357.64 | H14: =SUM(C14:G14) -> -144357.64
A15: 2000300 | B15: VOR Voorziening dubieuze debiteuren | C15: -55541 | D15: 23626 | E15: 0 | F15: 0 | G15: 0 | H15: =SUM(C15:G15) -> -31915
A16: Totaal Debiteuren | H16: =SUM(C16:G16) -> 0
H17: =SUM(C17:G17) -> 0
A18: 2640000 | B18: RC Kortlopend DMRRP INV - I BV | C18: -270817 | D18: -859900 | E18: 436656 | F18: 550984 | G18: 1407409 | H18: =SUM(C18:G18) -> 1264332
A19: Totaal Rekening-courant aandeelhouder | H19: =SUM(C19:G19) -> 0
H20: =SUM(C20:G20) -> 0
A21: 2040200 | B21: VOR Te vorderen waarborgsommen kortlopen | C21: 5000 | D21: 0 | E21: 0 | F21: 0 | G21: 0 | H21: =SUM(C21:G21) -> 5000
A22: 2040500 | B22: VOR Vooruitbetaalde verzekeringen | C22: 0 | D22: 0 | E22: -14411 | F22: 70849 | G22: -28219.3 | H22: =SUM(C22:G22) -> 28218.7
A23: 2040700 | B23: VOR Vooruitbetaalde servicekosten | C23: 3818 | D23: -1022 | E23: -2796 | F23: 0 | G23: 0 | H23: =SUM(C23:G23) -> 0
A24: 2040900 | B24: VOR Vooruitbetaalde overige kosten | C24: 155893 | D24: -155413 | E24: 198503.49 | F24: -251330.51 | G24: 311027.5 | H24: =SUM(C24:G24) -> 258680.48 | I24: Correctie betreft waterschapsbelasting, welke in Q3 betaald is over de hele periode van 2021. Deze kosten zijn verdeeld over 4 kwartalen.
A25: Totaal overige vorderingen | H25: =SUM(C25:G25) -> 0
H26: =SUM(C26:G26) -> 0
A27: 2300000 | B27: LM Kruisposten | C27: 0 | D27: 0 | E27: -343 | F27: -3777 | G27: -12957.2 | H27: =SUM(C27:G27) -> -17077.2
A28: 2400200 | B28: LM ABN AMRO Bank Disposal NL58 ABNA 0818 9180 39 | C28: 493 | D28: -482 | E28: -11 | F28: 0 | G28: 0.91 | H28: =SUM(C28:G28) -> 0.91
A29: 2400201 | B29: LM ABN AMRO Bank Deposit NL57 ABNA 0541 6205 68 | C29: 36751 | D29: -19 | E29: -19 | F29: -19 | G29: -18.04 | H29: =SUM(C29:G29) -> 36675.96
A30: 2400202 | B30: LM ABN AMRO Bank General NL93 ABNA 0541 6132 27 | C30: 275076 | D30: -13600 | E30: -7131 | F30: -37180 | G30: -53403.02 | H30: =SUM(C30:G30) -> 163761.98
A31: 2400203 | B31: LM ABN AMRO Bank Maintres NL04 ABNA 0541 6188 06 | C31: 588962 | D31: -393791 | E31: -99389 | F31: 8473 | G31: 67284.68 | H31: =SUM(C31:G31) -> 171539.68
A32: 2400204 | B32: LM ABN AMRO Bank Rent NL46 ABNA 0541 6088 35 | C32: 416544 | D32: 550068 | E32: 854946 | F32: -722443 | G32: -877600.44 | H32: =SUM(C32:G32) -> 221514.56
A33: 2400205 | B33: LM ABN AMRO Bank SR EXP NL88 ABNA 0541 6205 92 | C33: 177922 | D33: -125945 | E33: 61378 | F33: -72522 | G33: 32976.39 | H33: =SUM(C33:G33) -> 73809.39
A34: Totaal Liquide middelen | C34: 0
C35: 0
A36: 1000002 | B36: EV Normale aandelen Saldo | C36: -1 | D36: 0 | E36: 0 | F36: 0 | G36: 0 | H36: =SUM(C36:G36) -> -1
A37: 1100000 | B37: EV Agioreserve Agio aandelen | C37: -19231219 | D37: 0 | E37: 0 | F37: 200000 | G37: 0 | H37: =SUM(C37:G37) -> -19031219
A38: 1160000 | B38: EV Overige reserve Reserve aandelen | C38: 12615558 | D38: 0 | E38: 0 | F38: 0 | G38: 0 | H38: =SUM(C38:G38) -> 12615558
A39: 1160100 | B39: EV Overige reserve Dividenduitkeringen aandelen | C39: 207000 | D39: 0 | E39: 0 | F39: 2000000 | G39: 0 | H39: =SUM(C39:G39) -> 2207000
A40: Totaal Eigen vermogen | C40: 0 | H40: =SUM(C40:G40) -> 0
C41: 0 | H41: =SUM(C41:G41) -> 0
A42: 1930001 | B42: LLS Hoofdsom ABN AMRO Bank NV Senior Facility Agreement | C42: -130000000 | D42: 0 | E42: 0 | F42: 0 | G42: 0 | H42: =SUM(C42:G42) -> -130000000
A43: 1930101 | B43: LLS Cum aflossingen ABN AMRO Bank NV Senior Facility Agreement | C43: 18180866 | D43: 1984184 | E43: 1540803 | F43: 2253796 | G43: 889295.98 | H43: =SUM(C43:G43) -> 24848945
A44: Totaal Langlopende schulden | C44: 0 | H44: =SUM(C44:G44) -> 0
C45: 0 | H45: =SUM(C45:G45) -> 0
A46: 2730000 | B46: KLS Crediteuren | C46: -211318 | D46: =-342182+85763.82 -> -256418.18 | E46: =123229-85763.82 -> 37465.18 | F46: 411485 | G46: 6778.95 | H46: =SUM(C46:G46) -> -12007.05
A47: 2730001 | B47: KLS Crediteuren intercompany | C47: 0 | D47: 0 | E47: 0 | F47: 0 | G47: 0 | H47: =SUM(C47:G47) -> 0
A48: Totaal Crediteuren
A50: 2512100 | B50: BEL Afgedragen/ontvangen BTW | C50: -3664 | D50: 2114 | E50: 1550 | F50: -3898 | G50: =-828.56+460 -> -368.56 | H50: =SUM(C50:G50) -> -4266.56
A51: 2530000 | B51: BEL Te betalen vennootschapsbelasting | C51: 0 | D51: 0 | E51: 0 | F51: 0 | G51: 0 | H51: =SUM(C51:G51) -> 0
A52: 2550000 | B52: BEL Te betalen overige belastingen | C52: 0 | D52: 0 | E52: 0 | F52: 0 | G52: 0 | H52: =SUM(C52:G52) -> 0
A53: Totaal Belastingen | H53: =SUM(C53:G53) -> 0
H54: =SUM(C54:G54) -> 0
A55: 2740100 | B55: KLS Vooruitgefactureerde huur | C55: 0 | D55: 0 | E55: 0 | F55: 0 | G55: -990960 | H55: =SUM(C55:G55) -> -990960
A56: 2740300 | B56: KLS Te betalen waarborgsommen kortlopend | C56: -729992 | D56: -37329 | E56: =5524-2 -> 5522 | F56: =-1404+2 -> -1402 | G56: -43086.2 | H56: =SUM(C56:G56) -> -806287.2
A57: 2740500 | B57: KLS Te betalen accountants- en administratiekosten | C57: -22500 | D57: 0 | E57: 0 | F57: 0 | G57: 0 | H57: =SUM(C57:G57) -> -22500
A58: 2740600 | B58: KLS Te betalen rente | C58: 0 | D58: 0 | E58: 0 | F58: 0 | G58: 0 | H58: =SUM(C58:G58) -> 0
A59: 2740700 | B59: KLS Te betalen verzekeringen | C59: 2 | D59: -2 | E59: 0 | F59: 0 | G59: 0 | H59: =SUM(C59:G59) -> 0
A60: 2741000 | B60: KLS Te betalen servicekosten | C60: -29200 | D60: 45129 | E60: -15929 | F60: 0 | G60: 0 | H60: =SUM(C60:G60) -> 0
A61: 2741001 | B61: KLS Te betalen exploitatiekosten | C61: -2118 | D61: -4949 | E61: 7067 | F61: 0 | G61: 0 | H61: =SUM(C61:G61) -> 0
A62: 2741002 | B62: KLS Te betalen VVE | C62: -1846 | D62: 440 | E62: 1406 | F62: - | G62: - | H62: =SUM(C62:G62) -> 0 | I62: Correctie betreft Verhuurdersheffing, welke in Q3 betaald is over de hele periode van 2021. Deze kosten zijn verdeeld over 4 kwartalen.
A63: 2741004 | B63: KLS Te betalen Hoen | C63: -80580 | D63: 39007 | E63: -82495 | F63: -122526 | G63: 121338.8 | H63: =SUM(C63:G63) -> -125255.2
A64: 2741005 | B64: KLS Te betalen managementvergoedingen | C64: 0 | D64: 0 | E64: 0 | F64: 0 | G64: 0 | H64: =SUM(C64:G64) -> 0
A65: 2741200 | B65: KLS Te betalen agency fee | C65: 20000 | D65: 0 | E65: 0 | F65: -20000 | G65: 20000 | H65: =SUM(C65:G65) -> 20000
A66: 2741900 | B66: KLS Nog uit te zoeken posten MT940 | C66: -913 | D66: 913 | E66: 0 | F66: 0 | G66: 0 | H66: =SUM(C66:G66) -> 0
A67: 2742200 | B67: KLS Vooruitontvangen bedragen | C67: -136679 | D67: -9926 | E67: 146605 | F67: 0 | G67: 0 | H67: =SUM(C67:G67) -> 0
A68: Totaal Overige schulden
F70: =F74/F72-1 -> -0.021807699 | G70: =G74/G72-1 -> -0.020851622
A71: Winst- en verliesrekening (baten zijn positief, kosten negatief) | J71: Rent roll oct 21 / 4
A72: 8000003 | B72: OPB Netto-omzet Theoretische huuropbrengsten | D72: -2904386 | E72: -2904374 | F72: -2863530 | G72: -2860507 | H72: =SUM(C72:G72) -> -11532797 | J72: 2868597.9 | K72: =-J72+G72+F72+E72 -> -11497009
A73: 8000004 | B73: OPB Netto-omzet Leegstand huuropbrengsten | D73: 64137 | E73: 54882 | F73: 62447 | G73: 59646.21 | H73: =SUM(C73:G73) -> 241112.21
A74: Totaal Netto-omzet | D74: =SUM(D72:D73) -> -2840249 | E74: =SUM(E72:E73) -> -2849492 | F74: =SUM(F72:F73) -> -2801083 | G74: =SUM(G72:G73) -> -2800860.8 | H74: =SUM(C74:G74) -> -11291685
A76: 8400600 | B76: OPB Overige bedrijfsopbrengsten Totale servicekosten | D76: -168131 | E76: -172328 | F76: -164913 | G76: -163178 | H76: =SUM(C76:G76) -> -668550
A77: 8400700 | B77: OPB Overige bedrijfsopbrengsten Servicekosten leegstand | D77: 21484 | E77: 10569 | F77: 5322 | G77: 6288.75 | H77: =SUM(C77:G77) -> 43663.75
A78: 8400800 | B78: OPB Overige bedrijfsopbrengsten Gerealiseerde servicekosten | D78: 95892 | E78: 200668 | F78: 155500 | G78: 161869.1 | H78: =SUM(C78:G78) -> 613929.1
A79: Totaal Overige bedrijfsopbrengsten | D79: =SUM(D76:D78) -> -50755 | E79: =SUM(E76:E78) -> 38909 | F79: =SUM(F76:F78) -> -4091 | G79: =SUM(G76:G78) -> 4979.85 | H79: =SUM(C79:G79) -> -10957.15
A81: 4051400 | B81: KN Diensten door derden | D81: 123182 | E81: 122866 | F81: 121422 | G81: 121881.5 | H81: =SUM(C81:G81) -> 489351.5
A82: Totaal overige personeelskosten | D82: =SUM(D81) -> 123182 | E82: =SUM(E81) -> 122866 | F82: =SUM(F81) -> 121422 | G82: =SUM(G81) -> 121881.5 | H82: =SUM(C82:G82) -> 489351.5
A84: 4730000 | B84: AFKN Afschrijvingskosten Vastgoedbeleggingen | D84: 683661 | E84: 654502 | F84: 667313 | G84: 666766 | H84: =SUM(C84:G84) -> 2672242
A85: 4730200 | B85: AFKN Boekresultaat Vastgoedbeleggingen | D85: -812075 | E85: -746028 | F85: -1978183 | G85: -222065 | H85: =SUM(C85:G85) -> -3758351
A86: Totaal Afschrijvingen vastgoedbeleggingen | D86: =SUM(D84:D85) -> -128414 | E86: =SUM(E84:E85) -> -91526 | F86: =SUM(F84:F85) -> -1310870 | G86: =SUM(G84:G85) -> 444701 | H86: =SUM(C86:G86) -> -1086109
A88: 4100400 | B88: KN Onderhoud gebouwen | D88: =-68395+J4 -> 908655 | E88: =92418+K4 -> 264925 | F88: =194822+L4 -> 433307 | G88: =134619.1+M4 -> 364902.05 | H88: =SUM(C88:G88) -> 1971789.1
A89: 4100410 | B89: Verhuurdersheffing | D89: 2047 | E89: 129402.5 | F89: 129402.5 | G89: 129402.5 | H89: =SUM(C89:G89) -> 390254.5 | I89: Correctie betreft Verhuurdersheffing, welke in Q3 betaald is over de hele periode van 2021. Deze kosten zijn verdeeld over 4 kwartalen.
A90: 4100900 | B90: KN Onroerende zaakbelasting | D90: 80316 | E90: 83330 | F90: 80091 | G90: 84680.21 | H90: =SUM(C90:G90) -> 328417.21
A91: 4101000 | B91: KN VvE-kosten | D91: =52555+85763.82 -> 138318.82 | E91: =87859+85763.82 -> 173622.82 | F91: 157568 | G91: 107779.2 | H91: =SUM(C91:G91) -> 577288.84
A92: 4101010 | B92: Gemeentelijke belastingen | D92: 32352 | E92: 31087 | F92: 31441 | G92: 31288.14 | H92: =SUM(C92:G92) -> 126168.14
A93: 4101020 | B93: Waterschapsbelasting | D93: 19893 | E93: =18355+780 -> 19135 | F93: =1582+14862+69 -> 16513 | G93: =42842+9256-37236 -> 14862 | H93: =SUM(C93:G93) -> 70403 | I93: Correctie betreft waterschapsbelasting, welke in Q3 betaald is over de hele periode van 2021. Deze kosten zijn verdeeld over 4 kwartalen.
A94: 4101300 | B94: KN Servicekosten leegstand | D94: =99369-34600 -> 64769 | E94: -90 | F94: -348 | G94: 0 | H94: =SUM(C94:G94) -> 64331
A95: 4109800 | B95: KN Overige huisvestingskosten | D95: 0 | E95: 0 | F95: 0 | G95: 0
A96: Totaal Huisvestingskosten | D96: =SUM(D88:D95) -> 1246350.8 | E96: =SUM(E88:E95) -> 701412.32 | F96: =SUM(F88:F95) -> 847974.5 | G96: =SUM(G88:G95) -> 732914.1 | H96: =SUM(C96:G96) -> 3528651.7
A98: 4500400 | B98: KN Representatiekosten | D98: 0 | E98: 0 | F98: 0 | G98: 0 | H98: =SUM(C98:G98) -> 0
A99: 4501200 | B99: KN Mutatie voorziening dubieuze debiteuren | D99: -23626 | E99: 0 | F99: 0 | G99: 0 | H99: =SUM(C99:G99) -> -23626
A100: 4501300 | B100: KN Afboeking dubieuze debiteuren | D100: 15255 | E100: -90 | F100: -2606 | G100: 461 | H100: =SUM(C100:G100) -> 13020
A101: Totaal Verkoopkosten | D101: =SUM(D98:D100) -> -8371 | E101: =SUM(E98:E100) -> -90 | F101: =SUM(F98:F100) -> -2606 | G101: =SUM(G98:G100) -> 461 | H101: =SUM(C101:G101) -> -10606
A103: 4300500 | B103: KN Incassokosten | D103: 990 | E103: 0 | F103: 300 | G103: 300 | H103: =SUM(C103:G103) -> 1590
A104: Totaal Kantoorkosten | D104: =SUM(D103) -> 990 | E104: =SUM(E103) -> 0 | F104: =SUM(F103) -> 300 | G104: =SUM(G103) -> 300 | H104: =SUM(C104:G104) -> 1590
A106: 4310000 | B106: KN Abonnementen en contributies | D106: 0 | E106: 0 | F106: 0 | G106: 0
A107: 4310400 | B107: KN Assurantiepremie algemeen | D107: 22455 | E107: 25616 | F107: 28130 | G107: 28219.25 | H107: =SUM(C107:G107) -> 104420.25
A108: 4310500 | B108: KN Managementvergoeding | D108: 5445 | E108: 5445 | F108: 5445 | G108: 5445 | H108: =SUM(C108:G108) -> 21780
A109: 4310600 | B109: KN Accountantskosten | D109: 6639 | E109: 31618 | F109: 31660 | G109: 61669.95 | H109: =SUM(C109:G109) -> 131586.95
A110: 4310700 | B110: KN Administratiekosten | D110: 0 | E110: 2420 | F110: 0 | G110: 2420 | H110: =SUM(C110:G110) -> 4840
A111: 4310800 | B111: KN Makelaarskosten | D111: 109673 | E111: 40646 | F111: 63411 | G111: 50119.65 | H111: =SUM(C111:G111) -> 263849.65
A112: 4311000 | B112: KN Juridische kosten | D112: 7035 | E112: 2261 | F112: 8170 | G112: 3422.05 | H112: =SUM(C112:G112) -> 20888.05
...

Sheet BDO - Q4 2021
C1: Eindbalans per 31-12-2020 | D1: Mutaties Q1 2021 | E1: Mutaties Q2 2021 | F1: Mutaties Q3 2021 | G1: Mutaties Q4 | H1: Saldi per 31-12-2021 | K1: Mutaties Q1 2021 | L1: Mutaties Q2 2021 | M1: Mutaties Q3 2021 | N1: Mutaties Q4 2021
A3: Balans
A4: 1600200 | B4: VG Vastgoedbeleggingen Verkrijgings- of vervaardigingsprijs | C4: 130683585 | H4: =SUM(C4:G4) -> 130683585 | K4: 172507 | L4: 238485 | M4: 230282.95 | N4: 606011.02
A5: 1600200 | B5: VG Vastgoedbeleggingen Cum afschrijvingen en waardeverm | C5: -12924017 | D5: -277132 | E5: -667313 | F5: -666766 | G5: -679632 | H5: =SUM(C5:G5) -> -15214860
A6: 1610803 | B6: VG Comm VG in exploitatie Buitengebruikstellingen aanschaffingswaarde | C6: -4048750 | D6: -706761 | E6: -1597299 | F6: -144749 | G6: -856186 | H6: =SUM(C6:G6) -> -7353745 | N6: 47675
A7: 1611003 | B7: VG Comm VG in exploitatie Buitengebruikstellingen cum. afschr. en waardeverm. | C7: 377370 | D7: -303581 | E7: 170229 | F7: 16814 | G7: 102659 | H7: =SUM(C7:G7) -> 363491 | N7: =N4-N6 -> 558336.02
A8: Totaal Vastgoedbeleggingen | C8: 0
C9: 0
A10: 1790002 | B10: FVA Latente belastingvordering langlopend | C10: 3564213 | D10: 142740 | E10: 120923 | F10: 161798 | G10: 140246.2 | H10: =SUM(C10:G10) -> 4129920.2
A11: Totaal Financiële vaste activa | C11: 0
C12: 0
A13: 2000000 | B13: VOR Debiteuren | C13: 293275 | D13: -341343 | E13: 281344 | F13: -100006 | G13: -18687 | H13: =SUM(C13:G13) -> 114583 | I13: Herpresentatie debiteuren > betreft achterstand
B14: Vooruitontvangen op debiteuren | C14: 0 | D14: 0 | E14: 0 | F14: 0 | G14: 0 | H14: =SUM(C14:G14) -> 0
A15: 2000300 | B15: VOR Voorziening dubieuze debiteuren | C15: -31915 | D15: 0 | E15: 0 | F15: 0 | G15: 0 | H15: =SUM(C15:G15) -> -31915
A16: Totaal Debiteuren | C16: 0
C17: 0
A18: 2640000 | B18: RC Kortlopend DMRRP INV - I BV | C18: -1130717 | D18: 436656 | E18: 550984 | F18: 1407409 | G18: 416033.57 | H18: =SUM(C18:G18) -> 1680365.6
A19: Totaal Rekening-courant aandeelhouder
A21: 2040200 | B21: VOR Te vorderen waarborgsommen kortlopen | C21: 5000 | D21: 0 | E21: 0 | F21: 0 | G21: 0 | H21: =SUM(C21:G21) -> 5000
A22: 2040500 | B22: VOR Vooruitbetaalde verzekeringen | C22: 0 | D22: -14411 | E22: 70849 | F22: -28219.3 | G22: -28218.89 | H22: =SUM(C22:G22) -> -0.19
A23: 2040700 | B23: VOR Vooruitbetaalde servicekosten | C23: 2796 | D23: -2796 | E23: 0 | F23: 0 | G23: 0 | H23: =SUM(C23:G23) -> 0
A24: 2040900 | B24: VOR Vooruitbetaalde overige kosten | C24: 480 | D24: =328386-480-127996.51-1406 -> 198503.49 | E24: =-121928-129402.51 -> -251330.51 | F24: =-77180+388207.5 -> 311027.5 | G24: -258680.49 | H24: =SUM(C24:G24) -> -0.01
A25: Totaal overige vorderingen | C25: 0
C26: 0
A27: 2300000 | B27: LM Kruisposten | C27: 0 | D27: -343 | E27: -3775.5 | F27: -12957.2 | G27: 14454.18 | H27: =SUM(C27:G27) -> -2621.52
A28: 2400200 | B28: LM ABN AMRO Bank Disposal NL58 ABNA 0818 9180 39 | C28: 11 | D28: -11 | E28: 0 | F28: 0.91 | G28: -0.38 | H28: =SUM(C28:G28) -> 0.53
A29: 2400201 | B29: LM ABN AMRO Bank Deposit NL57 ABNA 0541 6205 68 | C29: 36732 | D29: -19 | E29: -19 | F29: -18.04 | G29: -18.04 | H29: =SUM(C29:G29) -> 36657.92
A30: 2400202 | B30: LM ABN AMRO Bank General NL93 ABNA 0541 6132 27 | C30: 261476 | D30: -7131 | E30: -37180 | F30: -53403.02 | G30: -8084.34 | H30: =SUM(C30:G30) -> 155677.64
A31: 2400203 | B31: LM ABN AMRO Bank Maintres NL04 ABNA 0541 6188 06 | C31: 195171 | D31: -99389 | E31: 8473 | F31: 67284.68 | G31: -89675.55 | H31: =SUM(C31:G31) -> 81864.13
A32: 2400204 | B32: LM ABN AMRO Bank Rent NL46 ABNA 0541 6088 35 | C32: 966612 | D32: 854946 | E32: -722443 | F32: -877600.44 | G32: 228072.92 | H32: =SUM(C32:G32) -> 449587.48
A33: 2400205 | B33: LM ABN AMRO Bank SR EXP NL88 ABNA 0541 6205 92 | C33: 51977 | D33: 61378 | E33: -72522 | F33: 32976.39 | G33: -48621.34 | H33: =SUM(C33:G33) -> 25188.05
A34: Totaal Liquide middelen | C34: 0
C35: 0
A36: 1000002 | B36: EV Normale aandelen Saldo | C36: -1 | D36: 0 | E36: 0 | F36: 0 | G36: 0 | H36: =SUM(C36:G36) -> -1
A37: 1100000 | B37: EV Agioreserve Agio aandelen | C37: -19231219 | D37: 0 | E37: 200000 | F37: 0 | G37: 0 | H37: =SUM(C37:G37) -> -19031219
A38: 1160000 | B38: EV Overige reserve Reserve aandelen | C38: 11975701 | D38: 0 | E38: 0 | F38: 0 | G38: 0 | H38: =SUM(C38:G38) -> 11975701
A39: 1160100 | B39: EV Overige reserve Dividenduitkeringen aandelen | C39: 207000 | D39: 0 | E39: 2000000 | F39: 0 | G39: 1100000 | H39: =SUM(C39:G39) -> 3307000
A40: Totaal Eigen vermogen | C40: 0
C41: 0
A42: 1930001 | B42: LLS Hoofdsom ABN AMRO Bank NV Senior Facility Agreement | C42: -130000000 | D42: 0 | E42: 0 | F42: 0 | G42: 0 | H42: =SUM(C42:G42) -> -130000000
A43: 1930101 | B43: LLS Cum aflossingen ABN AMRO Bank NV Senior Facility Agreement | C43: 20165050 | D43: 1540803 | E43: 2253796 | F43: 889295.98 | G43: 1579957 | H43: =SUM(C43:G43) -> 26428902
A44: Totaal Langlopende schulden | C44: 0
C45: 0
A46: 2730000 | B46: KLS Crediteuren | C46: -467736.18 | D46: =123229-85763.82 -> 37465.18 | E46: 411485 | F46: 6778.95 | G46: -285240.34 | H46: =SUM(C46:G46) -> -297247.39
A47: 2730001 | B47: KLS Crediteuren intercompany | C47: 0 | D47: 0 | E47: 0 | F47: 0 | G47: 0 | H47: =SUM(C47:G47) -> 0
A48: Totaal Crediteuren | C48: 0
C49: 0
A50: 2512100 | B50: BEL Afgedragen/ontvangen BTW | C50: -1550 | D50: 1550 | E50: -3898 | F50: =-828.56+460 -> -368.56 | G50: -858.91 | H50: =SUM(C50:G50) -> -5125.47
A51: 2530000 | B51: BEL Te betalen vennootschapsbelasting | C51: 0 | D51: 0 | E51: 0 | F51: 0 | G51: 0 | H51: =SUM(C51:G51) -> 0
A52: 2550000 | B52: BEL Te betalen overige belastingen | C52: 0 | D52: 0 | E52: 0 | F52: 0 | G52: 0 | H52: =SUM(C52:G52) -> 0
A53: Totaal Belastingen
A55: 2740100 | B55: KLS Vooruitgefactureerde huur | C55: 0 | D55: 0 | E55: 0 | F55: =-144357.64+1705 -> -142652.64 | G55: =-9268.61-1705 -> -10973.61 | H55: =SUM(C55:G55) -> -153626.25 | I55: Herpresentatie debiteuren > betreft voorstand
A56: 2740300 | B56: KLS Te betalen waarborgsommen kortlopend | C56: -767321 | D56: =5524-2 -> 5522 | E56: =-1404+2 -> -1402 | F56: -43086.2 | G56: -158.33 | H56: =SUM(C56:G56) -> -806445.53
A57: 2740500 | B57: KLS Te betalen accountants- en administratiekosten | C57: -22500 | D57: 0 | E57: 0 | F57: 0 | G57: 0 | H57: =SUM(C57:G57) -> -22500
A58: 2740600 | B58: KLS Te betalen rente | C58: 0 | D58: 0 | E58: 0 | F58: 0 | G58: 0 | H58: =SUM(C58:G58) -> 0
A59: 2740700 | B59: KLS Te betalen verzekeringen | C59: 0 | D59: 0 | E59: 0 | F59: 0 | G59: 0 | H59: =SUM(C59:G59) -> 0
A60: 2741000 | B60: KLS Te betalen servicekosten | C60: 15929 | D60: -15929 | E60: 0 | F60: 0 | G60: 0 | H60: =SUM(C60:G60) -> 0
A61: 2741001 | B61: KLS Te betalen exploitatiekosten | C61: -7067 | D61: 7067 | E61: 0 | F61: 0 | G61: 0 | H61: =SUM(C61:G61) -> 0
A62: 2741002 | B62: KLS Te betalen VVE | C62: -1406 | D62: 1406 | E62: 0 | F62: 0 | G62: 0 | H62: =SUM(C62:G62) -> 0
A63: 2741004 | B63: KLS Te betalen Hoen | C63: -41573 | D63: -82495 | E63: -122526 | F63: 121338.8 | G63: 43720.06 | H63: =SUM(C63:G63) -> -81535.14
A64: 2741005 | B64: KLS Te betalen managementvergoedingen | C64: 0 | D64: 0 | E64: 0 | F64: 0 | G64: 0 | H64: =SUM(C64:G64) -> 0
A65: 2741200 | B65: KLS Te betalen agency fee | C65: 20000 | D65: 0 | E65: -20000 | F65: 20000 | G65: 0 | H65: =SUM(C65:G65) -> 20000
A66: 2741900 | B66: KLS Nog uit te zoeken posten MT940 | C66: 0 | D66: 0 | E66: 0 | F66: 0 | G66: 0 | H66: =SUM(C66:G66) -> 0
A67: 2742200 | B67: KLS Vooruitontvangen bedragen | C67: -146605 | D67: 146605 | E67: 0 | F67: 0 | G67: 0 | H67: =SUM(C67:G67) -> 0
A68: Totaal Overige schulden
A71: Winst- en verliesrekening (baten zijn positief, kosten negatief)
A72: 8000003 | B72: OPB Netto-omzet Theoretische huuropbrengsten | D72: -2904374 | E72: -2863530 | F72: -2860507 | G72: -2862440.4 | H72: =SUM(C72:G72) -> -11490851
A73: 8000004 | B73: OPB Netto-omzet Leegstand huuropbrengsten | D73: 54882 | E73: 62447 | F73: 59646.21 | G73: 39631.63 | H73: =SUM(C73:G73) -> 216606.84
A74: Totaal Netto-omzet | D74: =SUM(D72:D73) -> -2849492 | E74: =SUM(E72:E73) -> -2801083 | F74: =SUM(F72:F73) -> -2800860.8 | G74: =SUM(G72:G73) -> -2822808.8 | H74: =SUM(C74:G74) -> -11274245
A76: 8400600 | B76: OPB Overige bedrijfsopbrengsten Totale servicekosten | D76: -172328 | E76: -164913 | F76: -163178 | G76: -165060.65 | H76: =SUM(C76:G76) -> -665479.65
A77: 8400700 | B77: OPB Overige bedrijfsopbrengsten Servicekosten leegstand | D77: 10569 | E77: 5322 | F77: 6288.75 | G77: 5162.42 | H77: =SUM(C77:G77) -> 27342.17
A78: 8400800 | B78: OPB Overige bedrijfsopbrengsten Gerealiseerde servicekosten | D78: 200668 | E78: 155500 | F78: 161869.1 | G78: 191433.77 | H78: =SUM(C78:G78) -> 709470.87
A79: Totaal Overige bedrijfsopbrengsten | D79: =SUM(D76:D78) -> 38909 | E79: =SUM(E76:E78) -> -4091 | F79: =SUM(F76:F78) -> 4979.85 | G79: =SUM(G76:G78) -> 31535.54 | H79: =SUM(C79:G79) -> 71333.39
A81: 4051400 | B81: KN Diensten door derden | D81: 122866 | E81: 121422 | F81: 121881.5 | G81: 121294.6 | H81: =SUM(C81:G81) -> 487464.1
A82: Totaal overige personeelskosten | D82: =SUM(D81) -> 122866 | E82: =SUM(E81) -> 121422 | F82: =SUM(F81) -> 121881.5 | G82: =SUM(G81) -> 121294.6 | H82: =SUM(C82:G82) -> 487464.1
A84: 4730000 | B84: AFKN Afschrijvingskosten Vastgoedbeleggingen | D84: 654502 | E84: 667313 | F84: 666766 | G84: 679632 | H84: =SUM(C84:G84) -> 2668213
A85: 4730200 | B85: AFKN Boekresultaat Vastgoedbeleggingen | D85: -746028 | E85: -1978183 | F85: -222065 | G85: -1362473 | H85: =SUM(C85:G85) -> -4308749
A86: Totaal Afschrijvingen vastgoedbeleggingen | D86: =SUM(D84:D85) -> -91526 | E86: =SUM(E84:E85) -> -1310870 | F86: =SUM(F84:F85) -> 444701 | G86: =SUM(G84:G85) -> -682841 | H86: =SUM(C86:G86) -> -1640536
A88: 4100400 | B88: KN Onderhoud gebouwen | D88: =92418+K4 -> 264925 | E88: =194822+L4 -> 433307 | F88: =134619.1+M4 -> 364902.05 | G88: =437789.79+N4 -> 1043800.8 | H88: =SUM(C88:G88) -> 2106934.9 | L88: 437789.79
A89: 4100410 | B89: Verhuurdersheffing | D89: 129402.5 | E89: 129402.5 | F89: 129402.5 | G89: 129402.49 | H89: =SUM(C89:G89) -> 517609.99
A90: 4100900 | B90: KN Onroerende zaakbelasting | D90: 83330 | E90: 80091 | F90: 84680.21 | G90: 82972.46 | H90: =SUM(C90:G90) -> 331073.67 | L90: =-57779.9-52965.5 -> -110745.4 | M90: ENVASTGOED IN KOSTEN
A91: 4101000 | B91: KN VvE-kosten | D91: =87859+85763.82 -> 173622.82 | E91: 157568 | F91: 107779.2 | G91: 186235.55 | H91: =SUM(C91:G91) -> 625205.57
A92: 4101010 | B92: Gemeentelijke belastingen | D92: 31087 | E92: 31441 | F92: 31288.14 | G92: 31086.75 | H92: =SUM(C92:G92) -> 124902.89 | L92: =L88+L90 -> 327044.39
A93: 4101020 | B93: Waterschapsbelasting | D93: =18355+780 -> 19135 | E93: =1582+14862+69 -> 16513 | F93: =42842+9256-37236 -> 14862 | G93: 16030.14 | H93: =SUM(D93:G93) -> 66540.14
A94: 4101300 | B94: KN Servicekosten leegstand | D94: -90 | E94: -348 | F94: 0 | G94: -22.71 | H94: =SUM(C94:G94) -> -460.71
A95: 4109800 | B95: KN Overige huisvestingskosten | D95: 0 | E95: 0 | F95: 0 | G95: 0 | H95: =SUM(C95:G95) -> 0
A96: Totaal Huisvestingskosten | D96: =SUM(D88:D95) -> 701412.32 | E96: =SUM(E88:E95) -> 847974.5 | F96: =SUM(F88:F95) -> 732914.1 | G96: =SUM(G88:G95) -> 1489505.5 | H96: =SUM(C96:G96) -> 3771806.4
A98: 4500400 | B98: KN Representatiekosten | D98: 0 | E98: 0 | F98: 0 | G98: 0 | H98: =SUM(C98:G98) -> 0
A99: 4501200 | B99: KN Mutatie voorziening dubieuze debiteuren | D99: 0 | E99: 0 | F99: 0 | G99: 0 | H99: =SUM(C99:G99) -> 0
A100: 4501300 | B100: KN Afboeking dubieuze debiteuren | D100: -90 | E100: -2606 | F100: 461 | G100: 156.38 | H100: =SUM(C100:G100) -> -2078.62
A101: Totaal Verkoopkosten | D101: =SUM(D98:D100) -> -90 | E101: =SUM(E98:E100) -> -2606 | F101: =SUM(F98:F100) -> 461 | G101: =SUM(G98:G100) -> 156.38 | H101: =SUM(C101:G101) -> -2078.62
A103: 4300500 | B103: KN Incassokosten | D103: 0 | E103: 300 | F103: 300 | G103: 340 | H103: =SUM(C103:G103) -> 940
A104: Totaal Kantoorkosten | D104: =SUM(D103) -> 0 | E104: =SUM(E103) -> 300 | F104: =SUM(F103) -> 300 | G104: =SUM(G103) -> 340 | H104: =SUM(C104:G104) -> 940
A106: 4310000 | B106: KN Abonnementen en contributies | D106: 0 | E106: 0 | F106: 0 | G106: 0
A107: 4310400 | B107: KN Assurantiepremie algemeen | D107: 25616 | E107: 28130 | F107: 28219.25 | G107: 29692.1 | H107: =SUM(C107:G107) -> 111657.35
A108: 4310500 | B108: KN Managementvergoeding | D108: 5445 | E108: 5445 | F108: 5445 | G108: 5445 | H108: =SUM(C108:G108) -> 21780
A109: 4310600 | B109: KN Accountantskosten | D109: 31618 | E109: 31660 | F109: 61669.95 | G109: 2612.6 | H109: =SUM(C109:G109) -> 127560.55
A110: 4310700 | B110: KN Administratiekosten | D110: 2420 | E110: 0 | F110: 2420 | G110: 2420 | H110: =SUM(C110:G110) -> 7260
A111: 4310800 | B111: KN Makelaarskosten | D111: 40646 | E111: 63411 | F111: 50119.65 | G111: 88242.28 | H111: =SUM(C111:G111) -> 242418.93
A112: 4311000 | B112: KN Juridische kosten | D112: 2261 | E112: 8170 | F112: 3422.05 | G112: 4094.49 | H112: =SUM(C112:G112) -> 17947.54
...

Sheet BDO - Q1-22
C1: Eindbalans per 31-03-2021 | D1: Mutaties Q2 2021 | E1: Mutaties Q3 2021 | F1: Mutaties Q4 2021 | G1: Mutaties Q1 2022 | H1: Saldi per 31-03-2022
A3: Balans
A4: 1600200 | B4: VG Vastgoedbeleggingen Verkrijgings- of vervaardigingsprijs | C4: 1.2567672e+08 | F4: =496000 -> 496000 | H4: =SUM(C4:G4) -> 1.2617272e+08 | I4: Aanpassing ivm jaarrekening: Nagekomen facturen 2021 vanuit Hoen | O4: 238485 | P4: 230282.95 | Q4: =694696.68-F4 -> 198696.68 | R4: 289183.25
A5: 1600200 | B5: VG Vastgoedbeleggingen Cum afschrijvingen en waardeverm | C5: -12070533 | D5: -667313 | E5: -666766 | F5: -679632 | G5: -682456 | H5: =SUM(C5:G5) -> -14766700
A6: 1610803 | B6: VG Comm VG in exploitatie Buitengebruikstellingen aanschaffingswaarde | C6: -706761 | D6: -1597299 | E6: -144749 | F6: -856186 | G6: -331590 | H6: =SUM(C6:G6) -> -3636585
A7: 1611003 | B7: VG Comm VG in exploitatie Buitengebruikstellingen cum. afschr. en waardeverm. | C7: 73789 | D7: 170229 | E7: 16814 | F7: 102659 | G7: 41047 | H7: =SUM(C7:G7) -> 404538
A8: Totaal Vastgoedbeleggingen | H8: =SUM(C8:G8) -> 0
A10: 1790002 | B10: FVA Latente belastingvordering langlopend | C10: 3706953 | D10: 120923 | E10: 161798 | F10: 273366.2 | G10: 237434 | H10: =SUM(C10:G10) -> 4500474.2 | I10: Aanpassing ivm jaarrekening: resultaat is aangepast, waardoor latentie ook
A11: Totaal Financiële vaste activa | H11: =SUM(C11:G11) -> 0
A13: 2000000 | B13: VOR Debiteuren | C13: -48068 | D13: 281344 | E13: =748301 -> 748301 | F13: -866992 | G13: -10254.87 | H13: =SUM(C13:G13) -> 104330.13
A14: 2000300 | B14: VOR Voorziening dubieuze debiteuren | C14: -31915 | D14: 0 | E14: 0 | F14: 0 | G14: 0 | H14: =SUM(C14:G14) -> -31915
A15: Totaal Debiteuren | H15: =SUM(C15:G15) -> 0
A17: 2640000 | B17: RC Kortlopend DMRRP INV - I BV | C17: -694061 | D17: 550984 | E17: 1407409 | F17: -1874859.4 | G17: 542643.28 | H17: =SUM(C17:G17) -> -67884.15 | I17: Aanpassing ivm jaarrekening: rente + boeking vpb
A18: Totaal Rekening-courant aandeelhouder | H18: =SUM(C18:G18) -> 0
A20: 2040200 | B20: VOR Te vorderen waarborgsommen kortlopen | C20: 5000 | D20: 0 | E20: 0 | F20: 0 | G20: 0 | H20: =SUM(C20:G20) -> 5000
A21: 2040500 | B21: VOR Vooruitbetaalde verzekeringen | C21: -14411 | D21: 70849 | E21: -28219.3 | F21: -28218.89 | G21: 0 | H21: =SUM(C21:G21) -> -0.19
A22: 2040700 | B22: VOR Vooruitbetaalde servicekosten | C22: 0 | D22: 0 | E22: 0 | F22: 1679.29 | G22: -1679 | H22: =SUM(C22:G22) -> 0.29
A23: 2040900 | B23: VOR Vooruitbetaalde overige kosten | C23: 198983.49 | D23: =-121928-129402.51 -> -251330.51 | E23: =-77180+388207.5 -> 311027.5 | F23: -258680.49 | G23: 220793.54 | H23: =SUM(C23:G23) -> 220793.53 | I23: Betreft vooruitbetaalde OZB/gemeentelijke belastingen 2022
A24: Totaal overige vorderingen | H24: =SUM(C24:G24) -> 0
A26: 2300000 | B26: LM Kruisposten | C26: -343 | D26: -3775.5 | E26: -12957.2 | F26: 17075.97 | G26: -281 | H26: =SUM(C26:G26) -> -280.73 | I26: Aanpassing ivm jaarrekening: afboeking rest kruisposten
A27: 2400200 | B27: LM ABN AMRO Bank Disposal NL58 ABNA 0818 9180 39 | C27: 0 | D27: 0 | E27: 0.91 | F27: -0.38 | G27: -0.37 | H27: =SUM(C27:G27) -> 0.16
A28: 2400201 | B28: LM ABN AMRO Bank Deposit NL57 ABNA 0541 6205 68 | C28: 36713 | D28: -19 | E28: -18.04 | F28: -18.04 | G28: -18.32 | H28: =SUM(C28:G28) -> 36639.6
A29: 2400202 | B29: LM ABN AMRO Bank General NL93 ABNA 0541 6132 27 | C29: 254345 | D29: -37180 | E29: -53403.02 | F29: -8084.34 | G29: -10036.05 | H29: =SUM(C29:G29) -> 145641.59
A30: 2400203 | B30: LM ABN AMRO Bank Maintres NL04 ABNA 0541 6188 06 | C30: 95782 | D30: 8473 | E30: 67284.68 | F30: -89675.55 | G30: -56453.47 | H30: =SUM(C30:G30) -> 25410.66
A31: 2400204 | B31: LM ABN AMRO Bank Rent NL46 ABNA 0541 6088 35 | C31: 1821558 | D31: -722443 | E31: -877600.44 | F31: 228072.92 | G31: 280038.53 | H31: =SUM(C31:G31) -> 729626.01
A32: 2400205 | B32: LM ABN AMRO Bank SR EXP NL88 ABNA 0541 6205 92 | C32: 113355 | D32: -72522 | E32: 32976.39 | F32: -48621.34 | G32: 84669.55 | H32: =SUM(C32:G32) -> 109857.6 | I32: =H13+H54 -> -7128.36
A33: Totaal Liquide middelen | H33: =SUM(C33:G33) -> 0
A35: 1000002 | B35: EV Normale aandelen Saldo | C35: -1 | D35: 0 | E35: 0 | F35: 0 | G35: 0 | H35: =SUM(C35:G35) -> -1
A36: 1100000 | B36: EV Agioreserve Agio aandelen | C36: -19231219 | D36: 200000 | E36: 0 | F36: 0 | G36: 0 | H36: =SUM(C36:G36) -> -19031219
A37: 1160000 | B37: EV Overige reserve Reserve aandelen | C37: 10426894 | D37: 0 | E37: 0 | F37: 0 | G37: 0 | H37: =SUM(C37:G37) -> 10426894
A38: 1160100 | B38: EV Overige reserve Dividenduitkeringen aandelen | D38: 2000000 | E38: 0 | F38: 1100000 | G38: 0 | H38: =SUM(C38:G38) -> 3100000
A39: Totaal Eigen vermogen | H39: =SUM(C39:G39) -> 0
A41: 1930001 | B41: LLS Hoofdsom ABN AMRO Bank NV Senior Facility Agreement | C41: -130000000 | D41: 0 | E41: 0 | F41: 0 | H41: =SUM(C41:G41) -> -130000000
A42: 1930101 | B42: LLS Cum aflossingen ABN AMRO Bank NV Senior Facility Agreement | C42: 21705853 | D42: 2253796 | E42: 889295.98 | F42: 1579957 | G42: 979503.98 | H42: =SUM(C42:G42) -> 27408406
A43: Totaal Langlopende schulden | H43: =SUM(C43:G43) -> 0
A45: 2730000 | B45: KLS Crediteuren | C45: -430271 | D45: 411485 | E45: 6778.95 | F45: -530169.95 | G45: -26012.24 | H45: =SUM(C45:G45) -> -568189.24 | I45: Aanpassing ivm jaarrekening: Nagekomen facturen 2021 vanuit Hoen
A46: 2730001 | B46: KLS Crediteuren intercompany | C46: 0 | D46: 0 | E46: 0 | F46: 0 | G46: -12100 | H46: =SUM(C46:G46) -> -12100
A47: Totaal Crediteuren | H47: =SUM(C47:G47) -> 0
A49: 2512100 | B49: BEL Afgedragen/ontvangen BTW | C49: 0 | D49: -3898 | E49: =-828.56+460 -> -368.56 | F49: -858.91 | G49: 525.91 | H49: =SUM(C49:G49) -> -4599.56
A50: 2530000 | B50: BEL Te betalen vennootschapsbelasting | C50: 0 | D50: 0 | E50: 0 | F50: 0 | G50: 0 | H50: =SUM(C50:G50) -> 0
A51: 2550000 | B51: BEL Te betalen overige belastingen | C51: 0 | D51: 0 | E51: 0 | F51: 0 | G51: 0 | H51: =SUM(C51:G51) -> 0
A52: Totaal Belastingen | H52: =SUM(C52:G52) -> 0
A54: 2740100 | B54: KLS Vooruitgefactureerde huur | D54: 0 | E54: -990960 | F54: 837333.62 | G54: 42167.89 | H54: =SUM(C54:G54) -> -111458.49
A55: 2740300 | B55: KLS Te betalen waarborgsommen kortlopend | C55: -761799 | D55: =-1404+2 -> -1402 | E55: -43086.2 | F55: -158.33 | G55: -10419.51 | H55: =SUM(C55:G55) -> -816865.04
A56: 2740500 | B56: KLS Te betalen accountants- en administratiekosten | C56: -22500 | D56: 0 | E56: 0 | F56: 0 | G56: 0 | H56: =SUM(C56:G56) -> -22500
A57: 2740600 | B57: KLS Te betalen rente | C57: 0 | D57: 0 | E57: 0 | F57: 0 | G57: 0 | H57: =SUM(C57:G57) -> 0
A58: 2740700 | B58: KLS Te betalen verzekeringen | C58: 0 | D58: 0 | E58: 0 | F58: 0 | H58: =SUM(C58:G58) -> 0
A59: 2741000 | B59: KLS Te betalen servicekosten | C59: 0 | D59: 0 | E59: 0 | F59: -13460 | G59: 13460 | H59: =SUM(C59:G59) -> 0 | I59: Aanpassing ivm jaarrekening: Overloop
A60: 2741001 | B60: KLS Te betalen exploitatiekosten | C60: 0 | D60: 0 | E60: 0 | F60: -1149.13 | G60: 1149 | H60: =SUM(C60:G60) -> -0.13 | I60: Aanpassing ivm jaarrekening: Overloop
A61: 2741002 | B61: KLS Te betalen VVE | C61: 0 | D61: 0 | E61: 0 | F61: -392.3 | G61: 392 | H61: =SUM(C61:G61) -> -0.3 | I61: Aanpassing ivm jaarrekening: Overloop
A62: 2741004 | B62: KLS Te betalen Hoen | C62: -124068 | D62: -122526 | E62: 121338.8 | F62: 84505.55 | G62: -40947 | H62: =SUM(C62:G62) -> -81696.65 | I62: Aanpassing ivm jaarrekening: Nagekomen facturen 2021 vanuit Hoen
A63: 2741005 | B63: KLS Te betalen managementvergoedingen | C63: 0 | D63: 0 | E63: 0 | F63: 0 | H63: =SUM(C63:G63) -> 0
A64: 2741200 | B64: KLS Te betalen agency fee | C64: 20000 | D64: -20000 | E64: 20000 | F64: 0 | G64: 0 | H64: =SUM(C64:G64) -> 20000
A65: 2741900 | B65: KLS Nog uit te zoeken posten MT940 | C65: 0 | D65: 0 | E65: 0 | F65: 0 | G65: 0 | H65: =SUM(C65:G65) -> 0
A66: 2742200 | B66: KLS Vooruitontvangen bedragen | C66: 0 | D66: 0 | E66: 0 | F66: 0 | G66: 0 | H66: =SUM(C66:G66) -> 0
A67: Totaal Overige schulden
A71: Winst- en verliesrekening (baten zijn positief, kosten negatief)
A72: 8000003 | B72: OPB Netto-omzet Theoretische huuropbrengsten | D72: -2863530 | E72: -2860507 | F72: -2862440.4 | G72: -2870089 | H72: =SUM(C72:G72) -> -11456566 | M72: -11456566 | N72: =M72-H72 -> 0
A73: 8000004 | B73: OPB Netto-omzet Leegstand huuropbrengsten | D73: 62447 | E73: 59646.21 | F73: 38520.4 | G73: 32888 | H73: =SUM(C73:G73) -> 193501.61 | I73: Aanpassing ivm jaarrekening | M73: 193501.61 | N73: =M73-H73 -> 0
A74: Totaal Netto-omzet | D74: =SUM(D72:D73) -> -2801083 | E74: =SUM(E72:E73) -> -2800860.8 | F74: =SUM(F72:F73) -> -2823920 | G74: =SUM(G72:G73) -> -2837201 | H74: =SUM(C74:G74) -> -11263065 | M74: -11263065 | N74: =M74-H74 -> 0
H75: =SUM(C75:G75) -> 0 | M75: 0 | N75: =M75-H75 -> 0
A76: 8400400 | B76: OPB Overige bedrijfsopbrengsten | D76: 0 | E76: 0 | F76: 13460 | G76: -13460 | H76: =SUM(C76:G76) -> 0 | I76: Aanpassing ivm jaarrekening: Overloop | M76: 0 | N76: =M76-H76 -> 0
A77: 8400600 | B77: OPB Overige bedrijfsopbrengsten Totale servicekosten | D77: -164913 | E77: -163178 | F77: -165060.65 | G77: -164313 | H77: =SUM(C77:G77) -> -657464.65 | M77: -657464.65 | N77: =M77-H77 -> 0
A78: 8400700 | B78: OPB Overige bedrijfsopbrengsten Servicekosten leegstand | D78: 5322 | E78: 6288.75 | F78: 5967.41 | G78: 1453 | H78: =SUM(C78:G78) -> 19031.16 | I78: Aanpassing ivm jaarrekening: Nagekomen facturen 2021 vanuit Hoen | M78: 19031.16 | N78: =M78-H78 -> 0
A79: 8400800 | B79: OPB Overige bedrijfsopbrengsten Gerealiseerde servicekosten | D79: 155500 | E79: 161869.1 | F79: 191429.47 | G79: 271928 | H79: =SUM(C79:G79) -> 780726.57 | M79: 780726.57 | N79: =M79-H79 -> 0
A80: Totaal Overige bedrijfsopbrengsten | D80: =SUM(D77:D79) -> -4091 | E80: =SUM(E77:E79) -> 4979.85 | F80: =SUM(F76:F79) -> 45796.23 | G80: =SUM(G76:G79) -> 95608 | H80: =SUM(C80:G80) -> 142293.08 | M80: 142293.08 | N80: =M80-H80 -> 0
N81: =M81-H81 -> 0
A82: 4051400 | B82: KN Diensten door derden | D82: 121422 | E82: 121881.5 | F82: 121294.6 | G82: 121679.68 | H82: =SUM(C82:G82) -> 486277.78 | M82: 486277.78 | N82: =M82-H82 -> 0
A83: Totaal overige personeelskosten | D83: =SUM(D82) -> 121422 | E83: =SUM(E82) -> 121881.5 | F83: =SUM(F82) -> 121294.6 | G83: =SUM(G82) -> 121679.68 | H83: =SUM(C83:G83) -> 486277.78 | M83: 486277.78 | N83: =M83-H83 -> 0
N84: =M84-H84 -> 0
A85: 4730000 | B85: AFKN Afschrijvingskosten Vastgoedbeleggingen | D85: 667313 | E85: 666766 | F85: 679632 | G85: 682456 | H85: =SUM(C85:G85) -> 2696167 | M85: 2696167 | N85: =M85-H85 -> 0
A86: 4730200 | B86: AFKN Boekresultaat Vastgoedbeleggingen | D86: -1978183 | E86: -222065 | F86: -1362473 | G86: -490457 | H86: =SUM(C86:G86) -> -4053178 | M86: -4053178 | N86: =M86-H86 -> 0
A87: Totaal Afschrijvingen vastgoedbeleggingen | D87: =SUM(D85:D86) -> -1310870 | E87: =SUM(E85:E86) -> 444701 | F87: =SUM(F85:F86) -> -682841 | G87: =SUM(G85:G86) -> 191999 | H87: =SUM(C87:G87) -> -1357011 | M87: -1357011 | N87: =M87-H87 -> 0
N88: =M88-H88 -> 0
A89: 4100400 | B89: KN Onderhoud gebouwen | D89: =194822+O4 -> 433307 | E89: =134619.1+P4 -> 364902.05 | F89: =510329.85+Q4 -> 709026.53 | G89: =178607+R4 -> 467790.25 | H89: =SUM(C89:G89) -> 1975025.8 | I89: Aanpassing ivm jaarrekening: Nagekomen facturen 2021 vanuit Hoen | M89: 1018377.9 | N89: =M89-H89 -> -956647.88
A90: 4100410 | B90: Verhuurdersheffing | D90: 129402.5 | E90: 129402.5 | F90: 129402.49 | G90: 127275 | H90: =SUM(C90:G90) -> 515482.49 | M90: 515482.49 | N90: =M90-H90 -> 0
A91: 4100900 | B91: KN Onroerende zaakbelasting | D91: 80091 | E91: 84680.21 | F91: 82972.46 | G91: 54979.46 | H91: =SUM(C91:G91) -> 302723.13 | M91: 302723.13 | N91: =M91-H91 -> 0
A92: 4101000 | B92: KN VvE-kosten | D92: 157568 | E92: 107779.2 | F92: 221370.06 | G92: 167096 | H92: =SUM(C92:G92) -> 653813.26 | I92: Aanpassing ivm jaarrekening: Nagekomen facturen 2021 vanuit Hoen | M92: 653813.26 | N92: =M92-H92 -> 0
A93: 4101010 | B93: Gemeentelijke belastingen | D93: 31441 | E93: 31288.14 | F93: 31086.75 | G93: 17584.71 | H93: =SUM(C93:G93) -> 111400.6 | M93: 111400.6 | N93: =M93-H93 -> 0
A94: 4101020 | B94: Waterschapsbelasting | D94: =1582+14862+69 -> 16513 | E94: =42842+9256-37236 -> 14862 | F94: 16030.14 | G94: 1077.52 | H94: =SUM(C94:G94) -> 48482.66 | M94: 48482.66 | N94: =M94-H94 -> 0
A95: 4101300 | B95: KN Servicekosten leegstand | D95: -348 | E95: 0 | F95: -22.71 | H95: =SUM(C95:G95) -> -370.71 | M95: -370.71 | N95: =M95-H95 -> 0
A96: 4109800 | B96: KN Overige huisvestingskosten | D96: 0 | E96: 0 | F96: 0 | H96: =SUM(C96:G96) -> 0 | M96: 0 | N96: =M96-H96 -> 0
A97: Totaal Huisvestingskosten | D97: =SUM(D89:D96) -> 847974.5 | E97: =SUM(E89:E96) -> 732914.1 | F97: =SUM(F89:F96) -> 1189865.7 | G97: =SUM(G89:G96) -> 835802.94 | H97: =SUM(C97:G97) -> 3606557.3 | M97: 2649909.4 | N97: =M97-H97 -> -956647.88
N98: =M98-H98 -> 0
A99: 4500400 | B99: KN Representatiekosten | D99: 0 | E99: 0 | F99: 0 | N99: =M99-H99 -> 0
A100: 4501200 | B100: KN Mutatie voorziening dubieuze debiteuren | D100: 0 | E100: 0 | F100: 0 | H100: =SUM(C100:G100) -> 0 | M100: 0 | N100: =M100-H100 -> 0
A101: 4501300 | B101: KN Afboeking dubieuze debiteuren | D101: -2606 | E101: 461 | F101: 238.16 | G101: -3681 | H101: =SUM(C101:G101) -> -5587.84 | I101: Aanpassing ivm jaarrekening: Nagekomen facturen 2021 vanuit Hoen | M101: -5587.84 | N101: =M101-H101 -> 0
A102: Totaal Verkoopkosten | D102: =SUM(D99:D101) -> -2606 | E102: =SUM(E99:E101) -> 461 | F102: =SUM(F99:F101) -> 238.16 | G102: =SUM(G99:G101) -> -3681 | H102: =SUM(C102:G102) -> -5587.84 | M102: -5587.84 | N102: =M102-H102 -> 0
N103: =M103-H103 -> 0
A104: 4300500 | B104: KN Incassokosten | D104: 300 | E104: 300 | F104: 340 | G104: 307 | H104: =SUM(C104:G104) -> 1247 | M104: 1247 | N104: =M104-H104 -> 0
A105: Totaal Kantoorkosten | D105: =SUM(D104) -> 300 | E105: =SUM(E104) -> 300 | F105: =SUM(F104) -> 340 | G105: =SUM(G104) -> 307 | H105: =SUM(C105:G105) -> 1247 | M105: 1247 | N105: =M105-H105 -> 0
N106: =M106-H106 -> 0
A107: 4310000 | B107: KN Abonnementen en contributies | D107: 0 | E107: 0 | F107: 0 | H107: =SUM(C107:G107) -> 0 | M107: 0 | N107: =M107-H107 -> 0
A108: 4310400 | B108: KN Assurantiepremie algemeen | D108: 28130 | E108: 28219.25 | F108: 29692.1 | G108: 377.53 | H108: =SUM(C108:G108) -> 86418.88 | M108: 86418.88 | N108: =M108-H108 -> 0
A109: 4310500 | B109: KN Managementvergoeding | D109: 5445 | E109: 5445 | F109: 5445 | G109: 5445 | H109: =SUM(C109:G109) -> 21780 | M109: 21780 | N109: =M109-H109 -> 0
A110: 4310600 | B110: KN Accountantskosten | D110: 31660 | E110: 61669.95 | F110: 2612.6 | G110: 4564 | H110: =SUM(C110:G110) -> 100506.55 | M110: 100506.55 | N110: =M110-H110 -> 0
A111: 4310700 | B111: KN Administratiekosten | D111: 0 | E111: 2420 | F111: 2420 | H111: =SUM(C111:G111) -> 4840 | M111: 4840 | N111: =M111-H111 -> 0
A112: 4310800 | B112: KN Makelaarskosten | D112: 63411 | E112: 50119.65 | F112: 94401.18 | G112: 41825 | H112: =SUM(C112:G112) -> 249756.83 | I112: Aanpassing ivm jaarrekening: Nagekomen facturen 2021 vanuit Hoen | M112: 249756.83 | N112: =M112-H112 -> 0
A113: 4311000 | B113: KN Juridische kosten | D113: 8170 | E113: 3422.05 | F113: 4699.49 | G113: 901 | H113: =SUM(C113:G113) -> 17192.54 | I113: Aanpassing ivm jaarrekening: Nagekomen facturen 2021 vanuit Hoen | M113: 17192.54 | N113: =M113-H113 -> 0
A114: 4311800 | B114: KN Advieskosten | D114: 0 | E114: 0 | F114: 0 | G114: 12100 | H114: =SUM(C114:G114) -> 12100 | M114: 12100 | N114: =M114-H114 -> 0
...

Sheet BDO - Q2-22
C1: Eindbalans per 30-06-2021 | D1: Mutaties Q3 2021 | E1: Mutaties Q4 2021 | F1: Mutaties Q1 2022 | G1: Mutaties Q2 2022 | H1: Saldi per 30-06-2022
A3: Balans
A4: 1600000 | B4: VG Vastgoedbeleggingen Verkrijgings- of vervaardigingsprijs | C4: 1.2591521e+08 | E4: 496000 | H4: =SUM(C4:G4) -> 1.2641121e+08 | L4: 230282.95 | M4: 198696.68 | N4: 289183.25 | O4: 291783.9
A5: 1600200 | B5: VG Vastgoedbeleggingen Cum afschrijvingen en waardeverm | C5: -12737846 | D5: -666766 | E5: -679632 | F5: -682456 | G5: -682714 | H5: =SUM(C5:G5) -> -15449414
A6: 1610803 | B6: VG Comm VG in exploitatie Buitengebruikstellingen aanschaffingswaarde | C6: -2304060 | D6: -144749 | E6: -856186 | F6: -331590 | G6: -276183 | H6: =SUM(C6:G6) -> -3912768
A7: 1611003 | B7: VG Comm VG in exploitatie Buitengebruikstellingen cum. afschr. en waardeverm. | C7: 244018 | D7: 16814 | E7: 102659 | F7: 41047 | G7: 36141 | H7: =SUM(C7:G7) -> 440679
A8: Totaal Vastgoedbeleggingen | C8: 0 | H8: =SUM(C8:F8) -> 0
C9: 0
A10: 1790002 | B10: FVA Latente belastingvordering langlopend | C10: 3827876 | D10: 161798 | E10: 273366.2 | F10: 237434 | G10: 121126 | H10: =SUM(C10:G10) -> 4621600.2
A11: Totaal Financiële vaste activa | C11: 0 | H11: =SUM(C11:F11) -> 0
C12: 0
A13: 2000000 | B13: VOR Debiteuren | C13: 233276 | D13: 748299.62 | E13: -866992 | F13: -10254.87 | G13: -9192.36 | H13: =SUM(C13:G13) -> 95136.39
A14: 2000300 | B14: VOR Voorziening dubieuze debiteuren | C14: -31915 | D14: 0 | E14: -59966.86 | F14: 0 | G14: 0 | H14: =SUM(C14:G14) -> -91881.86 | I14: Correctie nav definitieve jaarrekening
A15: Totaal Debiteuren | C15: 0 | H15: =SUM(C15:F15) -> 0
A17: 2640000 | B17: RC Kortlopend DMRRP INV - I BV | C17: -143077 | D17: 1407409 | E17: -1860053.4 | F17: 542643.28 | G17: 1293310.9 | H17: =SUM(C17:G17) -> 1240232.8 | I17: Correctie nav definitieve jaarrekening
A18: Totaal Rekening-courant aandeelhouder | C18: 0 | H18: =SUM(C18:F18) -> 0
C19: 0
A20: 2040200 | B20: VOR Te vorderen waarborgsommen kortlopen | C20: 5000 | D20: 0 | E20: 0 | F20: 0 | G20: 0 | H20: =SUM(C20:G20) -> 5000
A21: 2040500 | B21: VOR Vooruitbetaalde verzekeringen | C21: 56438 | D21: -28219.3 | E21: -28218.89 | F21: -29220.54 | G21: 87661.64 | H21: =SUM(C21:G21) -> 58440.91 | I21: Verdelen verzekering over heel 2022
A22: 2040700 | B22: VOR Vooruitbetaalde servicekosten | C22: 0 | D22: 0 | E22: 1679.29 | F22: -1679 | G22: 0 | H22: =SUM(C22:G22) -> 0.29
A23: 2040900 | B23: VOR Vooruitbetaalde overige kosten | C23: -52347.02 | D23: =-77180+388207.5 -> 311027.5 | E23: -258680.49 | F23: 302583.68 | G23: -64419.13 | H23: =SUM(C23:G23) -> 238164.54 | I23: Kosten verdelen over heel 2022
A24: Totaal overige vorderingen | C24: 0 | H24: =SUM(C24:F24) -> 0
C25: 0
A26: 2300000 | B26: LM Kruisposten | C26: -4118.5 | D26: -12957.2 | E26: 17075.97 | F26: -281 | G26: -1981.76 | H26: =SUM(C26:G26) -> -2262.49
A27: 2400200 | B27: LM ABN AMRO Bank Disposal NL58 ABNA 0818 9180 39 | C27: 0 | D27: 0.91 | E27: -0.38 | F27: -0.37 | G27: 0.1 | H27: =SUM(C27:G27) -> 0.26
A28: 2400201 | B28: LM ABN AMRO Bank Deposit NL57 ABNA 0541 6205 68 | C28: 36694 | D28: -18.04 | E28: -18.04 | F28: -18.32 | G28: -18.48 | H28: =SUM(C28:G28) -> 36621.12
A29: 2400202 | B29: LM ABN AMRO Bank General NL93 ABNA 0541 6132 27 | C29: 217165 | D29: -53403.02 | E29: -8084.34 | F29: -10036.05 | G29: -95658.58 | H29: =SUM(C29:G29) -> 49983.01
A30: 2400203 | B30: LM ABN AMRO Bank Maintres NL04 ABNA 0541 6188 06 | C30: 104255 | D30: 67284.68 | E30: -89675.55 | F30: -56453.47 | G30: 17670.91 | H30: =SUM(C30:G30) -> 43081.57
A31: 2400204 | B31: LM ABN AMRO Bank Rent NL46 ABNA 0541 6088 35 | C31: 1099115 | D31: -877600.44 | E31: 228072.92 | F31: 280038.53 | G31: 367648.53 | H31: =SUM(C31:G31) -> 1097274.5
A32: 2400205 | B32: LM ABN AMRO Bank SR EXP NL88 ABNA 0541 6205 92 | C32: 40833 | D32: 32976.39 | E32: -48621.34 | F32: 84669.55 | G32: -105672.08 | H32: =SUM(C32:G32) -> 4185.52
A33: Totaal Liquide middelen | C33: 0 | H33: =SUM(C33:F33) -> 0
C34: 0
A35: 1000002 | B35: EV Normale aandelen Saldo | C35: -1 | D35: 0 | E35: 0 | F35: 0 | G35: 0 | H35: =SUM(C35:G35) -> -1
A36: 1100000 | B36: EV Agioreserve Agio aandelen | C36: -19031219 | D36: 0 | E36: 100000 | F36: 0 | G36: 0 | H36: =SUM(C36:G36) -> -18931219 | I36: Correctie nav definitieve jaarrekening
A37: 1160000 | B37: EV Overige reserve Reserve aandelen | C37: 7620034.1 | D37: 0 | E37: 0 | F37: 0 | G37: 0 | H37: =SUM(C37:G37) -> 7620034.1
A38: 1160100 | B38: EV Overige reserve Dividenduitkeringen aandelen | C38: 2000000 | D38: 0 | E38: 1000000 | F38: 0 | G38: 0 | H38: =SUM(C38:G38) -> 3000000 | I38: Correctie nav definitieve jaarrekening
A39: Totaal Eigen vermogen | C39: 0 | H39: =SUM(C39:F39) -> 0
C40: 0
A41: 1930001 | B41: LLS Hoofdsom ABN AMRO Bank NV Senior Facility Agreement | C41: -130000000 | D41: 0 | E41: 0 | G41: 0 | H41: =SUM(C41:G41) -> -130000000
A42: 1930101 | B42: LLS Cum aflossingen ABN AMRO Bank NV Senior Facility Agreement | C42: 23959649 | D42: 889295.98 | E42: 1579957 | F42: 979503.98 | G42: 948219.98 | H42: =SUM(C42:G42) -> 28356626
A43: Totaal Langlopende schulden | C43: 0 | H43: =SUM(C43:F43) -> 0
C44: 0
A45: 2730000 | B45: KLS Crediteuren | C45: -18786 | D45: 6778.95 | E45: -530169.95 | F45: -26012.24 | G45: 394615.53 | H45: =SUM(C45:G45) -> -173573.71
A46: 2730001 | B46: KLS Crediteuren intercompany | C46: 0 | D46: 0 | E46: 0 | F46: -12100 | G46: 0 | H46: =SUM(C46:G46) -> -12100
A47: Totaal Crediteuren | C47: 0 | H47: =SUM(C47:F47) -> 0
C48: 0
A49: 2512100 | B49: BEL Afgedragen/ontvangen BTW | C49: -3898 | D49: =-828.56+460 -> -368.56 | E49: -858.91 | F49: 525.91 | G49: 101.01 | H49: =SUM(C49:G49) -> -4498.55
A50: 2530000 | B50: BEL Te betalen vennootschapsbelasting | C50: 0 | D50: 0 | E50: 0 | F50: 0 | G50: 0 | H50: =SUM(C50:G50) -> 0
A51: 2550000 | B51: BEL Te betalen overige belastingen | C51: 0 | D51: 0 | E51: 0 | F51: 0 | G51: 0 | H51: =SUM(C51:G51) -> 0
A52: Totaal Belastingen | C52: 0 | H52: =SUM(C52:F52) -> 0
C53: 0
A54: 2740100 | B54: KLS Vooruitgefactureerde huur | C54: 0 | D54: -990959.87 | E54: 837333.62 | F54: 42167.89 | G54: -796644.01 | H54: =SUM(C54:G54) -> -908102.37
A55: 2740300 | B55: KLS Te betalen waarborgsommen kortlopend | C55: -763201 | D55: -43086.2 | E55: -158.33 | F55: -10419.51 | G55: -23268.06 | H55: =SUM(C55:G55) -> -840133.1
A56: 2740500 | B56: KLS Te betalen accountants- en administratiekosten | C56: -22500 | D56: 0 | E56: 0 | F56: 0 | G56: 0 | H56: =SUM(C56:G56) -> -22500
A57: 2740600 | B57: KLS Te betalen rente | C57: 0 | D57: 0 | E57: 0 | F57: 0 | G57: 0 | H57: =SUM(C57:G57) -> 0
A58: 2740700 | B58: KLS Te betalen verzekeringen | C58: 0 | D58: 0 | E58: 0 | F58: 0 | G58: 0 | H58: =SUM(C58:G58) -> 0
A59: 2741000 | B59: KLS Te betalen servicekosten | C59: 0 | D59: 0 | E59: -13460 | F59: 13460 | G59: 0 | H59: =SUM(C59:G59) -> 0
A60: 2741001 | B60: KLS Te betalen exploitatiekosten | C60: 0 | D60: 0 | E60: -1149.13 | F60: 1149 | G60: 0 | H60: =SUM(C60:G60) -> -0.13
A61: 2741002 | B61: KLS Te betalen VVE | C61: 0 | D61: 0 | E61: -392.3 | F61: 392 | G61: 0 | H61: =SUM(C61:G61) -> -0.3
A62: 2741004 | B62: KLS Te betalen Hoen | C62: -246594 | D62: 121338.8 | E62: 84505.55 | F62: -40947 | G62: -123710.23 | H62: =SUM(C62:G62) -> -205406.88
A63: 2741005 | B63: KLS Te betalen managementvergoedingen | C63: 0 | D63: 0 | E63: 0 | F63: 0 | G63: 0 | H63: =SUM(C63:G63) -> 0
A64: 2741200 | B64: KLS Te betalen agency fee | C64: 0 | D64: 20000 | E64: 0 | F64: 0 | G64: -20000 | H64: =SUM(C64:G64) -> 0
A65: 2741900 | B65: KLS Nog uit te zoeken posten MT940 | C65: 0 | D65: 0 | E65: 0 | F65: 0 | G65: 0 | H65: =SUM(C65:G65) -> 0
A66: 2742200 | B66: KLS Vooruitontvangen bedragen | C66: 0 | D66: 0 | E66: 0 | F66: 0 | G66: 0 | H66: =SUM(C66:G66) -> 0
A67: Totaal Overige schulden
A71: Winst- en verliesrekening (baten zijn positief, kosten negatief)
A72: 8000003 | B72: OPB Netto-omzet Theoretische huuropbrengsten | D72: -2860507 | E72: -2862440.4 | F72: -2870089 | G72: -2871329.2 | H72: =SUM(C72:G72) -> -11464366
A73: 8000004 | B73: OPB Netto-omzet Leegstand huuropbrengsten | D73: 59646.21 | E73: 38520.4 | F73: 32888 | G73: 39968.65 | H73: =SUM(C73:G73) -> 171023.26
A74: Totaal Netto-omzet | D74: =SUM(D72:D73) -> -2800860.8 | E74: =SUM(E72:E73) -> -2823920 | F74: =SUM(F72:F73) -> -2837201 | G74: =SUM(G72:G73) -> -2831360.5 | H74: =SUM(C74:G74) -> -11293342
A76: 8400400 | B76: OPB Overige bedrijfsopbrengsten | D76: 0 | E76: 13460 | F76: -13460 | G76: 0 | H76: =SUM(C76:G76) -> 0
A77: 8400600 | B77: OPB Overige bedrijfsopbrengsten Totale servicekosten | D77: -163178 | E77: -165060.65 | F77: -164313 | G77: -164598.62 | H77: =SUM(C77:G77) -> -657150.27
A78: 8400700 | B78: OPB Overige bedrijfsopbrengsten Servicekosten leegstand | D78: 6288.75 | E78: 5967.41 | F78: 1453 | G78: 6011.91 | H78: =SUM(C78:G78) -> 19721.07
A79: 8400800 | B79: OPB Overige bedrijfsopbrengsten Gerealiseerde servicekosten | D79: 161869.1 | E79: 191429.47 | F79: 271928 | G79: 195259.97 | H79: =SUM(C79:G79) -> 820486.54
A80: Totaal Overige bedrijfsopbrengsten | D80: =SUM(D77:D79) -> 4979.85 | E80: =SUM(E76:E79) -> 45796.23 | F80: =SUM(F76:F79) -> 95608 | G80: =SUM(G76:G79) -> 36673.26 | H80: =SUM(C80:G80) -> 183057.34
A82: 4051400 | B82: KN Diensten door derden | D82: 121881.5 | E82: 121294.6 | F82: 121679.68 | G82: 121956.77 | H82: =SUM(C82:G82) -> 486812.55
A83: Totaal overige personeelskosten | D83: =SUM(D82) -> 121881.5 | E83: =SUM(E82) -> 121294.6 | F83: =SUM(F82) -> 121679.68 | G83: =SUM(G82) -> 121956.77 | H83: =SUM(C83:G83) -> 486812.55
A85: 4730000 | B85: AFKN Afschrijvingskosten Vastgoedbeleggingen | D85: 666766 | E85: 679632 | F85: 682456 | G85: 682714 | H85: =SUM(C85:G85) -> 2711568
A86: 4730200 | B86: AFKN Boekresultaat Vastgoedbeleggingen | D86: -222065 | E86: -1362473 | F86: -490457 | G86: -423958 | H86: =SUM(C86:G86) -> -2498953
A87: Totaal Afschrijvingen vastgoedbeleggingen | D87: =SUM(D85:D86) -> 444701 | E87: =SUM(E85:E86) -> -682841 | F87: =SUM(F85:F86) -> 191999 | G87: =SUM(G85:G86) -> 258756 | H87: =SUM(C87:G87) -> 212615
A89: 4100400 | B89: KN Onderhoud gebouwen | D89: =134619.1+L4 -> 364902.05 | E89: =510329.85+M4 -> 709026.53 | F89: =178607+N4 -> 467790.25 | G89: =230456.52+O4 -> 522240.42 | H89: =SUM(C89:G89) -> 2063959.2
A90: 4100410 | B90: Verhuurdersheffing | D90: 129402.5 | E90: 129402.49 | F90: 31818.72 | G90: 31818.72 | H90: =SUM(C90:G90) -> 322442.43 | I90: Kosten verdelen over heel 2022
A91: 4100900 | B91: KN Onroerende zaakbelasting | D91: 84680.21 | E91: 82972.46 | F91: 54979.46 | G91: 61017.04 | H91: =SUM(C91:G91) -> 283649.17
A92: 4101000 | B92: KN VvE-kosten | D92: 107779.2 | E92: 221370.06 | F92: 167096 | G92: 146899.4 | H92: =SUM(C92:G92) -> 643144.66
A93: 4101010 | B93: Gemeentelijke belastingen | D93: 31288.14 | E93: 31086.75 | F93: 17584.71 | G93: 22504.3 | H93: =SUM(C93:G93) -> 102463.9
A94: 4101020 | B94: Waterschapsbelasting | D94: =42842+9256-37236 -> 14862 | E94: 16030.14 | F94: 14743.33 | G94: 24087.56 | H94: =SUM(C94:G94) -> 69723.03 | I94: Kosten verdelen over heel 2022
A95: 4101300 | B95: KN Servicekosten leegstand | D95: 0 | E95: -22.71 | G95: 0 | H95: =SUM(C95:G95) -> -22.71
A96: 4109800 | B96: KN Overige huisvestingskosten | D96: 0 | E96: 0 | G96: 0 | H96: =SUM(C96:G96) -> 0
A97: Totaal Huisvestingskosten | D97: =SUM(D89:D96) -> 732914.1 | E97: =SUM(E89:E96) -> 1189865.7 | F97: =SUM(F89:F96) -> 754012.47 | G97: =SUM(G89:G96) -> 808567.44 | H97: =SUM(C97:G97) -> 3485359.7
A99: 4500400 | B99: KN Representatiekosten | D99: 0 | E99: 0 | H99: =SUM(C99:G99) -> 0
A100: 4501200 | B100: KN Mutatie voorziening dubieuze debiteuren | D100: 0 | E100: 59966.86 | H100: =SUM(C100:G100) -> 59966.86
A101: 4501300 | B101: KN Afboeking dubieuze debiteuren | D101: 461 | E101: 238.16 | F101: -3681 | G101: 1678.58 | H101: =SUM(C101:G101) -> -1303.26
A102: Totaal Verkoopkosten | D102: =SUM(D99:D101) -> 461 | E102: =SUM(E99:E101) -> 60205.02 | F102: =SUM(F99:F101) -> -3681 | G102: =SUM(G99:G101) -> 1678.58 | H102: =SUM(C102:G102) -> 58663.6
A104: 4300500 | B104: KN Incassokosten | D104: 300 | E104: 340 | F104: 307 | G104: 300 | H104: =SUM(C104:G104) -> 1247
A105: Totaal Kantoorkosten | D105: =SUM(D104) -> 300 | E105: =SUM(E104) -> 340 | F105: =SUM(F104) -> 307 | G105: =SUM(G104) -> 300 | H105: =SUM(C105:G105) -> 1247
A107: 4310000 | B107: KN Abonnementen en contributies | D107: 0 | E107: 0 | F107: 0 | G107: 0 | H107: =SUM(C107:G107) -> 0
A108: 4310400 | B108: KN Assurantiepremie algemeen | D108: 28219.25 | E108: 29692.1 | F108: 29598.07 | G108: 29220.54 | H108: =SUM(C108:G108) -> 116729.96 | I108: Verdelen verzekering over heel 2022
A109: 4310500 | B109: KN Managementvergoeding | D109: 5445 | E109: 5445 | F109: 5445 | G109: 1815 | H109: =SUM(C109:G109) -> 18150
A110: 4310600 | B110: KN Accountantskosten | D110: 61669.95 | E110: 2612.6 | F110: 4564 | G110: 17202.63 | H110: =SUM(C110:G110) -> 86049.18
A111: 4310700 | B111: KN Administratiekosten | D111: 2420 | E111: 2420 | G111: 2420 | H111: =SUM(C111:G111) -> 7260
A112: 4310800 | B112: KN Makelaarskosten | D112: 50119.65 | E112: 94401.18 | F112: 41825 | G112: 56676.4 | H112: =SUM(C112:G112) -> 243022.23
...

Sheet BDO - Q3-22
C1: Eindbalans per 30-09-2021 | D1: Mutaties Q4 2021 | E1: Mutaties Q1 2022 | F1: Mutaties Q2 2022 | G1: Mutaties Q3 2022 | H1: Saldi per 30-09-2022
A3: Balans
A4: 1600000 | B4: VG Vastgoedbeleggingen Verkrijgings- of vervaardigingsprijs | C4: 1.2614549e+08 | D4: 496000 | H4: =SUM(C4:G4) -> 1.2664149e+08 | J4: 198696.68 | K4: 289183.25 | L4: 291783.9 | M4: 243593.77
A5: 1600200 | B5: VG Vastgoedbeleggingen Cum afschrijvingen en waardeverm | C5: -13404612 | D5: -679632 | E5: -682456 | F5: -682714 | G5: -695326 | H5: =SUM(C5:G5) -> -16144740
A6: 1610803 | B6: VG Comm VG in exploitatie Buitengebruikstellingen aanschaffingswaarde | C6: -2448809 | D6: -856186 | E6: -331590 | F6: -276183 | G6: -363436 | H6: =SUM(C6:G6) -> -4276204
A7: 1611003 | B7: VG Comm VG in exploitatie Buitengebruikstellingen cum. afschr. en waardeverm. | C7: 260832 | D7: 102659 | E7: 41047 | F7: 36141 | G7: 49532 | H7: =SUM(C7:G7) -> 490211
A8: Totaal Vastgoedbeleggingen | C8: 0 | H8: =SUM(C8:G8) -> 0
C9: 0 | H9: =SUM(C9:G9) -> 0
A10: 1790002 | B10: FVA Latente belastingvordering langlopend | C10: 3989674 | D10: 273366.2 | E10: 237434 | F10: 121126 | G10: 165568 | H10: =SUM(C10:G10) -> 4787168.2
A11: Totaal Financiële vaste activa | C11: 0 | H11: =SUM(C11:G11) -> 0
C12: 0 | H12: =SUM(C12:G12) -> 0
A13: 2000000 | B13: VOR Debiteuren | C13: 981575.62 | D13: -866992 | E13: -10254.87 | F13: -9192.36 | G13: 1191082.2 | H13: =SUM(C13:G13) -> 1286218.5
A14: 2000300 | B14: VOR Voorziening dubieuze debiteuren | C14: -31915 | D14: -59966.86 | E14: 0 | F14: 0 | G14: 0 | H14: =SUM(C14:G14) -> -91881.86
A15: Totaal Debiteuren | C15: 0 | H15: =SUM(C15:G15) -> 0
C16: 0 | H16: =SUM(C16:G16) -> 0
A17: 2640000 | B17: RC Kortlopend DMRRP INV - I BV | C17: 1264332 | D17: -1860053.4 | E17: 542643.28 | F17: 1293310.9 | G17: 570839.92 | H17: =SUM(C17:G17) -> 1811072.7
A18: Totaal Rekening-courant aandeelhouder | C18: 0 | H18: =SUM(C18:G18) -> 0
C19: 0 | H19: =SUM(C19:G19) -> 0
A20: 2040200 | B20: VOR Te vorderen waarborgsommen kortlopen | C20: 5000 | D20: 0 | E20: 0 | F20: 0 | G20: 0 | H20: =SUM(C20:G20) -> 5000
A21: 2040500 | B21: VOR Vooruitbetaalde verzekeringen | C21: 28218.7 | D21: -28218.89 | E21: -29220.54 | F21: 87661.64 | G21: -29220.56 | H21: =SUM(C21:G21) -> 29220.35
A22: 2040700 | B22: VOR Vooruitbetaalde servicekosten | C22: 0 | D22: 1679.29 | E22: -1679 | F22: 0 | G22: 0 | H22: =SUM(C22:G22) -> 0.29
